Workbook

Sheet Maestra
A1: Correo del candidato | B1: Nombre del candidato | C1: Tipo de identificación | D1: Número de documento de identificación | E1: Género con el que te identificas | F1: ¿Cuál es tu edad? | G1: ¿Actualmente estás cursando un pregrado universitario? | H1: Ciudad en la que resides actualmente | I1: Lugar en el que estarías dispuesto/a a realizar tus prácticas | J1: A que universidad perteneces | K1: ¿Cuál?. | L1: Nombre del programa académico | M1: ¿Cuál? | N1: ¿Debes cursar asignaturas durante la realización de tus prácticas? | O1: ¿Anteriormente ha tenido vinculación como aprendiz SENA? | P1: Nivel de inglés | Q1: Nivel de manejo de Excel | R1: Primer área de interés para realizar la práctica | S1: Vacantes Producción (Operaciones) | T1: Vacantes Finanzas | U1: Vacantes Talento | V1: Vacantes Ventas | W1: Segunda área de interés para realizar la práctica | X1: Vacantes Producción (Operaciones)2 | Y1: Vacantes Finanzas3 | Z1: Vacantes Talento4 | AA1: Vacantes Ventas5 | AB1: ¿Has trabajado anteriormente para nuestra compañía? | AC1: ¿Tienes algún familiar laborado con la compañía? | AD1: Si tu respuesta fue "Sí", indica el parentesco y nombre completo (Ejemplo: Madre – Rosa Elena Medina Delgado): | AE1: ¿Tienes algún familiar que sea o labore con un proveedor de la compañía? | AF1: Si tu respuesta fue "Sí", indica e parentesco y nombre completo (Ejemplo: Madre - Rosa Elena Medina Delgado): | AG1: ¿Tienes algún familiar que sea o labore con un cliente de la compañía? | AH1: Si tu respuesta fue "Sí", indica el parentesco y nombre completo (Ejemplo: Madre - Rosa Elena Medina Delgado): | AI1: ¿Tienes algún familiar que sea o labore con la competencia de la compañía? | AJ1: Si tu respuesta fue "Sí", indica el parentesco y nombre completo (Ejemplo: Madre - Rosa Elena Medina Delgado): | AK1: ¿Por qué medio te enteraste de nuestra convocatoria? | AL1: Nombre de la etapa | AM1: Día | AN1: Hora | AO1: Teléfono | AP1: Dirección | AQ1: Magneto ERI | AR1: Magneto % | AS1: Encargado | AT1: Vacante sugerida | AU1: Confirmación | AV1: Comentarios | AW1: Carrera | AX1: Teléfono contacto | AY1: Site | AZ1: Fecha creatón | BA1: Horario creatón
A2: jepr.240505@gmail.com | B2: Juan Esteban Paez Ruiz | C2: Cédula de ciudadanía | D2: 1031641933 | E2: Hombre | F2: 22 | G2: TRUE | I2: Bogotá | J2: Universidad del Bosque | L2: Estadística | N2: TRUE | O2: FALSE | P2: Intermedio | Q2: Avanzado | R2: Tecnología | U2: Área financiera | W2: Talento | AB2: FALSE | AC2: FALSE | AE2: FALSE | AG2: FALSE | AI2: FALSE | AK2: LinkedIn | AL2: CREATÓN | AM2: 46278 | AN2: 0.80265046 | AO2: 310 3824756 | AP2: Calle 83 103C-55, 111011 Bogota, D.C., Colombia | AQ2: DP | AR2: 74.5 | AS2: Cata | AT2: Area financiera (PPM) | AU2: NO | AV2: OK | AW2: =IF(L2="Otra",IF(M2="","Otra",M2&""),L2&"") -> Estadística | AX2: =IF(OR(AO2="",AO2=0),"",TRIM(AO2)) -> 310 3824756 | AY2: =IFERROR(INDEX(Vacantes!$C:$C,MATCH(AT2,Vacantes!$A:$A,0)),"") -> 127 | AZ2: =IFERROR(INDEX(Vacantes!$D:$D,MATCH(AT2,Vacantes!$A:$A,0)),"") -> 13 de octubre de 2026 | BA2: =IFERROR(INDEX(Vacantes!$E:$E,MATCH(AT2,Vacantes!$A:$A,0)),"") -> 7:30 a.m. a 11:30 a.m.
A3: gabrielalopezp5@gmail.com | B3: Gabriela Lopez | C3: Cédula de ciudadanía | D3: 1034516871 | E3: Mujer | F3: 21 | G3: TRUE | H3: BOGOTÁ | I3: Bogotá | J3: Universidad de los Andes | L3: Economía | N3: FALSE | O3: FALSE | P3: Avanzado | Q3: Intermedio | R3: Finanzas | W3: Compras | Y3: Finanzas Impuestos | AB3: FALSE | AC3: FALSE | AE3: FALSE | AG3: FALSE | AI3: FALSE | AK3: LinkedIn | AL3: CREATÓN | AM3: 46265 | AN3: 0.56325231 | AO3: 316 2398383 | AP3: Calle 84 9-85, 110221 Bogota, D.C., Colombia | AQ3: DP | AR3: 79.7 | AS3: Santi | AT3: Area financiera (PPM) | AU3: NO | AV3: OK | AW3: =IF(L3="Otra",IF(M3="","Otra",M3&""),L3&"") -> Economía | AX3: =IF(OR(AO3="",AO3=0),"",TRIM(AO3)) -> 316 2398383 | AY3: =IFERROR(INDEX(Vacantes!$C:$C,MATCH(AT3,Vacantes!$A:$A,0)),"") -> 127 | AZ3: =IFERROR(INDEX(Vacantes!$D:$D,MATCH(AT3,Vacantes!$A:$A,0)),"") -> 13 de octubre de 2026 | BA3: =IFERROR(INDEX(Vacantes!$E:$E,MATCH(AT3,Vacantes!$A:$A,0)),"") -> 7:30 a.m. a 11:30 a.m.
A4: mateo.fontecha@outlook.com | B4: Mateo Fontecha | C4: Cédula de ciudadanía | D4: 1000364978 | E4: Hombre | F4: 25 | G4: TRUE | H4: BOGOTA | I4: Bogotá | J4: Universidad de los Andes | L4: Economía | N4: FALSE | O4: FALSE | P4: Avanzado | Q4: Intermedio | R4: Finanzas | W4: Asuntos Corporativos | Y4: Finanzas Impuestos | AB4: FALSE | AC4: FALSE | AE4: FALSE | AG4: FALSE | AI4: FALSE | AK4: LinkedIn | AL4: CREATÓN | AM4: 46266 | AN4: 0.45931713 | AO4: 0 | AP4: Carrera 52A 57B-33, 111321 Bogota, D.C., Colombia | AQ4: DP | AR4: 89.6 | AS4: Cata | AT4: Asuntos Corporativos | AU4: NO | AV4: OK | AW4: =IF(L4="Otra",IF(M4="","Otra",M4&""),L4&"") -> Economía | AX4: =IF(OR(AO4="",AO4=0),"",TRIM(AO4)) | AY4: =IFERROR(INDEX(Vacantes!$C:$C,MATCH(AT4,Vacantes!$A:$A,0)),"") -> 127 | AZ4: =IFERROR(INDEX(Vacantes!$D:$D,MATCH(AT4,Vacantes!$A:$A,0)),"") -> 13 de octubre de 2026 | BA4: =IFERROR(INDEX(Vacantes!$E:$E,MATCH(AT4,Vacantes!$A:$A,0)),"") -> 1:30 p.m. a 5:30 p.m.
A5: juanjeronimo1508@gmail.com | B5: Juan David Jerónimo González | C5: Cédula de ciudadanía | D5: 1027525480 | E5: Hombre | F5: 20 | G5: TRUE | I5: Bogotá | J5: Universidad del Bosque | L5: Estadística | N5: TRUE | O5: FALSE | P5: Intermedio | Q5: Avanzado | R5: Tecnología | U5: Compensación y Beneficios | W5: Talento | AB5: FALSE | AC5: FALSE | AE5: FALSE | AG5: FALSE | AI5: FALSE | AK5: Instagram | AL5: CREATÓN | AM5: 46255 | AN5: 0.4500463 | AO5: 324 4326262 | AP5: Carrera 33A 56 S-14, 110611 Bogota, D.C., Colombia | AQ5: DP | AR5: 90.8 | AS5: Santi | AT5: Compensación y beneficios | AU5: NO | AV5: OK | AW5: =IF(L5="Otra",IF(M5="","Otra",M5&""),L5&"") -> Estadística | AX5: =IF(OR(AO5="",AO5=0),"",TRIM(AO5)) -> 324 4326262 | AY5: =IFERROR(INDEX(Vacantes!$C:$C,MATCH(AT5,Vacantes!$A:$A,0)),"") -> 127 | AZ5: =IFERROR(INDEX(Vacantes!$D:$D,MATCH(AT5,Vacantes!$A:$A,0)),"") -> 13 de octubre de 2026 | BA5: =IFERROR(INDEX(Vacantes!$E:$E,MATCH(AT5,Vacantes!$A:$A,0)),"") -> 7:30 a.m. a 11:30 a.m.
A6: johningla15@gmail.com | B6: John Alejandro Rosas Guerrero | C6: Cédula de ciudadanía | D6: 1013259327 | E6: Hombre | F6: 21 | G6: TRUE | I6: Bogotá | J6: Universidad EAFIT | L6: Finanzas | N6: FALSE | O6: FALSE | P6: Intermedio | Q6: Avanzado | R6: Finanzas | W6: Compras | Y6: Finanzas Impuestos | AB6: FALSE | AC6: FALSE | AE6: FALSE | AG6: FALSE | AI6: FALSE | AK6: LinkedIn | AL6: CREATÓN | AM6: 46255 | AN6: 0.4146875 | AO6: 0 | AP6: Calle 33AA 78A-17, 050031 Medellin, Colombia | AQ6: DP | AR6: 93.3 | AS6: Cata | AT6: Compras (Procurement PPM Reporting) | AU6: NO | AV6: OK | AW6: =IF(L6="Otra",IF(M6="","Otra",M6&""),L6&"") -> Finanzas | AX6: =IF(OR(AO6="",AO6=0),"",TRIM(AO6)) | AY6: =IFERROR(INDEX(Vacantes!$C:$C,MATCH(AT6,Vacantes!$A:$A,0)),"") -> 127 | AZ6: =IFERROR(INDEX(Vacantes!$D:$D,MATCH(AT6,Vacantes!$A:$A,0)),"") -> 13 de octubre de 2026 | BA6: =IFERROR(INDEX(Vacantes!$E:$E,MATCH(AT6,Vacantes!$A:$A,0)),"") -> 7:30 a.m. a 11:30 a.m.
A7: santiago.zambrano1008@gmail.com | B7: Santiago Zambrano Iregui | C7: Cédula de ciudadanía | D7: 1032876688 | E7: Hombre | F7: 21 | G7: TRUE | H7: Tabio | I7: Bogotá | J7: Universidad de La Sabana | L7: Administración de Empresas | N7: FALSE | O7: FALSE | P7: Avanzado | Q7: Avanzado | R7: Marketing | W7: Ventas | AA7: Gestión de Ejecución Premium | AB7: FALSE | AC7: FALSE | AE7: FALSE | AG7: FALSE | AI7: FALSE | AK7: Instagram | AL7: CREATÓN | AM7: 46258 | AN7: 0.39797454 | AO7: 318 8147439 | AP7: Tabio Cundinamarca, 250237 Tabio, Colombia | AQ7: DP | AR7: 84.3 | AS7: Santi | AT7: Comunicaciones | AU7: NO | AV7: OK | AW7: =IF(L7="Otra",IF(M7="","Otra",M7&""),L7&"") -> Administración de Empresas | AX7: =IF(OR(AO7="",AO7=0),"",TRIM(AO7)) -> 318 8147439 | AY7: =IFERROR(INDEX(Vacantes!$C:$C,MATCH(AT7,Vacantes!$A:$A,0)),"") -> 127 | AZ7: =IFERROR(INDEX(Vacantes!$D:$D,MATCH(AT7,Vacantes!$A:$A,0)),"") -> 13 de octubre de 2026 | BA7: =IFERROR(INDEX(Vacantes!$E:$E,MATCH(AT7,Vacantes!$A:$A,0)),"") -> 1:30 p.m. a 5:30 p.m.
A8: selmasanabriad@gmail.com | B8: Selma Melisa Andrea Sanabria Durango | C8: Cédula de ciudadanía | D8: 1066872533 | E8: Mujer | F8: 18 | G8: TRUE | H8: VALLEDUPAR | I8: Bogotá | J8: Universidad del Bosque | L8: Marketing / Mercadeo | N8: FALSE | O8: FALSE | P8: Intermedio | Q8: Intermedio | R8: Marketing | W8: Comunicaciones | AB8: FALSE | AC8: FALSE | AE8: FALSE | AG8: FALSE | AI8: FALSE | AK8: Instagram | AL8: CREATÓN | AM8: 46277 | AN8: 0.79758102 | AO8: 313 6263013 | AP8: Valledupar, Colombia | AQ8: DP | AR8: 73.2 | AS8: Cata | AT8: Comunicaciones | AU8: NO | AV8: OK | AW8: =IF(L8="Otra",IF(M8="","Otra",M8&""),L8&"") -> Marketing / Mercadeo | AX8: =IF(OR(AO8="",AO8=0),"",TRIM(AO8)) -> 313 6263013 | AY8: =IFERROR(INDEX(Vacantes!$C:$C,MATCH(AT8,Vacantes!$A:$A,0)),"") -> 127 | AZ8: =IFERROR(INDEX(Vacantes!$D:$D,MATCH(AT8,Vacantes!$A:$A,0)),"") -> 13 de octubre de 2026 | BA8: =IFERROR(INDEX(Vacantes!$E:$E,MATCH(AT8,Vacantes!$A:$A,0)),"") -> 1:30 p.m. a 5:30 p.m.
A9: carolinaandrea6470@gmail.com | B9: Carolina Hernandez | C9: Cédula de ciudadanía | D9: 1023372339 | E9: Mujer | F9: 20 | G9: TRUE | H9: Bogota | I9: Bogotá | J9: Otra | K9: Universidad EAN | L9: Negocios Internacionales | N9: FALSE | O9: FALSE | P9: Intermedio | Q9: Intermedio | R9: Logística | W9: Marketing | AB9: FALSE | AC9: FALSE | AE9: FALSE | AG9: FALSE | AI9: FALSE | AK9: LinkedIn | AL9: CREATÓN | AM9: 46277 | AN9: 0.97130787 | AO9: 3106091858 | AP9: Calle 70D Sur 79-45, 110741 Bogota, D.C., Colombia | AQ9: DP | AR9: 75.2 | AS9: Cata | AT9: Logística T2 (Safety & DPO T2) | AU9: NO | AV9: OK | AW9: =IF(L9="Otra",IF(M9="","Otra",M9&""),L9&"") -> Negocios Internacionales | AX9: =IF(OR(AO9="",AO9=0),"",TRIM(AO9)) -> 3106091858 | AY9: =IFERROR(INDEX(Vacantes!$C:$C,MATCH(AT9,Vacantes!$A:$A,0)),"") -> 127 | AZ9: =IFERROR(INDEX(Vacantes!$D:$D,MATCH(AT9,Vacantes!$A:$A,0)),"") -> 13 de octubre de 2026 | BA9: =IFERROR(INDEX(Vacantes!$E:$E,MATCH(AT9,Vacantes!$A:$A,0)),"") -> 7:30 a.m. a 11:30 a.m.
A10: angelamendozaeslava2000@gmail.com | B10: Angela Mendoza Eslava | C10: Cédula de ciudadanía | D10: 1018432023 | E10: Mujer | F10: 18 | G10: TRUE | H10: BOGOTA | I10: Bogotá | J10: Pontificia Universidad Javeriana | L10: Administración de Empresas | N10: FALSE | O10: FALSE | P10: Avanzado | Q10: Avanzado | R10: Talento | U10: Atracción de Talento y Marca Empleadora | W10: Talento | Z10: Support | AB10: FALSE | AC10: FALSE | AE10: FALSE | AG10: FALSE | AI10: FALSE | AK10: Página Web Oficial | AL10: CREATÓN | AM10: 46268 | AN10: 0.52506944 | AO10: 305 3700517 | AP10: Calle 83A 118-29, 111011 Bogota, D.C., Colombia | AQ10: DP | AR10: 82.2 | AS10: Cata | AT10: People Support 2 | AU10: NO | AV10: OK | AW10: =IF(L10="Otra",IF(M10="","Otra",M10&""),L10&"") -> Administración de Empresas | AX10: =IF(OR(AO10="",AO10=0),"",TRIM(AO10)) -> 305 3700517 | AY10: =IFERROR(INDEX(Vacantes!$C:$C,MATCH(AT10,Vacantes!$A:$A,0)),"") -> 127 | AZ10: =IFERROR(INDEX(Vacantes!$D:$D,MATCH(AT10,Vacantes!$A:$A,0)),"") -> 13 de octubre de 2026 | BA10: =IFERROR(INDEX(Vacantes!$E:$E,MATCH(AT10,Vacantes!$A:$A,0)),"") -> 1:30 p.m. a 5:30 p.m.
A11: acastanedaruiz55@gmail.com | B11: Alejandro Castaneda Ruiz | C11: Cédula de ciudadanía | D11: 1014858199 | E11: Hombre | F11: 21 | G11: TRUE | H11: Bogota | I11: Bogotá | J11: Universidad de los Andes | L11: Economía | N11: FALSE | O11: FALSE | P11: Avanzado | Q11: Intermedio | R11: Tecnología | T11: Finanzas Impuestos | W11: Finanzas | AB11: FALSE | AC11: FALSE | AE11: FALSE | AG11: FALSE | AI11: FALSE | AK11: LinkedIn | AL11: CREATÓN | AM11: 46265 | AN11: 0.56325231 | AO11: 310 8888133 | AP11: Calle 146A 58B-22, 111156 Bogota, D.C., Colombia | AQ11: DP | AR11: 88.9 | AS11: Cata | AT11: Tecnología (JR Data Scientist) | AU11: NO | AV11: OK | AW11: =IF(L11="Otra",IF(M11="","Otra",M11&""),L11&"") -> Economía | AX11: =IF(OR(AO11="",AO11=0),"",TRIM(AO11)) -> 310 8888133 | AY11: =IFERROR(INDEX(Vacantes!$C:$C,MATCH(AT11,Vacantes!$A:$A,0)),"") -> 127 | AZ11: =IFERROR(INDEX(Vacantes!$D:$D,MATCH(AT11,Vacantes!$A:$A,0)),"") -> 13 de octubre de 2026 | BA11: =IFERROR(INDEX(Vacantes!$E:$E,MATCH(AT11,Vacantes!$A:$A,0)),"") -> 7:30 a.m. a 11:30 a.m.
A12: julim2702@gmail.com | B12: Juliana Manrique Monroy | C12: Cédula de ciudadanía | D12: 1000612606 | E12: Mujer | F12: 23 | G12: TRUE | I12: Bogotá | J12: Universidad del Rosario | L12: Marketing / Mercadeo | N12: TRUE | O12: FALSE | P12: Avanzado | Q12: Intermedio | R12: Marketing | W12: Ventas | AA12: BEES | AB12: FALSE | AC12: FALSE | AE12: FALSE | AG12: FALSE | AI12: FALSE | AK12: LinkedIn | AL12: CREATÓN | AM12: 46257 | AN12: 0.77711806 | AO12: 316 2325718 | AP12: Edificio Roger VI, 111321 Bogota, D.C., Colombia | AQ12: DP | AR12: 93.6 | AS12: Cata | AT12: Channel Strategy and Performance (BEES) | AU12: NO | AV12: OK | AW12: =IF(L12="Otra",IF(M12="","Otra",M12&""),L12&"") -> Marketing / Mercadeo | AX12: =IF(OR(AO12="",AO12=0),"",TRIM(AO12)) -> 316 2325718 | AY12: =IFERROR(INDEX(Vacantes!$C:$C,MATCH(AT12,Vacantes!$A:$A,0)),"") -> 127 | AZ12: =IFERROR(INDEX(Vacantes!$D:$D,MATCH(AT12,Vacantes!$A:$A,0)),"") -> 13 de octubre de 2026 | BA12: =IFERROR(INDEX(Vacantes!$E:$E,MATCH(AT12,Vacantes!$A:$A,0)),"") -> 1:30 p.m. a 5:30 p.m.
A13: ottorincon0408@gmail.com | B13: Oto Esteban Rincón Giraldo | C13: Cédula de ciudadanía | D13: 1070589753 | E13: Hombre | F13: 21 | G13: TRUE | H13: BUCARAMANGA | I13: Bogotá | J13: Otra | K13: Universidad de Santander | L13: Otra | M13: Administración de Negocios Internacionales | N13: TRUE | O13: FALSE | P13: Intermedio | Q13: Intermedio | R13: Logística | W13: Compras | AB13: FALSE | AC13: FALSE | AE13: FALSE | AG13: FALSE | AI13: FALSE | AK13: LinkedIn | AL13: CREATÓN | AM13: 46261 | AN13: 0.6196412 | AO13: 305 4120170 | AP13: Torres de Monterrey, 680004 Bucaramanga, Colombia | AQ13: DP | AR13: 88.6 | AS13: Cata | AT13: Compras (Procurement PPM Reporting) | AU13: NO | AV13: OK | AW13: =IF(L13="Otra",IF(M13="","Otra",M13&""),L13&"") -> Administración de Negocios Internacionales | AX13: =IF(OR(AO13="",AO13=0),"",TRIM(AO13)) -> 305 4120170 | AY13: =IFERROR(INDEX(Vacantes!$C:$C,MATCH(AT13,Vacantes!$A:$A,0)),"") -> 127 | AZ13: =IFERROR(INDEX(Vacantes!$D:$D,MATCH(AT13,Vacantes!$A:$A,0)),"") -> 13 de octubre de 2026 | BA13: =IFERROR(INDEX(Vacantes!$E:$E,MATCH(AT13,Vacantes!$A:$A,0)),"") -> 7:30 a.m. a 11:30 a.m.
A14: ricardocubillosc@javeriana.edu.co | B14: Ricardo Cubillos Combariza | C14: Cédula de ciudadanía | D14: 1014859662 | E14: Hombre | F14: 20 | G14: TRUE | H14: BOGOTA | I14: Bogotá | J14: Pontificia Universidad Javeriana | L14: Finanzas | N14: FALSE | O14: FALSE | P14: Avanzado | Q14: Avanzado | R14: Finanzas | U14: Área financiera | W14: Talento | Y14: Finanzas Impuestos | AB14: FALSE | AC14: FALSE | AE14: FALSE | AG14: FALSE | AI14: FALSE | AK14: Página Web Oficial | AL14: CREATÓN | AM14: 46258 | AN14: 0.76322917 | AO14: 321 8574669 | AP14: Calle 117D 57-96, 111111 Bogota, D.C., Colombia | AQ14: DP | AR14: 89.9 | AS14: Cata | AT14: Area financiera (PPM) | AU14: SI | AV14: OK | AW14: =IF(L14="Otra",IF(M14="","Otra",M14&""),L14&"") -> Finanzas | AX14: =IF(OR(AO14="",AO14=0),"",TRIM(AO14)) -> 321 8574669 | AY14: =IFERROR(INDEX(Vacantes!$C:$C,MATCH(AT14,Vacantes!$A:$A,0)),"") -> 127 | AZ14: =IFERROR(INDEX(Vacantes!$D:$D,MATCH(AT14,Vacantes!$A:$A,0)),"") -> 13 de octubre de 2026 | BA14: =IFERROR(INDEX(Vacantes!$E:$E,MATCH(AT14,Vacantes!$A:$A,0)),"") -> 7:30 a.m. a 11:30 a.m.
A15: sanvalentin139@gmail.com | B15: Valentín Moncada Sánchez | C15: Cédula de ciudadanía | D15: 1022939244 | E15: Hombre | F15: 20 | G15: TRUE | H15: Bogotá | I15: Bogotá | J15: Pontificia Universidad Javeriana | L15: Finanzas | N15: TRUE | O15: FALSE | P15: Intermedio | Q15: Intermedio | R15: Finanzas | U15: Área financiera | W15: Talento | Y15: Finanzas Impuestos | AB15: FALSE | AC15: FALSE | AE15: FALSE | AG15: FALSE | AI15: FALSE | AK15: Otros | AL15: CREATÓN | AM15: 46267 | AN15: 0.26954861 | AO15: 319 5528847 | AP15: Carrera 69K 68-59, 111061 Bogota, D.C., Colombia | AQ15: DP | AR15: 86.4 | AS15: Cata | AT15: Area financiera (PPM) | AU15: SI | AV15: OK | AW15: =IF(L15="Otra",IF(M15="","Otra",M15&""),L15&"") -> Finanzas | AX15: =IF(OR(AO15="",AO15=0),"",TRIM(AO15)) -> 319 5528847 | AY15: =IFERROR(INDEX(Vacantes!$C:$C,MATCH(AT15,Vacantes!$A:$A,0)),"") -> 127 | AZ15: =IFERROR(INDEX(Vacantes!$D:$D,MATCH(AT15,Vacantes!$A:$A,0)),"") -> 13 de octubre de 2026 | BA15: =IFERROR(INDEX(Vacantes!$E:$E,MATCH(AT15,Vacantes!$A:$A,0)),"") -> 7:30 a.m. a 11:30 a.m.
A16: cristianbeltran450@gmail.com | B16: Cristian Beltran Mendez | C16: Cédula de ciudadanía | D16: 1027210314 | E16: Hombre | F16: 21 | G16: TRUE | H16: Bogotá | I16: Bogotá | J16: Universidad del Rosario | L16: Analítica de Datos | N16: FALSE | O16: FALSE | P16: Avanzado | Q16: Avanzado | R16: Finanzas | W16: Compras | Y16: Finanzas Impuestos | AB16: FALSE | AC16: FALSE | AE16: FALSE | AG16: FALSE | AI16: FALSE | AK16: Página Web Oficial | AL16: CREATÓN | AM16: 46278 | AN16: 0.67866898 | AO16: 315 6652203 | AP16: Calle 191A 11A-25, 110141 Bogota, D.C., Colombia | AQ16: DP | AR16: 74.5 | AS16: Cata | AT16: Area financiera (PPM) | AU16: SI | AV16: OK | AW16: =IF(L16="Otra",IF(M16="","Otra",M16&""),L16&"") -> Analítica de Datos | AX16: =IF(OR(AO16="",AO16=0),"",TRIM(AO16)) -> 315 6652203 | AY16: =IFERROR(INDEX(Vacantes!$C:$C,MATCH(AT16,Vacantes!$A:$A,0)),"") -> 127 | AZ16: =IFERROR(INDEX(Vacantes!$D:$D,MATCH(AT16,Vacantes!$A:$A,0)),"") -> 13 de octubre de 2026 | BA16: =IFERROR(INDEX(Vacantes!$E:$E,MATCH(AT16,Vacantes!$A:$A,0)),"") -> 7:30 a.m. a 11:30 a.m.
A17: dkarina.th@gmail.com | B17: Danna Karina Tovar Cabezas | C17: Cédula de ciudadanía | D17: 1013102674 | E17: Mujer | F17: 21 | G17: TRUE | H17: BOGOTA D.C. | I17: Bogotá | J17: Universidad Nacional de Colombia | L17: Economía | N17: FALSE | O17: FALSE | P17: Avanzado | Q17: Avanzado | R17: Finanzas | T17: Finanzas Impuestos | W17: Finanzas | Y17: Finanzas Impuestos | AB17: FALSE | AC17: FALSE | AE17: FALSE | AG17: FALSE | AI17: FALSE | AK17: Otros | AL17: CREATÓN | AM17: 46258 | AN17: 0.91048611 | AO17: 3026715667 | AP17: Calle 69B Sur 64, Bogota, D.C., Colombia | AQ17: DP | AR17: 83.7 | AS17: Cata | AT17: Area financiera (PPM) | AU17: SI | AV17: OK | AW17: =IF(L17="Otra",IF(M17="","Otra",M17&""),L17&"") -> Economía | AX17: =IF(OR(AO17="",AO17=0),"",TRIM(AO17)) -> 3026715667 | AY17: =IFERROR(INDEX(Vacantes!$C:$C,MATCH(AT17,Vacantes!$A:$A,0)),"") -> 127 | AZ17: =IFERROR(INDEX(Vacantes!$D:$D,MATCH(AT17,Vacantes!$A:$A,0)),"") -> 13 de octubre de 2026 | BA17: =IFERROR(INDEX(Vacantes!$E:$E,MATCH(AT17,Vacantes!$A:$A,0)),"") -> 7:30 a.m. a 11:30 a.m.
A18: afdelgado@universidadmayor.edu.co | B18: ANDRES FELIPE DELGADO REY | C18: Cédula de ciudadanía | D18: 1000163318 | E18: Hombre | F18: 25 | G18: TRUE | H18: BOGOTA | I18: Bogotá | J18: Otra | K18: Universidad colegio mayor de cundinamarca | L18: Economía | N18: FALSE | O18: FALSE | P18: Intermedio | Q18: Avanzado | R18: Finanzas | T18: Finanzas Impuestos | W18: Finanzas | Y18: Finanzas Impuestos | AB18: FALSE | AC18: FALSE | AE18: FALSE | AG18: FALSE | AI18: FALSE | AK18: Página Web Oficial | AL18: CREATÓN | AM18: 46269 | AN18: 0.24945602 | AO18: 3143611237 | AP18: Carrera 95A 56H S-52, 110711 Bogota, D.C., Colombia | AQ18: DP | AR18: 82.1 | AS18: Cata | AT18: Area financiera (PPM) | AU18: SI | AV18: OK | AW18: =IF(L18="Otra",IF(M18="","Otra",M18&""),L18&"") -> Economía | AX18: =IF(OR(AO18="",AO18=0),"",TRIM(AO18)) -> 3143611237 | AY18: =IFERROR(INDEX(Vacantes!$C:$C,MATCH(AT18,Vacantes!$A:$A,0)),"") -> 127 | AZ18: =IFERROR(INDEX(Vacantes!$D:$D,MATCH(AT18,Vacantes!$A:$A,0)),"") -> 13 de octubre de 2026 | BA18: =IFERROR(INDEX(Vacantes!$E:$E,MATCH(AT18,Vacantes!$A:$A,0)),"") -> 7:30 a.m. a 11:30 a.m.
A19: pericoagudelomariafernanda@gmail.com | B19: Maria Fernanda Perico Agudelo | C19: Cédula de ciudadanía | D19: 1031644605 | E19: Mujer | F19: 21 | G19: TRUE | H19: BOGOTA | I19: Bogotá | J19: Universidad Externado de Colombia | L19: Derecho | N19: FALSE | O19: FALSE | P19: Avanzado | Q19: Básico | R19: Asuntos corporativos | W19: Tecnología | AB19: FALSE | AC19: FALSE | AE19: FALSE | AG19: FALSE | AI19: FALSE | AK19: Otros | AL19: CREATÓN | AM19: 46266 | AN19: 0.68083333 | AO19: 3197010253 | AP19: Calle 159 54-35, 111156 Bogota, D.C., Colombia | AQ19: DP | AR19: 95.5 | AS19: Santi | AT19: Asuntos Corporativos | AU19: SI | AV19: OK | AW19: =IF(L19="Otra",IF(M19="","Otra",M19&""),L19&"") -> Derecho | AX19: =IF(OR(AO19="",AO19=0),"",TRIM(AO19)) -> 3197010253 | AY19: =IFERROR(INDEX(Vacantes!$C:$C,MATCH(AT19,Vacantes!$A:$A,0)),"") -> 127 | AZ19: =IFERROR(INDEX(Vacantes!$D:$D,MATCH(AT19,Vacantes!$A:$A,0)),"") -> 13 de octubre de 2026 | BA19: =IFERROR(INDEX(Vacantes!$E:$E,MATCH(AT19,Vacantes!$A:$A,0)),"") -> 1:30 p.m. a 5:30 p.m.
A20: lunaardila08@hotmail.com | B20: Luna Carolina Ardila Jiménez | C20: Cédula de ciudadanía | D20: 1025528570 | E20: Mujer | F20: 20 | G20: TRUE | H20: Bogotá | I20: Bogotá | J20: Otra | K20: Universidad EAN | L20: Negocios Internacionales | N20: FALSE | O20: FALSE | P20: Intermedio | Q20: Intermedio | R20: Asuntos corporativos | U20: Atracción de Talento y Marca Empleadora | W20: Talento | AB20: FALSE | AC20: FALSE | AE20: FALSE | AG20: FALSE | AI20: FALSE | AK20: Medios Tradicionales | AL20: CREATÓN | AM20: 46266 | AN20: 0.66010417 | AO20: 0 | AP20: Diagonal 23C BIS Transversal 88C-88b, 110911 Bogota, D.C., Colombia | AQ20: DP | AR20: 90.5 | AS20: Cata | AT20: Asuntos Corporativos | AU20: SI | AV20: OK | AW20: =IF(L20="Otra",IF(M20="","Otra",M20&""),L20&"") -> Negocios Internacionales | AX20: =IF(OR(AO20="",AO20=0),"",TRIM(AO20)) | AY20: =IFERROR(INDEX(Vacantes!$C:$C,MATCH(AT20,Vacantes!$A:$A,0)),"") -> 127 | AZ20: =IFERROR(INDEX(Vacantes!$D:$D,MATCH(AT20,Vacantes!$A:$A,0)),"") -> 13 de octubre de 2026 | BA20: =IFERROR(INDEX(Vacantes!$E:$E,MATCH(AT20,Vacantes!$A:$A,0)),"") -> 1:30 p.m. a 5:30 p.m.
A21: dfelipegomeza203@gmail.com | B21: Daniel Gómez Anaya | C21: Cédula de ciudadanía | D21: 1001096590 | E21: Hombre | F21: 23 | G21: TRUE | H21: BOGOTA | I21: Bogotá | J21: Universidad del Rosario | L21: Economía | N21: TRUE | O21: FALSE | P21: Avanzado | Q21: Intermedio | R21: Asuntos corporativos | W21: Compras | AB21: FALSE | AC21: FALSE | AE21: FALSE | AG21: FALSE | AI21: FALSE | AK21: Otros | AL21: CREATÓN | AM21: 46262 | AN21: 0.35939815 | AO21: 302 2508910 | AP21: Carrera 7B 127C-58, 110121 Bogota, D.C., Colombia | AQ21: DP | AR21: 70.1 | AS21: Cata | AT21: Asuntos Corporativos | AU21: SI | AV21: OK | AW21: =IF(L21="Otra",IF(M21="","Otra",M21&""),L21&"") -> Economía | AX21: =IF(OR(AO21="",AO21=0),"",TRIM(AO21)) -> 302 2508910 | AY21: =IFERROR(INDEX(Vacantes!$C:$C,MATCH(AT21,Vacantes!$A:$A,0)),"") -> 127 | AZ21: =IFERROR(INDEX(Vacantes!$D:$D,MATCH(AT21,Vacantes!$A:$A,0)),"") -> 13 de octubre de 2026 | BA21: =IFERROR(INDEX(Vacantes!$E:$E,MATCH(AT21,Vacantes!$A:$A,0)),"") -> 1:30 p.m. a 5:30 p.m.
A22: daza.matias@javeriana.edu.co | B22: Matias Daza | C22: Cédula de ciudadanía | D22: 1031652558 | E22: Hombre | F22: 19 | G22: TRUE | H22: BOGOTA | I22: Bogotá | J22: Pontificia Universidad Javeriana | L22: Derecho | N22: TRUE | O22: FALSE | P22: Avanzado | Q22: Intermedio | R22: Asuntos corporativos | W22: Ventas | AA22: Ventas Comercial | AB22: FALSE | AC22: FALSE | AE22: FALSE | AG22: FALSE | AI22: FALSE | AK22: Instagram | AL22: CREATÓN | AM22: 46277 | AN22: 0.61746528 | AO22: 3058170290 | AP22: Carrera 89 147B-79, 111156 Bogota, D.C., Colombia | AQ22: DP | AR22: 74.1 | AS22: Cata | AT22: Asuntos Corporativos | AU22: SI | AV22: OK | AW22: =IF(L22="Otra",IF(M22="","Otra",M22&""),L22&"") -> Derecho | AX22: =IF(OR(AO22="",AO22=0),"",TRIM(AO22)) -> 3058170290 | AY22: =IFERROR(INDEX(Vacantes!$C:$C,MATCH(AT22,Vacantes!$A:$A,0)),"") -> 127 | AZ22: =IFERROR(INDEX(Vacantes!$D:$D,MATCH(AT22,Vacantes!$A:$A,0)),"") -> 13 de octubre de 2026 | BA22: =IFERROR(INDEX(Vacantes!$E:$E,MATCH(AT22,Vacantes!$A:$A,0)),"") -> 1:30 p.m. a 5:30 p.m.
A23: nicolechiquiza@gmail.com | B23: Nicole Daiam Chiquiza Moreno | C23: Cédula de ciudadanía | D23: 1072644235 | E23: Mujer | F23: 21 | G23: TRUE | H23: CHIA CUNDINAMARCA | I23: Bogotá | J23: Universidad de los Andes | L23: Administración de Empresas | N23: FALSE | O23: FALSE | P23: Intermedio | Q23: Intermedio | R23: Marketing | U23: Atracción de Talento y Marca Empleadora | W23: Talento | AB23: FALSE | AC23: FALSE | AE23: FALSE | AG23: FALSE | AI23: FALSE | AK23: LinkedIn | AL23: CREATÓN | AM23: 46268 | AN23: 0.0018171296 | AO23: 305 3136665 | AP23: Calle 7 1-84, 250001 Chía, Colombia | AQ23: DP | AR23: 83.8 | AS23: Cata | AT23: Atracción de talento y Marca Empleadora | AU23: SI | AV23: OK | AW23: =IF(L23="Otra",IF(M23="","Otra",M23&""),L23&"") -> Administración de Empresas | AX23: =IF(OR(AO23="",AO23=0),"",TRIM(AO23)) -> 305 3136665 | AY23: =IFERROR(INDEX(Vacantes!$C:$C,MATCH(AT23,Vacantes!$A:$A,0)),"") -> 127 | AZ23: =IFERROR(INDEX(Vacantes!$D:$D,MATCH(AT23,Vacantes!$A:$A,0)),"") -> 13 de octubre de 2026 | BA23: =IFERROR(INDEX(Vacantes!$E:$E,MATCH(AT23,Vacantes!$A:$A,0)),"") -> 7:30 a.m. a 11:30 a.m.
A24: gabyaguirrecortes@gmail.com | B24: Gabriela Aguirre Cortes | C24: Cédula de ciudadanía | D24: 1016912331 | E24: Mujer | F24: 21 | G24: TRUE | I24: Bogotá | J24: Universidad Externado de Colombia | L24: Administración de Empresas | N24: FALSE | O24: FALSE | P24: Avanzado | Q24: Avanzado | R24: Marketing | U24: Atracción de Talento y Marca Empleadora | W24: Talento | AB24: FALSE | AC24: FALSE | AE24: FALSE | AG24: FALSE | AI24: FALSE | AK24: Otros | AL24: CREATÓN | AM24: 46256 | AN24: 0.42581019 | AO24: 319 4972788 | AP24: Carrera 73B 146F-25, 111156 Bogota, D.C., Colombia | AQ24: DP | AR24: 85.2 | AS24: Cata | AT24: Atracción de talento y Marca Empleadora | AU24: SI | AV24: OK | AW24: =IF(L24="Otra",IF(M24="","Otra",M24&""),L24&"") -> Administración de Empresas | AX24: =IF(OR(AO24="",AO24=0),"",TRIM(AO24)) -> 319 4972788 | AY24: =IFERROR(INDEX(Vacantes!$C:$C,MATCH(AT24,Vacantes!$A:$A,0)),"") -> 127 | AZ24: =IFERROR(INDEX(Vacantes!$D:$D,MATCH(AT24,Vacantes!$A:$A,0)),"") -> 13 de octubre de 2026 | BA24: =IFERROR(INDEX(Vacantes!$E:$E,MATCH(AT24,Vacantes!$A:$A,0)),"") -> 7:30 a.m. a 11:30 a.m.
A25: foreroandres292@gmail.com | B25: Andres Fuentes Forero | C25: Cédula de ciudadanía | D25: 1000286128 | E25: Hombre | F25: 23 | G25: TRUE | I25: Bogotá | J25: Universidad del Rosario | L25: Negocios Internacionales | N25: FALSE | O25: FALSE | P25: Avanzado | Q25: Intermedio | R25: Logística | U25: Atracción de Talento y Marca Empleadora | W25: Talento | AB25: FALSE | AC25: FALSE | AE25: FALSE | AG25: FALSE | AI25: FALSE | AK25: Instagram | AL25: CREATÓN | AM25: 46255 | AN25: 0.4146875 | AO25: 318 2479065 | AP25: Calle 53 4A-69, 110231 Bogota, D.C., Colombia | AQ25: DP | AR25: 81.9 | AS25: Cata | AT25: Atracción de talento y Marca Empleadora | AU25: SI | AV25: OK | AW25: =IF(L25="Otra",IF(M25="","Otra",M25&""),L25&"") -> Negocios Internacionales | AX25: =IF(OR(AO25="",AO25=0),"",TRIM(AO25)) -> 318 2479065 | AY25: =IFERROR(INDEX(Vacantes!$C:$C,MATCH(AT25,Vacantes!$A:$A,0)),"") -> 127 | AZ25: =IFERROR(INDEX(Vacantes!$D:$D,MATCH(AT25,Vacantes!$A:$A,0)),"") -> 13 de octubre de 2026 | BA25: =IFERROR(INDEX(Vacantes!$E:$E,MATCH(AT25,Vacantes!$A:$A,0)),"") -> 7:30 a.m. a 11:30 a.m.
A26: sarahernandezn.20@gmail.com | B26: Sara Sofia Hernandez Neira | C26: Cédula de ciudadanía | D26: 1021512114 | E26: Mujer | F26: 22 | G26: TRUE | H26: Bogotá | I26: Bogotá | J26: Universidad de La Sabana | L26: Negocios Internacionales | N26: FALSE | O26: FALSE | P26: Avanzado | Q26: Avanzado | R26: Talento | W26: Ventas | Z26: Atracción de Talento y Marca Empleadora | AA26: Gestión de Ejecución Premium | AB26: FALSE | AC26: FALSE | AE26: FALSE | AG26: FALSE | AI26: FALSE | AK26: Instagram | AL26: CREATÓN | AM26: 46259 | AN26: 0.81193287 | AO26: 313 4649889 | AP26: Carrera 62 165A-69, 111156 Bogota, D.C., Colombia | AQ26: DP | AR26: 80.5 | AS26: Cata | AT26: Atracción de talento y Marca Empleadora | AU26: SI | AV26: OK | AW26: =IF(L26="Otra",IF(M26="","Otra",M26&""),L26&"") -> Negocios Internacionales | AX26: =IF(OR(AO26="",AO26=0),"",TRIM(AO26)) -> 313 4649889 | AY26: =IFERROR(INDEX(Vacantes!$C:$C,MATCH(AT26,Vacantes!$A:$A,0)),"") -> 127 | AZ26: =IFERROR(INDEX(Vacantes!$D:$D,MATCH(AT26,Vacantes!$A:$A,0)),"") -> 13 de octubre de 2026 | BA26: =IFERROR(INDEX(Vacantes!$E:$E,MATCH(AT26,Vacantes!$A:$A,0)),"") -> 7:30 a.m. a 11:30 a.m.
A27: mariacasjau@unisabana.edu.co | B27: Maria Alejandra Castro Jauregui | C27: Cédula de ciudadanía | D27: 1012337267 | E27: Mujer | F27: 20 | G27: TRUE | H27: Bogotá | I27: Bogotá | J27: Universidad de La Sabana | L27: Psicología | N27: FALSE | O27: FALSE | P27: Avanzado | Q27: Intermedio | R27: Talento | W27: Comunicaciones | Z27: Atracción de Talento y Marca Empleadora | AB27: FALSE | AC27: TRUE | AE27: FALSE | AG27: FALSE | AH27: Padre - William Humberto Castro Riaño | AI27: FALSE | AK27: Instagram | AL27: CREATÓN | AM27: 46265 | AN27: 0.45572917 | AO27: 322 4018881 | AP27: Carrera 53 141-69, 111156 Bogota, D.C., Colombia | AQ27: DP | AR27: 88.2 | AS27: Cata | AT27: Atracción de talento y Marca Empleadora | AU27: SI | AV27: OK | AW27: =IF(L27="Otra",IF(M27="","Otra",M27&""),L27&"") -> Psicología | AX27: =IF(OR(AO27="",AO27=0),"",TRIM(AO27)) -> 322 4018881 | AY27: =IFERROR(INDEX(Vacantes!$C:$C,MATCH(AT27,Vacantes!$A:$A,0)),"") -> 127 | AZ27: =IFERROR(INDEX(Vacantes!$D:$D,MATCH(AT27,Vacantes!$A:$A,0)),"") -> 13 de octubre de 2026 | BA27: =IFERROR(INDEX(Vacantes!$E:$E,MATCH(AT27,Vacantes!$A:$A,0)),"") -> 7:30 a.m. a 11:30 a.m.
A28: c.gomezt2@uniandes.edu.co | B28: Catalina Gómez | C28: Cédula de ciudadanía | D28: 1107834811 | E28: Mujer | F28: 22 | G28: TRUE | H28: BOGOTA | I28: Bogotá | J28: Universidad de los Andes | L28: Administración de Empresas | N28: FALSE | O28: FALSE | P28: Avanzado | Q28: Avanzado | R28: Ventas | V28: Talento Ventas | W28: Marketing | AB28: FALSE | AC28: FALSE | AE28: FALSE | AG28: FALSE | AI28: FALSE | AK28: LinkedIn | AL28: CREATÓN | AM28: 46269 | AN28: 0.24943287 | AO28: 3116257553 | AP28: Calle 70A 7-36, 110231 Bogota, D.C., Colombia | AQ28: DP | AR28: 98.3 | AS28: Cata | AT28: Atracción de talento y Marca Empleadora | AU28: SI | AV28: OK | AW28: =IF(L28="Otra",IF(M28="","Otra",M28&""),L28&"") -> Administración de Empresas | AX28: =IF(OR(AO28="",AO28=0),"",TRIM(AO28)) -> 3116257553 | AY28: =IFERROR(INDEX(Vacantes!$C:$C,MATCH(AT28,Vacantes!$A:$A,0)),"") -> 127 | AZ28: =IFERROR(INDEX(Vacantes!$D:$D,MATCH(AT28,Vacantes!$A:$A,0)),"") -> 13 de octubre de 2026 | BA28: =IFERROR(INDEX(Vacantes!$E:$E,MATCH(AT28,Vacantes!$A:$A,0)),"") -> 7:30 a.m. a 11:30 a.m.
A29: marianaroro16@gmail.com | B29: Mariana Rojas Rodriguez | C29: Cédula de ciudadanía | D29: 1023372804 | E29: Mujer | F29: 20 | G29: TRUE | H29: BOGOTÁ D.C | I29: Bogotá | J29: Universidad Piloto de Colombia | L29: Psicología | N29: TRUE | O29: FALSE | P29: Intermedio | Q29: Intermedio | R29: Talento | W29: Marketing | Z29: Atracción de Talento y Marca Empleadora | AB29: FALSE | AC29: FALSE | AE29: FALSE | AG29: FALSE | AI29: FALSE | AK29: LinkedIn | AL29: CREATÓN | AM29: 46262 | AN29: 0.24175926 | AO29: 305 7325384 | AP29: Calle 56A Sur 72C-10, 110741 Bogota, D.C., Colombia | AQ29: DP | AR29: 86.2 | AS29: Cata | AT29: Atracción de talento y Marca Empleadora | AU29: SI | AV29: OK | AW29: =IF(L29="Otra",IF(M29="","Otra",M29&""),L29&"") -> Psicología | AX29: =IF(OR(AO29="",AO29=0),"",TRIM(AO29)) -> 305 7325384 | AY29: =IFERROR(INDEX(Vacantes!$C:$C,MATCH(AT29,Vacantes!$A:$A,0)),"") -> 127 | AZ29: =IFERROR(INDEX(Vacantes!$D:$D,MATCH(AT29,Vacantes!$A:$A,0)),"") -> 13 de octubre de 2026 | BA29: =IFERROR(INDEX(Vacantes!$E:$E,MATCH(AT29,Vacantes!$A:$A,0)),"") -> 7:30 a.m. a 11:30 a.m.
A30: gabilievano0120@gmail.com | B30: Gabriela Lievano | C30: Cédula de ciudadanía | D30: 1031610059 | E30: Mujer | F30: 22 | G30: TRUE | H30: Bogotá, D.C. | I30: Bogotá | J30: Universidad de los Andes | L30: Administración de Empresas | N30: FALSE | O30: FALSE | P30: Avanzado | Q30: Avanzado | R30: Talento | W30: Marketing | Z30: Atracción de Talento y Marca Empleadora | AB30: FALSE | AC30: FALSE | AE30: FALSE | AG30: FALSE | AI30: FALSE | AK30: LinkedIn | AL30: CREATÓN | AM30: 46266 | AN30: 0.68083333 | AO30: 3107579299 | AP30: Los Rosales, Bogota, D.C., Colombia | AQ30: DP | AR30: 93.4 | AS30: Santi | AT30: Atracción de talento y Marca Empleadora | AU30: SI | AV30: OK | AW30: =IF(L30="Otra",IF(M30="","Otra",M30&""),L30&"") -> Administración de Empresas | AX30: =IF(OR(AO30="",AO30=0),"",TRIM(AO30)) -> 3107579299 | AY30: =IFERROR(INDEX(Vacantes!$C:$C,MATCH(AT30,Vacantes!$A:$A,0)),"") -> 127 | AZ30: =IFERROR(INDEX(Vacantes!$D:$D,MATCH(AT30,Vacantes!$A:$A,0)),"") -> 13 de octubre de 2026 | BA30: =IFERROR(INDEX(Vacantes!$E:$E,MATCH(AT30,Vacantes!$A:$A,0)),"") -> 7:30 a.m. a 11:30 a.m.
A31: alejandraparracard@gmail.com | B31: María Alejandra Parra Cárdenas | C31: Cédula de ciudadanía | D31: 1011090066 | E31: Mujer | F31: 20 | G31: TRUE | I31: Bogotá | J31: Universidad Externado de Colombia | L31: Finanzas | N31: FALSE | O31: FALSE | P31: Intermedio | Q31: Intermedio | R31: Ventas | V31: Canal Moderno | W31: Marketing | AB31: FALSE | AC31: FALSE | AE31: FALSE | AG31: FALSE | AI31: FALSE | AK31: Instagram | AL31: CREATÓN | AM31: 46273 | AN31: 0.26524306 | AO31: 321 9095151 | AP31: Calle 66C 61-1, 111221 Bogota, D.C., Colombia | AQ31: DP | AR31: 96.4 | AS31: Cata | AT31: Canal moderno (KA) | AU31: SI | AV31: OK | AW31: =IF(L31="Otra",IF(M31="","Otra",M31&""),L31&"") -> Finanzas | AX31: =IF(OR(AO31="",AO31=0),"",TRIM(AO31)) -> 321 9095151 | AY31: =IFERROR(INDEX(Vacantes!$C:$C,MATCH(AT31,Vacantes!$A:$A,0)),"") -> 127 | AZ31: =IFERROR(INDEX(Vacantes!$D:$D,MATCH(AT31,Vacantes!$A:$A,0)),"") -> 13 de octubre de 2026 | BA31: =IFERROR(INDEX(Vacantes!$E:$E,MATCH(AT31,Vacantes!$A:$A,0)),"") -> 1:30 p.m. a 5:30 p.m.
A32: ignacio.vega.gouffray@gmail.com | B32: Hernando Ignacio Vega Gouffray | C32: Cédula de ciudadanía | D32: 1000503044 | E32: Hombre | F32: 23 | G32: TRUE | H32: Bogotá | I32: Bogotá | J32: Pontificia Universidad Javeriana | L32: Ingeniería Industrial | N32: FALSE | O32: FALSE | P32: Avanzado | Q32: Avanzado | R32: Ventas | V32: Ventas Comercial | W32: Ventas | AA32: Canal Moderno | AB32: FALSE | AC32: FALSE | AE32: FALSE | AG32: FALSE | AI32: FALSE | AK32: LinkedIn | AL32: CREATÓN | AM32: 46259 | AN32: 0.55434028 | AO32: 316 6197879 | AP32: Edificio Palo Alto, 110221 Bogota, D.C., Colombia | AQ32: DP | AR32: 76.7 | AS32: Cata | AT32: Canal moderno (KA) | AU32: SI | AV32: OK | AW32: =IF(L32="Otra",IF(M32="","Otra",M32&""),L32&"") -> Ingeniería Industrial | AX32: =IF(OR(AO32="",AO32=0),"",TRIM(AO32)) -> 316 6197879 | AY32: =IFERROR(INDEX(Vacantes!$C:$C,MATCH(AT32,Vacantes!$A:$A,0)),"") -> 127 | AZ32: =IFERROR(INDEX(Vacantes!$D:$D,MATCH(AT32,Vacantes!$A:$A,0)),"") -> 13 de octubre de 2026 | BA32: =IFERROR(INDEX(Vacantes!$E:$E,MATCH(AT32,Vacantes!$A:$A,0)),"") -> 1:30 p.m. a 5:30 p.m.
A33: danigalan1805@gmail.com | B33: Daniela Galán Muñoz | C33: Cédula de ciudadanía | D33: 1051066730 | E33: Mujer | F33: 20 | G33: TRUE | I33: Bogotá | J33: Otra | K33: Universidad de Boyacá | L33: Ingeniería Industrial | N33: TRUE | O33: FALSE | P33: Intermedio | Q33: Intermedio | R33: Logística | W33: Ventas | AA33: Canal Moderno | AB33: FALSE | AC33: FALSE | AE33: FALSE | AG33: FALSE | AI33: FALSE | AK33: Página Web Oficial | AL33: CREATÓN | AM33: 46255 | AN33: 0.41467593 | AO33: 322 9448422 | AP33: Paipa, Colombia | AQ33: DP | AR33: 93.9 | AS33: Cata | AT33: Canal moderno (KA) | AU33: SI | AV33: OK | AW33: =IF(L33="Otra",IF(M33="","Otra",M33&""),L33&"") -> Ingeniería Industrial | AX33: =IF(OR(AO33="",AO33=0),"",TRIM(AO33)) -> 322 9448422 | AY33: =IFERROR(INDEX(Vacantes!$C:$C,MATCH(AT33,Vacantes!$A:$A,0)),"") -> 127 | AZ33: =IFERROR(INDEX(Vacantes!$D:$D,MATCH(AT33,Vacantes!$A:$A,0)),"") -> 13 de octubre de 2026 | BA33: =IFERROR(INDEX(Vacantes!$E:$E,MATCH(AT33,Vacantes!$A:$A,0)),"") -> 1:30 p.m. a 5:30 p.m.
A34: valeriarojasmora2@gmail.com | B34: Valeria Rojas Mora | C34: Cédula de ciudadanía | D34: 1031809430 | E34: Mujer | F34: 19 | G34: TRUE | H34: BOGOTÁ | I34: Bogotá | J34: Universidad del Bosque | L34: Negocios Internacionales | N34: FALSE | O34: FALSE | P34: Avanzado | Q34: Intermedio | R34: Ventas | V34: Talento Ventas | W34: Marketing | AB34: FALSE | AC34: FALSE | AE34: FALSE | AG34: FALSE | AI34: FALSE | AK34: LinkedIn | AL34: CREATÓN | AM34: 46267 | AN34: 0.55072917 | AO34: 322 2237039 | AP34: Calle 151B 102B-90, 111161 Bogota, D.C., Colombia | AQ34: DP | AR34: 91.5 | AS34: Santi | AT34: Canal moderno (KA) | AU34: SI | AV34: OK | AW34: =IF(L34="Otra",IF(M34="","Otra",M34&""),L34&"") -> Negocios Internacionales | AX34: =IF(OR(AO34="",AO34=0),"",TRIM(AO34)) -> 322 2237039 | AY34: =IFERROR(INDEX(Vacantes!$C:$C,MATCH(AT34,Vacantes!$A:$A,0)),"") -> 127 | AZ34: =IFERROR(INDEX(Vacantes!$D:$D,MATCH(AT34,Vacantes!$A:$A,0)),"") -> 13 de octubre de 2026 | BA34: =IFERROR(INDEX(Vacantes!$E:$E,MATCH(AT34,Vacantes!$A:$A,0)),"") -> 1:30 p.m. a 5:30 p.m.
A35: erikacure12@gmail.com | B35: Erika Cure | C35: Cédula de ciudadanía | D35: 1042243518 | E35: Mujer | F35: 21 | G35: TRUE | H35: BOGOTA | I35: Bogotá | J35: Colegio de Estudios Superiores de Administración CESA | L35: Administración de Empresas | N35: TRUE | O35: FALSE | P35: Avanzado | Q35: Avanzado | R35: Marketing | W35: Ventas | AA35: Canal Moderno | AB35: FALSE | AC35: FALSE | AE35: FALSE | AG35: FALSE | AI35: FALSE | AK35: Otros | AL35: CREATÓN | AM35: 46277 | AN35: 0.6271412 | AO35: 321 7794626 | AP35: Calle 72A 0-54, 110221 Bogota, D.C., Colombia | AQ35: DP | AR35: 71.3 | AS35: Cata | AT35: Canal moderno (KA) | AU35: SI | AV35: OK | AW35: =IF(L35="Otra",IF(M35="","Otra",M35&""),L35&"") -> Administración de Empresas | AX35: =IF(OR(AO35="",AO35=0),"",TRIM(AO35)) -> 321 7794626 | AY35: =IFERROR(INDEX(Vacantes!$C:$C,MATCH(AT35,Vacantes!$A:$A,0)),"") -> 127 | AZ35: =IFERROR(INDEX(Vacantes!$D:$D,MATCH(AT35,Vacantes!$A:$A,0)),"") -> 13 de octubre de 2026 | BA35: =IFERROR(INDEX(Vacantes!$E:$E,MATCH(AT35,Vacantes!$A:$A,0)),"") -> 1:30 p.m. a 5:30 p.m.
A36: natalia.lizarazo.lopez@gmail.com | B36: Natalia Lizarazo | C36: Cédula de ciudadanía | D36: 1034399810 | E36: Mujer | F36: 20 | G36: TRUE | I36: Bogotá | J36: Escuela Colombiana de Ingeniería Julio Garavito | L36: Ingeniería Industrial | N36: TRUE | O36: FALSE | P36: Intermedio | Q36: Básico | R36: Logística | W36: Ventas | AA36: BEES | AB36: FALSE | AC36: FALSE | AE36: FALSE | AG36: FALSE | AI36: FALSE | AK36: Instagram | AL36: CREATÓN | AM36: 46257 | AN36: 0.77711806 | AO36: 0 | AP36: Calle 75A 76-58, 111051 Bogota, D.C., Colombia | AQ36: DP | AR36: 89.8 | AS36: Santi | AT36: Channel Strategy and Performance (BEES) | AU36: SI | AV36: OK | AW36: =IF(L36="Otra",IF(M36="","Otra",M36&""),L36&"") -> Ingeniería Industrial | AX36: =IF(OR(AO36="",AO36=0),"",TRIM(AO36)) | AY36: =IFERROR(INDEX(Vacantes!$C:$C,MATCH(AT36,Vacantes!$A:$A,0)),"") -> 127 | AZ36: =IFERROR(INDEX(Vacantes!$D:$D,MATCH(AT36,Vacantes!$A:$A,0)),"") -> 13 de octubre de 2026 | BA36: =IFERROR(INDEX(Vacantes!$E:$E,MATCH(AT36,Vacantes!$A:$A,0)),"") -> 1:30 p.m. a 5:30 p.m.
A37: douglas.plazasg@gmail.com | B37: Douglas Plazas Guzman | C37: Cédula de ciudadanía | D37: 1000502600 | E37: Hombre | F37: 24 | G37: TRUE | I37: Bogotá | J37: Universidad de los Andes | L37: Economía | N37: FALSE | O37: FALSE | P37: Avanzado | Q37: Avanzado | R37: Ventas | V37: Gestión de Ejecución Premium | W37: Logística | AB37: FALSE | AC37: FALSE | AE37: FALSE | AG37: FALSE | AI37: FALSE | AK37: Instagram | AL37: CREATÓN | AM37: 46256 | AN37: 0.65561343 | AO37: 310 4683903 | AP37: Bogota, D.C., Colombia | AQ37: DP | AR37: 91 | AS37: Cata | AT37: Channel Strategy and Performance (BEES) | AU37: SI | AV37: OK | AW37: =IF(L37="Otra",IF(M37="","Otra",M37&""),L37&"") -> Economía | AX37: =IF(OR(AO37="",AO37=0),"",TRIM(AO37)) -> 310 4683903 | AY37: =IFERROR(INDEX(Vacantes!$C:$C,MATCH(AT37,Vacantes!$A:$A,0)),"") -> 127 | AZ37: =IFERROR(INDEX(Vacantes!$D:$D,MATCH(AT37,Vacantes!$A:$A,0)),"") -> 13 de octubre de 2026 | BA37: =IFERROR(INDEX(Vacantes!$E:$E,MATCH(AT37,Vacantes!$A:$A,0)),"") -> 1:30 p.m. a 5:30 p.m.
A38: isabellaforero0210@outlook.com | B38: Isabella Forero | C38: Cédula de ciudadanía | D38: 1001191913 | E38: Mujer | F38: 22 | G38: TRUE | H38: BOGOTA | I38: Bogotá | J38: Universidad del Rosario | L38: Marketing / Mercadeo | N38: FALSE | O38: FALSE | P38: Avanzado | Q38: Intermedio | R38: Marketing | W38: Ventas | AA38: BEES | AB38: FALSE | AC38: FALSE | AE38: FALSE | AG38: FALSE | AI38: FALSE | AK38: Página Web Oficial | AL38: CREATÓN | AM38: 46271 | AN38: 0.72023148 | AO38: 304 4266492 | AP38: Calle 114A 19A-67, 110111 Bogota, D.C., Colombia | AQ38: DP | AR38: 92.3 | AS38: Cata | AT38: Channel Strategy and Performance (BEES) | AU38: SI | AV38: OK | AW38: =IF(L38="Otra",IF(M38="","Otra",M38&""),L38&"") -> Marketing / Mercadeo | AX38: =IF(OR(AO38="",AO38=0),"",TRIM(AO38)) -> 304 4266492 | AY38: =IFERROR(INDEX(Vacantes!$C:$C,MATCH(AT38,Vacantes!$A:$A,0)),"") -> 127 | AZ38: =IFERROR(INDEX(Vacantes!$D:$D,MATCH(AT38,Vacantes!$A:$A,0)),"") -> 13 de octubre de 2026 | BA38: =IFERROR(INDEX(Vacantes!$E:$E,MATCH(AT38,Vacantes!$A:$A,0)),"") -> 1:30 p.m. a 5:30 p.m.
A39: daniel.felipe.ladino@gmail.com | B39: Daniel Felipe Ladino Torres | C39: Cédula de ciudadanía | D39: 1000796156 | E39: Hombre | F39: 23 | G39: TRUE | H39: Bogota | I39: Bogotá | J39: Universidad Externado de Colombia | L39: Administración de Empresas | N39: FALSE | O39: FALSE | P39: Intermedio | Q39: Intermedio | R39: Marketing | W39: Ventas | AA39: BEES | AB39: FALSE | AC39: FALSE | AE39: FALSE | AG39: FALSE | AI39: FALSE | AK39: Otros | AL39: CREATÓN | AM39: 46266 | AN39: 0.36131944 | AO39: 3175756956 | AP39: Carrera 74A 168A-50, 111156 Bogota, D.C., Colombia | AQ39: DP | AR39: 75.2 | AS39: Cata | AT39: Channel Strategy and Performance (BEES) | AU39: SI | AV39: OK | AW39: =IF(L39="Otra",IF(M39="","Otra",M39&""),L39&"") -> Administración de Empresas | AX39: =IF(OR(AO39="",AO39=0),"",TRIM(AO39)) -> 3175756956 | AY39: =IFERROR(INDEX(Vacantes!$C:$C,MATCH(AT39,Vacantes!$A:$A,0)),"") -> 127 | AZ39: =IFERROR(INDEX(Vacantes!$D:$D,MATCH(AT39,Vacantes!$A:$A,0)),"") -> 13 de octubre de 2026 | BA39: =IFERROR(INDEX(Vacantes!$E:$E,MATCH(AT39,Vacantes!$A:$A,0)),"") -> 1:30 p.m. a 5:30 p.m.
A40: cataochoad300@gmail.com | B40: Catalina Ochoa Dueñas | C40: Cédula de ciudadanía | D40: 1025061418 | E40: Mujer | F40: 21 | G40: TRUE | H40: BOGOTA | I40: Bogotá | J40: Universidad Externado de Colombia | L40: Administración de Empresas | N40: FALSE | O40: FALSE | P40: Intermedio | Q40: Avanzado | R40: Ventas | V40: BEES | W40: Ventas | AA40: Talento Ventas | AB40: FALSE | AC40: FALSE | AE40: FALSE | AG40: FALSE | AI40: FALSE | AK40: Otros | AL40: CREATÓN | AM40: 46271 | AN40: 0.72021991 | AO40: 322 2444642 | AP40: Calle 45-16, 111321 Bogota, D.C., Colombia | AQ40: DP | AR40: 81.1 | AS40: Cata | AT40: Channel Strategy and Performance (BEES) | AU40: SI | AV40: OK | AW40: =IF(L40="Otra",IF(M40="","Otra",M40&""),L40&"") -> Administración de Empresas | AX40: =IF(OR(AO40="",AO40=0),"",TRIM(AO40)) -> 322 2444642 | AY40: =IFERROR(INDEX(Vacantes!$C:$C,MATCH(AT40,Vacantes!$A:$A,0)),"") -> 127 | AZ40: =IFERROR(INDEX(Vacantes!$D:$D,MATCH(AT40,Vacantes!$A:$A,0)),"") -> 13 de octubre de 2026 | BA40: =IFERROR(INDEX(Vacantes!$E:$E,MATCH(AT40,Vacantes!$A:$A,0)),"") -> 1:30 p.m. a 5:30 p.m.
A41: brayanjaramillo_05@hotmail.com | B41: BRAYAN STEVEN JARAMILLO MORENO | C41: Cédula de ciudadanía | D41: 1070596087 | E41: Hombre | F41: 19 | G41: TRUE | H41: RICAURTE CUNDINAMARCA | I41: Bogotá | J41: Corporación Universitaria Minuto de Dios (UNIMINUTO) | L41: Ingeniería Industrial | N41: TRUE | O41: FALSE | P41: Intermedio | Q41: Intermedio | R41: Talento | W41: Compras | Z41: Compensación y Beneficios | AB41: FALSE | AC41: FALSE | AE41: FALSE | AG41: FALSE | AI41: FALSE | AK41: Medios Tradicionales | AL41: CREATÓN | AM41: 46264 | AN41: 0.91195602 | AO41: 3136370565 | AP41: Ricaurte, Colombia | AQ41: DP | AR41: 80.3 | AS41: Cata | AT41: Compensación y beneficios | AU41: SI | AV41: OK | AW41: =IF(L41="Otra",IF(M41="","Otra",M41&""),L41&"") -> Ingeniería Industrial | AX41: =IF(OR(AO41="",AO41=0),"",TRIM(AO41)) -> 3136370565 | AY41: =IFERROR(INDEX(Vacantes!$C:$C,MATCH(AT41,Vacantes!$A:$A,0)),"") -> 127 | AZ41: =IFERROR(INDEX(Vacantes!$D:$D,MATCH(AT41,Vacantes!$A:$A,0)),"") -> 13 de octubre de 2026 | BA41: =IFERROR(INDEX(Vacantes!$E:$E,MATCH(AT41,Vacantes!$A:$A,0)),"") -> 7:30 a.m. a 11:30 a.m.
A42: karengonzalezk158@gmail.com | B42: Karen Sofia Gonzalez Sanchez | C42: Cédula de ciudadanía | D42: 1023369712 | E42: Mujer | F42: 21 | G42: TRUE | H42: Bogotá D.C. | I42: Bogotá | J42: Universidad Piloto de Colombia | L42: Psicología | N42: FALSE | O42: FALSE | P42: Intermedio | Q42: Intermedio | R42: Talento | W42: Logística | Z42: Compensación y Beneficios | AB42: FALSE | AC42: FALSE | AE42: FALSE | AG42: FALSE | AI42: FALSE | AK42: Medios Tradicionales | AL42: CREATÓN | AM42: 46262 | AN42: 0.24175926 | AO42: 3108828777 | AP42: Carrera 73J 58A S-24, 111921 Bogota, D.C., Colombia | AQ42: DP | AR42: 82.6 | AS42: Cata | AT42: Compensación y beneficios | AU42: SI | AV42: OK | AW42: =IF(L42="Otra",IF(M42="","Otra",M42&""),L42&"") -> Psicología | AX42: =IF(OR(AO42="",AO42=0),"",TRIM(AO42)) -> 3108828777 | AY42: =IFERROR(INDEX(Vacantes!$C:$C,MATCH(AT42,Vacantes!$A:$A,0)),"") -> 127 | AZ42: =IFERROR(INDEX(Vacantes!$D:$D,MATCH(AT42,Vacantes!$A:$A,0)),"") -> 13 de octubre de 2026 | BA42: =IFERROR(INDEX(Vacantes!$E:$E,MATCH(AT42,Vacantes!$A:$A,0)),"") -> 7:30 a.m. a 11:30 a.m.
A43: juanita.morenov@urosario.edu.co | B43: Juanita Moreno Vargas | C43: Cédula de ciudadanía | D43: 1013036270 | E43: Mujer | F43: 22 | G43: TRUE | I43: Bogotá | J43: Universidad del Rosario | L43: Psicología | N43: TRUE | O43: FALSE | P43: Intermedio | Q43: Intermedio | R43: Talento | U43: Atracción de Talento y Marca Empleadora | W43: Talento | Z43: Atracción de Talento y Marca Empleadora | AB43: FALSE | AC43: FALSE | AE43: FALSE | AG43: FALSE | AI43: FALSE | AK43: Instagram | AL43: CREATÓN | AM43: 46255 | AN43: 0.41466435 | AO43: 301 6701913 | AP43: Calle 74 BIS 82-61, 111051 Bogota, D.C., Colombia | AQ43: DP | AR43: 85.4 | AS43: Cata | AT43: Compensación y beneficios | AU43: SI | AV43: OK | AW43: =IF(L43="Otra",IF(M43="","Otra",M43&""),L43&"") -> Psicología | AX43: =IF(OR(AO43="",AO43=0),"",TRIM(AO43)) -> 301 6701913 | AY43: =IFERROR(INDEX(Vacantes!$C:$C,MATCH(AT43,Vacantes!$A:$A,0)),"") -> 127 | AZ43: =IFERROR(INDEX(Vacantes!$D:$D,MATCH(AT43,Vacantes!$A:$A,0)),"") -> 13 de octubre de 2026 | BA43: =IFERROR(INDEX(Vacantes!$E:$E,MATCH(AT43,Vacantes!$A:$A,0)),"") -> 7:30 a.m. a 11:30 a.m.
A44: sofiaararat2@gmail.com | B44: Ana Sofía Ararat Corzo | C44: Cédula de ciudadanía | D44: 1097782112 | E44: Mujer | F44: 21 | G44: TRUE | H44: Bogotá D.C | I44: Bogotá | J44: Universidad Santo Tomás | L44: Administración de Empresas | N44: TRUE | O44: FALSE | P44: Intermedio | Q44: Avanzado | R44: Marketing | U44: Atracción de Talento y Marca Empleadora | W44: Talento | AB44: FALSE | AC44: FALSE | AE44: FALSE | AG44: FALSE | AI44: FALSE | AK44: LinkedIn | AL44: CREATÓN | AM44: 46277 | AN44: 0.48756944 | AO44: 318 3068387 | AP44: Calle 56 57A-14, 111321 Bogota, D.C., Colombia | AQ44: DP | AR44: 86 | AS44: Cata | AT44: Compensación y beneficios | AU44: SI | AV44: OK | AW44: =IF(L44="Otra",IF(M44="","Otra",M44&""),L44&"") -> Administración de Empresas | AX44: =IF(OR(AO44="",AO44=0),"",TRIM(AO44)) -> 318 3068387 | AY44: =IFERROR(INDEX(Vacantes!$C:$C,MATCH(AT44,Vacantes!$A:$A,0)),"") -> 127 | AZ44: =IFERROR(INDEX(Vacantes!$D:$D,MATCH(AT44,Vacantes!$A:$A,0)),"") -> 13 de octubre de 2026 | BA44: =IFERROR(INDEX(Vacantes!$E:$E,MATCH(AT44,Vacantes!$A:$A,0)),"") -> 7:30 a.m. a 11:30 a.m.
A45: marialzateballesteros123@gmail.com | B45: MARIA ANGELICA ALZATE BALLESTEROS | C45: Cédula de ciudadanía | D45: 1119394634 | E45: Mujer | F45: 23 | G45: TRUE | I45: Bogotá | J45: Otra | K45: Universidad de La Guajira | L45: Ingeniería Industrial | N45: FALSE | O45: FALSE | P45: Básico | Q45: Intermedio | R45: Compras | U45: Compensación y Beneficios | W45: Talento | AB45: FALSE | AC45: FALSE | AE45: FALSE | AG45: FALSE | AI45: FALSE | AK45: Página Web Oficial | AL45: CREATÓN | AM45: 46278 | AN45: 0.60923611 | AO45: 3005253020 | AP45: Calle 14 6-50, 440001 Riohacha, Colombia | AQ45: DP | AR45: 74.9 | AS45: Cata | AT45: Compensación y beneficios | AU45: SI | AV45: OK | AW45: =IF(L45="Otra",IF(M45="","Otra",M45&""),L45&"") -> Ingeniería Industrial | AX45: =IF(OR(AO45="",AO45=0),"",TRIM(AO45)) -> 3005253020 | AY45: =IFERROR(INDEX(Vacantes!$C:$C,MATCH(AT45,Vacantes!$A:$A,0)),"") -> 127 | AZ45: =IFERROR(INDEX(Vacantes!$D:$D,MATCH(AT45,Vacantes!$A:$A,0)),"") -> 13 de octubre de 2026 | BA45: =IFERROR(INDEX(Vacantes!$E:$E,MATCH(AT45,Vacantes!$A:$A,0)),"") -> 7:30 a.m. a 11:30 a.m.
A46: valemontes2004@outlook.es | B46: Nicol Valentina Montes Arcila | C46: Cédula de ciudadanía | D46: 1021664406 | E46: Mujer | F46: 22 | G46: TRUE | I46: Bogotá | J46: Universidad Externado de Colombia | L46: Administración de Empresas | N46: FALSE | O46: FALSE | P46: Intermedio | Q46: Intermedio | R46: Ventas | U46: Compensación y Beneficios | V46: Ventas Comercial | W46: Talento | AB46: FALSE | AC46: FALSE | AE46: FALSE | AG46: FALSE | AI46: FALSE | AK46: Otros | AL46: CREATÓN | AM46: 46255 | AN46: 0.6958912 | AO46: 321 4013423 | AP46: Avenida Calle 26 70-46, 111071 Bogota, D.C., Colombia | AQ46: DP | AR46: 75.5 | AS46: Cata | AT46: Compensación y beneficios | AU46: SI | AV46: OK | AW46: =IF(L46="Otra",IF(M46="","Otra",M46&""),L46&"") -> Administración de Empresas | AX46: =IF(OR(AO46="",AO46=0),"",TRIM(AO46)) -> 321 4013423 | AY46: =IFERROR(INDEX(Vacantes!$C:$C,MATCH(AT46,Vacantes!$A:$A,0)),"") -> 127 | AZ46: =IFERROR(INDEX(Vacantes!$D:$D,MATCH(AT46,Vacantes!$A:$A,0)),"") -> 13 de octubre de 2026 | BA46: =IFERROR(INDEX(Vacantes!$E:$E,MATCH(AT46,Vacantes!$A:$A,0)),"") -> 7:30 a.m. a 11:30 a.m.
A47: sofsuarez26@gmail.com | B47: Sofia Suarez Martinez | C47: Cédula de ciudadanía | D47: 1021633586 | E47: Mujer | F47: 21 | G47: TRUE | H47: Bogota | I47: Bogotá | J47: Colegio de Estudios Superiores de Administración CESA | L47: Administración de Empresas | N47: TRUE | O47: FALSE | P47: Avanzado | Q47: Intermedio | R47: Marketing | U47: Atracción de Talento y Marca Empleadora | W47: Talento | AB47: FALSE | AC47: FALSE | AE47: FALSE | AG47: FALSE | AI47: FALSE | AK47: LinkedIn | AL47: CREATÓN | AM47: 46275 | AN47: 0.83815972 | AO47: 310 7078253 | AP47: Carrera 10B 134A-53, 110121 Bogota, D.C., Colombia | AQ47: DP | AR47: 94.1 | AS47: Cata | AT47: Compensación y beneficios | AU47: SI | AV47: OK | AW47: =IF(L47="Otra",IF(M47="","Otra",M47&""),L47&"") -> Administración de Empresas | AX47: =IF(OR(AO47="",AO47=0),"",TRIM(AO47)) -> 310 7078253 | AY47: =IFERROR(INDEX(Vacantes!$C:$C,MATCH(AT47,Vacantes!$A:$A,0)),"") -> 127 | AZ47: =IFERROR(INDEX(Vacantes!$D:$D,MATCH(AT47,Vacantes!$A:$A,0)),"") -> 13 de octubre de 2026 | BA47: =IFERROR(INDEX(Vacantes!$E:$E,MATCH(AT47,Vacantes!$A:$A,0)),"") -> 7:30 a.m. a 11:30 a.m.
A48: miguelcaza24@gmail.com | B48: Miguel Ángel Casas Zárate | C48: Cédula de ciudadanía | D48: 1014479562 | E48: Hombre | F48: 20 | G48: TRUE | H48: Bogotá | I48: Bogotá | J48: Universidad Piloto de Colombia | L48: Economía | N48: FALSE | O48: FALSE | P48: Básico | Q48: Intermedio | R48: Finanzas | W48: Compras | Y48: Finanzas Impuestos | AB48: FALSE | AC48: FALSE | AE48: FALSE | AG48: FALSE | AI48: FALSE | AK48: Página Web Oficial | AL48: CREATÓN | AM48: 46266 | AN48: 0.25701389 | AO48: 300 1653749 | AP48: Calle 71A Sur 81-20, 110731 Bogota, D.C., Colombia | AQ48: DP | AR48: 92 | AS48: Cata | AT48: Compras (Procurement PPM Reporting) | AU48: SI | AV48: OK | AW48: =IF(L48="Otra",IF(M48="","Otra",M48&""),L48&"") -> Economía | AX48: =IF(OR(AO48="",AO48=0),"",TRIM(AO48)) -> 300 1653749 | AY48: =IFERROR(INDEX(Vacantes!$C:$C,MATCH(AT48,Vacantes!$A:$A,0)),"") -> 127 | AZ48: =IFERROR(INDEX(Vacantes!$D:$D,MATCH(AT48,Vacantes!$A:$A,0)),"") -> 13 de octubre de 2026 | BA48: =IFERROR(INDEX(Vacantes!$E:$E,MATCH(AT48,Vacantes!$A:$A,0)),"") -> 7:30 a.m. a 11:30 a.m.
A49: mariajulianarodriguez2003@gmail.com | B49: María Juliana Rodríguez Álvarez | C49: Cédula de ciudadanía | D49: 1007558149 | E49: Mujer | F49: 23 | G49: TRUE | H49: Bogotá | I49: Bogotá | J49: Universidad de los Andes | L49: Otra | M49: Narrativas Digitales y Ciencia Politica | N49: FALSE | O49: FALSE | P49: Avanzado | Q49: Intermedio | R49: Marketing | W49: Comunicaciones | AB49: FALSE | AC49: FALSE | AE49: FALSE | AG49: FALSE | AI49: FALSE | AK49: Medios Tradicionales | AL49: CREATÓN | AM49: 46264 | AN49: 0.43060185 | AO49: 301 4372540 | AP49: Carrera 71, Bogota, D.C., Colombia | AQ49: DP | AR49: 91.8 | AS49: Cata | AT49: Comunicaciones | AU49: SI | AV49: OK | AW49: =IF(L49="Otra",IF(M49="","Otra",M49&""),L49&"") -> Narrativas Digitales y Ciencia Politica | AX49: =IF(OR(AO49="",AO49=0),"",TRIM(AO49)) -> 301 4372540 | AY49: =IFERROR(INDEX(Vacantes!$C:$C,MATCH(AT49,Vacantes!$A:$A,0)),"") -> 127 | AZ49: =IFERROR(INDEX(Vacantes!$D:$D,MATCH(AT49,Vacantes!$A:$A,0)),"") -> 13 de octubre de 2026 | BA49: =IFERROR(INDEX(Vacantes!$E:$E,MATCH(AT49,Vacantes!$A:$A,0)),"") -> 1:30 p.m. a 5:30 p.m.
A50: laurav0193@gmail.com | B50: Laura Valentina Franco Segura | C50: Cédula de ciudadanía | D50: 1027210269 | E50: Mujer | F50: 21 | G50: TRUE | H50: Bogotá | I50: Bogotá | J50: Universidad Externado de Colombia | L50: Comunicación social | N50: FALSE | O50: FALSE | P50: Intermedio | Q50: Intermedio | R50: Comunicaciones | W50: Marketing | AB50: FALSE | AC50: FALSE | AE50: FALSE | AG50: FALSE | AI50: FALSE | AK50: LinkedIn | AL50: CREATÓN | AM50: 46265 | AN50: 0.92298611 | AO50: 322 2350694 | AP50: Carrera 55 152B-68, 111156 Bogota, D.C., Colombia | AQ50: DP | AR50: 97.3 | AS50: Santi | AT50: Comunicaciones | AU50: SI | AV50: OK | AW50: =IF(L50="Otra",IF(M50="","Otra",M50&""),L50&"") -> Comunicación social | AX50: =IF(OR(AO50="",AO50=0),"",TRIM(AO50)) -> 322 2350694 | AY50: =IFERROR(INDEX(Vacantes!$C:$C,MATCH(AT50,Vacantes!$A:$A,0)),"") -> 127 | AZ50: =IFERROR(INDEX(Vacantes!$D:$D,MATCH(AT50,Vacantes!$A:$A,0)),"") -> 13 de octubre de 2026 | BA50: =IFERROR(INDEX(Vacantes!$E:$E,MATCH(AT50,Vacantes!$A:$A,0)),"") -> 1:30 p.m. a 5:30 p.m.
A51: arianasofiagomez19@gmail.com | B51: Ariana Gómez Pinzón | C51: Cédula de ciudadanía | D51: 1000365880 | E51: Mujer | F51: 25 | G51: TRUE | H51: Bogotá D.C. | I51: Bogotá | J51: Universidad Sergio Arboleda | L51: Publicidad | N51: FALSE | O51: FALSE | P51: Avanzado | Q51: Intermedio | R51: Marketing | W51: Comunicaciones | AB51: FALSE | AC51: FALSE | AE51: FALSE | AG51: FALSE | AI51: FALSE | AK51: LinkedIn | AL51: CREATÓN | AM51: 46265 | AN51: 0.92298611 | AO51: 3508455279 | AP51: Carrera 10D 27A S-41, 111821 Bogota, D.C., Colombia | AQ51: DP | AR51: 86.2 | AS51: Cata | AT51: Comunicaciones | AU51: SI | AV51: OK | AW51: =IF(L51="Otra",IF(M51="","Otra",M51&""),L51&"") -> Publicidad | AX51: =IF(OR(AO51="",AO51=0),"",TRIM(AO51)) -> 3508455279 | AY51: =IFERROR(INDEX(Vacantes!$C:$C,MATCH(AT51,Vacantes!$A:$A,0)),"") -> 127 | AZ51: =IFERROR(INDEX(Vacantes!$D:$D,MATCH(AT51,Vacantes!$A:$A,0)),"") -> 13 de octubre de 2026 | BA51: =IFERROR(INDEX(Vacantes!$E:$E,MATCH(AT51,Vacantes!$A:$A,0)),"") -> 1:30 p.m. a 5:30 p.m.
A52: isabellarojasdada05@gmail.com | B52: Isabella Rojas Dada | C52: Cédula de ciudadanía | D52: 1019842441 | E52: Mujer | F52: 21 | G52: TRUE | I52: Bogotá | J52: Pontificia Universidad Javeriana | L52: Comunicación social | N52: FALSE | O52: FALSE | P52: Avanzado | Q52: Intermedio | R52: Marketing | W52: Comunicaciones | AB52: FALSE | AC52: FALSE | AE52: FALSE | AG52: FALSE | AI52: FALSE | AK52: TikTok | AL52: CREATÓN | AM52: 46256 | AN52: 0.5362037 | AO52: 3166210415 | AP52: Bogota, D.C., Colombia | AQ52: DP | AR52: 80 | AS52: Cata | AT52: Comunicaciones | AU52: SI | AV52: OK | AW52: =IF(L52="Otra",IF(M52="","Otra",M52&""),L52&"") -> Comunicación social | AX52: =IF(OR(AO52="",AO52=0),"",TRIM(AO52)) -> 3166210415 | AY52: =IFERROR(INDEX(Vacantes!$C:$C,MATCH(AT52,Vacantes!$A:$A,0)),"") -> 127 | AZ52: =IFERROR(INDEX(Vacantes!$D:$D,MATCH(AT52,Vacantes!$A:$A,0)),"") -> 13 de octubre de 2026 | BA52: =IFERROR(INDEX(Vacantes!$E:$E,MATCH(AT52,Vacantes!$A:$A,0)),"") -> 1:30 p.m. a 5:30 p.m.
A53: leidysanaven@gmail.com | B53: Leidy Sánchez Avendaño | C53: Cédula de ciudadanía | D53: 1014856810 | E53: Mujer | F53: 22 | G53: TRUE | H53: BOGOTA | I53: Bogotá | J53: Politécnico Grancolombiano | L53: Marketing / Mercadeo | N53: FALSE | O53: FALSE | P53: Avanzado | Q53: Intermedio | R53: Marketing | W53: Comunicaciones | AB53: FALSE | AC53: FALSE | AE53: FALSE | AG53: FALSE | AI53: FALSE | AK53: LinkedIn | AL53: CREATÓN | AM53: 46277 | AN53: 0.60421296 | AO53: 311 2686111 | AP53: Calle 64A 57-23, 111221 Bogota, D.C., Colombia | AQ53: DP | AR53: 73.9 | AS53: Cata | AT53: Comunicaciones | AU53: SI | AV53: OK | AW53: =IF(L53="Otra",IF(M53="","Otra",M53&""),L53&"") -> Marketing / Mercadeo | AX53: =IF(OR(AO53="",AO53=0),"",TRIM(AO53)) -> 311 2686111 | AY53: =IFERROR(INDEX(Vacantes!$C:$C,MATCH(AT53,Vacantes!$A:$A,0)),"") -> 127 | AZ53: =IFERROR(INDEX(Vacantes!$D:$D,MATCH(AT53,Vacantes!$A:$A,0)),"") -> 13 de octubre de 2026 | BA53: =IFERROR(INDEX(Vacantes!$E:$E,MATCH(AT53,Vacantes!$A:$A,0)),"") -> 1:30 p.m. a 5:30 p.m.
A54: pipecorreanegro@gmail.com | B54: Andres Correa | C54: Cédula de ciudadanía | D54: 1001297216 | E54: Hombre | F54: 24 | G54: TRUE | H54: BOGOTÁ DC | I54: Bogotá | J54: Otra | K54: Universidad EAN | L54: Administración de Empresas | N54: TRUE | O54: FALSE | P54: Avanzado | Q54: Avanzado | R54: Logística | T54: Finanzas Impuestos | W54: Finanzas | AB54: FALSE | AC54: FALSE | AE54: FALSE | AG54: FALSE | AI54: FALSE | AK54: LinkedIn | AL54: CREATÓN | AM54: 46259 | AN54: 0.90423611 | AO54: 3014451602 | AP54: Calle 23C, Bogota, D.C., Colombia | AQ54: DP | AR54: 89.4 | AS54: Cata | AT54: Logística T2 (Safety & DPO T2) | AU54: SI | AV54: OK | AW54: =IF(L54="Otra",IF(M54="","Otra",M54&""),L54&"") -> Administración de Empresas | AX54: =IF(OR(AO54="",AO54=0),"",TRIM(AO54)) -> 3014451602 | AY54: =IFERROR(INDEX(Vacantes!$C:$C,MATCH(AT54,Vacantes!$A:$A,0)),"") -> 127 | AZ54: =IFERROR(INDEX(Vacantes!$D:$D,MATCH(AT54,Vacantes!$A:$A,0)),"") -> 13 de octubre de 2026 | BA54: =IFERROR(INDEX(Vacantes!$E:$E,MATCH(AT54,Vacantes!$A:$A,0)),"") -> 7:30 a.m. a 11:30 a.m.
A55: linapaolaparralobo15@gmail.com | B55: Lina Paola Parra Lobo | C55: Cédula de ciudadanía | D55: 1031806221 | E55: Mujer | F55: 20 | G55: TRUE | H55: Bogotá | I55: Bogotá | J55: Universidad Jorge Tadeo Lozano | L55: Comercio Internacional | N55: TRUE | O55: FALSE | P55: Avanzado | Q55: Intermedio | R55: Logística | T55: Finanzas Impuestos | W55: Finanzas | AB55: FALSE | AC55: FALSE | AE55: FALSE | AG55: FALSE | AI55: FALSE | AK55: LinkedIn | AL55: CREATÓN | AM55: 46271 | AN55: 0.72023148 | AO55: 313 3998174 | AP55: Calle 147C 99-80, 111161 Bogota, D.C., Colombia | AQ55: DP | AR55: 91.9 | AS55: Santi | AT55: Logística T2 (Safety & DPO T2) | AU55: SI | AV55: OK | AW55: =IF(L55="Otra",IF(M55="","Otra",M55&""),L55&"") -> Comercio Internacional | AX55: =IF(OR(AO55="",AO55=0),"",TRIM(AO55)) -> 313 3998174 | AY55: =IFERROR(INDEX(Vacantes!$C:$C,MATCH(AT55,Vacantes!$A:$A,0)),"") -> 127 | AZ55: =IFERROR(INDEX(Vacantes!$D:$D,MATCH(AT55,Vacantes!$A:$A,0)),"") -> 13 de octubre de 2026 | BA55: =IFERROR(INDEX(Vacantes!$E:$E,MATCH(AT55,Vacantes!$A:$A,0)),"") -> 7:30 a.m. a 11:30 a.m.
A56: tomas101220sandovalr@gmail.com | B56: Tomás Felipe Sandoval Rojas | C56: Cédula de ciudadanía | D56: 1013260603 | E56: Hombre | F56: 20 | G56: TRUE | H56: BOGOTA | I56: Bogotá | J56: Universidad de La Sabana | L56: Ingeniería Industrial | N56: FALSE | O56: FALSE | P56: Avanzado | Q56: Intermedio | R56: Logística | W56: Producción (Operaciones) | X56: Elaboración | AB56: FALSE | AC56: FALSE | AE56: FALSE | AG56: FALSE | AI56: FALSE | AK56: LinkedIn | AL56: CREATÓN | AM56: 46273 | AN56: 0.93543981 | AO56: 315 6071565 | AP56: 110141 Bogota, D.C., Colombia | AQ56: DP | AR56: 95.3 | AS56: Cata | AT56: Logística T2 (Safety & DPO T2) | AU56: SI | AV56: OK | AW56: =IF(L56="Otra",IF(M56="","Otra",M56&""),L56&"") -> Ingeniería Industrial | AX56: =IF(OR(AO56="",AO56=0),"",TRIM(AO56)) -> 315 6071565 | AY56: =IFERROR(INDEX(Vacantes!$C:$C,MATCH(AT56,Vacantes!$A:$A,0)),"") -> 127 | AZ56: =IFERROR(INDEX(Vacantes!$D:$D,MATCH(AT56,Vacantes!$A:$A,0)),"") -> 13 de octubre de 2026 | BA56: =IFERROR(INDEX(Vacantes!$E:$E,MATCH(AT56,Vacantes!$A:$A,0)),"") -> 7:30 a.m. a 11:30 a.m.
A57: juandiperezcris@hotmail.com | B57: Juan Diego Perez Cristancho | C57: Cédula de ciudadanía | D57: 1000708616 | E57: Hombre | F57: 23 | G57: TRUE | H57: Bogota | I57: Bogotá | J57: Universidad de La Sabana | L57: Administración de Empresas | N57: TRUE | O57: FALSE | P57: Avanzado | Q57: Intermedio | R57: Logística | W57: Producción (Operaciones) | X57: Calidad | AB57: FALSE | AC57: FALSE | AE57: FALSE | AG57: FALSE | AI57: FALSE | AK57: Otros | AL57: CREATÓN | AM57: 46261 | AN57: 0.8528125 | AO57: 311 2459346 | AP57: Calle 128A 57C-4, 111111 Bogota, D.C., Colombia | AQ57: DP | AR57: 87.8 | AS57: Cata | AT57: Logística T2 (Safety & DPO T2) | AU57: SI | AV57: OK | AW57: =IF(L57="Otra",IF(M57="","Otra",M57&""),L57&"") -> Administración de Empresas | AX57: =IF(OR(AO57="",AO57=0),"",TRIM(AO57)) -> 311 2459346 | AY57: =IFERROR(INDEX(Vacantes!$C:$C,MATCH(AT57,Vacantes!$A:$A,0)),"") -> 127 | AZ57: =IFERROR(INDEX(Vacantes!$D:$D,MATCH(AT57,Vacantes!$A:$A,0)),"") -> 13 de octubre de 2026 | BA57: =IFERROR(INDEX(Vacantes!$E:$E,MATCH(AT57,Vacantes!$A:$A,0)),"") -> 7:30 a.m. a 11:30 a.m.
A58: wilsiton16ruiz@gmail.com | B58: Wilson Andrés Ruiz Bohórquez | C58: Cédula de ciudadanía | D58: 1031648377 | E58: Hombre | F58: 21 | G58: TRUE | I58: Bogotá | J58: Universidad de La Sabana | L58: Logística | N58: TRUE | O58: FALSE | P58: Avanzado | Q58: Intermedio | R58: Logística | W58: Marketing | AB58: FALSE | AC58: FALSE | AE58: FALSE | AG58: FALSE | AI58: FALSE | AK58: LinkedIn | AL58: CREATÓN | AM58: 46278 | AN58: 0.39740741 | AO58: 0 | AP58: Carrera 48 150A-31, 111156 Bogota, D.C., Colombia | AQ58: DP | AR58: 74.4 | AS58: Cata | AT58: Logística T2 (Safety & DPO T2) | AU58: SI | AV58: OK | AW58: =IF(L58="Otra",IF(M58="","Otra",M58&""),L58&"") -> Logística | AX58: =IF(OR(AO58="",AO58=0),"",TRIM(AO58)) | AY58: =IFERROR(INDEX(Vacantes!$C:$C,MATCH(AT58,Vacantes!$A:$A,0)),"") -> 127 | AZ58: =IFERROR(INDEX(Vacantes!$D:$D,MATCH(AT58,Vacantes!$A:$A,0)),"") -> 13 de octubre de 2026 | BA58: =IFERROR(INDEX(Vacantes!$E:$E,MATCH(AT58,Vacantes!$A:$A,0)),"") -> 7:30 a.m. a 11:30 a.m.
A59: sharitvargas@usantotomas.edu.co | B59: Tatiana Vargas Lara | C59: Cédula de ciudadanía | D59: 1031641717 | E59: Mujer | F59: 21 | G59: TRUE | H59: Bogotá | I59: Bogotá | J59: Universidad Santo Tomás | L59: Ingeniería Industrial | N59: FALSE | O59: FALSE | P59: Intermedio | Q59: Avanzado | R59: Logística | W59: Producción (Operaciones) | X59: Calidad | AB59: FALSE | AC59: FALSE | AE59: FALSE | AG59: FALSE | AI59: FALSE | AK59: Medios Tradicionales | AL59: CREATÓN | AM59: 46269 | AN59: 0.24934028 | AO59: 313 8429527 | AP59: Calle 133 151A-84, 111151 Bogota, D.C., Colombia | AQ59: DP | AR59: 93.8 | AS59: Santi | AT59: Logística T2 (Safety & DPO T2) | AU59: SI | AV59: OK | AW59: =IF(L59="Otra",IF(M59="","Otra",M59&""),L59&"") -> Ingeniería Industrial | AX59: =IF(OR(AO59="",AO59=0),"",TRIM(AO59)) -> 313 8429527 | AY59: =IFERROR(INDEX(Vacantes!$C:$C,MATCH(AT59,Vacantes!$A:$A,0)),"") -> 127 | AZ59: =IFERROR(INDEX(Vacantes!$D:$D,MATCH(AT59,Vacantes!$A:$A,0)),"") -> 13 de octubre de 2026 | BA59: =IFERROR(INDEX(Vacantes!$E:$E,MATCH(AT59,Vacantes!$A:$A,0)),"") -> 7:30 a.m. a 11:30 a.m.
A60: isabellasanin2003@gmail.com | B60: Isabella Sanin Osorio | C60: Cédula de ciudadanía | D60: 1000180082 | E60: Mujer | F60: 22 | G60: TRUE | H60: BOGOTA | I60: Bogotá | J60: Otra | K60: Universidad EAN | L60: Negocios Internacionales | N60: FALSE | O60: FALSE | P60: Avanzado | Q60: Intermedio | R60: Logística | W60: Comunicaciones | AB60: FALSE | AC60: FALSE | AE60: FALSE | AG60: FALSE | AI60: FALSE | AK60: Medios Tradicionales | AL60: CREATÓN | AM60: 46264 | AN60: 0.78413194 | AO60: 3016201098 | AP60: Calle 163 72-61, 111156 Bogota, D.C., Colombia | AQ60: DP | AR60: 87.1 | AS60: Cata | AT60: Logística T2 (Safety & DPO T2) | AU60: SI | AV60: OK | AW60: =IF(L60="Otra",IF(M60="","Otra",M60&""),L60&"") -> Negocios Internacionales | AX60: =IF(OR(AO60="",AO60=0),"",TRIM(AO60)) -> 3016201098 | AY60: =IFERROR(INDEX(Vacantes!$C:$C,MATCH(AT60,Vacantes!$A:$A,0)),"") -> 127 | AZ60: =IFERROR(INDEX(Vacantes!$D:$D,MATCH(AT60,Vacantes!$A:$A,0)),"") -> 13 de octubre de 2026 | BA60: =IFERROR(INDEX(Vacantes!$E:$E,MATCH(AT60,Vacantes!$A:$A,0)),"") -> 7:30 a.m. a 11:30 a.m.
A61: jeidyyulianabeltrantriana@gmail.com | B61: Jeidy Yuliana Beltran Triana | C61: Cédula de ciudadanía | D61: 1014736816 | E61: Mujer | F61: 22 | G61: TRUE | H61: CHÍA | I61: Bogotá | J61: Universidad Militar Nueva Granada | L61: Relaciones Internacionales | N61: FALSE | O61: FALSE | P61: Básico | Q61: Intermedio | R61: Asuntos corporativos | W61: Logística | AB61: FALSE | AC61: FALSE | AE61: FALSE | AG61: FALSE | AI61: FALSE | AK61: LinkedIn | AL61: CREATÓN | AM61: 46261 | AN61: 0.55489583 | AO61: 310 3765539 | AP61: Calle 4 11-06, 250001 Chía, Colombia | AQ61: DP | AR61: 89.1 | AS61: Cata | AT61: People Support 1 | AU61: SI | AV61: OK | AW61: =IF(L61="Otra",IF(M61="","Otra",M61&""),L61&"") -> Relaciones Internacionales | AX61: =IF(OR(AO61="",AO61=0),"",TRIM(AO61)) -> 310 3765539 | AY61: =IFERROR(INDEX(Vacantes!$C:$C,MATCH(AT61,Vacantes!$A:$A,0)),"") -> 127 | AZ61: =IFERROR(INDEX(Vacantes!$D:$D,MATCH(AT61,Vacantes!$A:$A,0)),"") -> 13 de octubre de 2026 | BA61: =IFERROR(INDEX(Vacantes!$E:$E,MATCH(AT61,Vacantes!$A:$A,0)),"") -> 7:30 a.m. a 11:30 a.m.
A62: karenlizethlopezcastro@gmail.com | B62: Karen Lizeth López Castro | C62: Cédula de ciudadanía | D62: 1077142999 | E62: Mujer | F62: 21 | G62: TRUE | I62: Bogotá | J62: Universidad Santo Tomás | L62: Psicología | N62: FALSE | O62: FALSE | P62: Intermedio | Q62: Básico | R62: Talento | W62: Marketing | Z62: Atracción de Talento y Marca Empleadora | AB62: FALSE | AC62: FALSE | AE62: FALSE | AG62: FALSE | AI62: FALSE | AK62: Otros | AL62: CREATÓN | AM62: 46257 | AN62: 0.84240741 | AO62: 322 8756281 | AP62: Carrera 54 167-56, 111156 Bogota, D.C., Colombia | AQ62: DP | AR62: 90.9 | AS62: Cata | AT62: People Support 1 | AU62: SI | AV62: OK | AW62: =IF(L62="Otra",IF(M62="","Otra",M62&""),L62&"") -> Psicología | AX62: =IF(OR(AO62="",AO62=0),"",TRIM(AO62)) -> 322 8756281 | AY62: =IFERROR(INDEX(Vacantes!$C:$C,MATCH(AT62,Vacantes!$A:$A,0)),"") -> 127 | AZ62: =IFERROR(INDEX(Vacantes!$D:$D,MATCH(AT62,Vacantes!$A:$A,0)),"") -> 13 de octubre de 2026 | BA62: =IFERROR(INDEX(Vacantes!$E:$E,MATCH(AT62,Vacantes!$A:$A,0)),"") -> 7:30 a.m. a 11:30 a.m.
A63: veronica.salamanca028@gmail.com | B63: VERONICA SALAMANCA BECERRA | C63: Cédula de ciudadanía | D63: 1057571944 | E63: Mujer | F63: 22 | G63: TRUE | H63: SOGAMOSO | I63: Bogotá | J63: Universidad Pedagógica y Tecnológica de Colombia | L63: Ingeniería Industrial | N63: FALSE | O63: FALSE | P63: Intermedio | Q63: Intermedio | R63: Talento | W63: Comunicaciones | Z63: Support | AB63: FALSE | AC63: FALSE | AE63: FALSE | AG63: FALSE | AI63: FALSE | AK63: Instagram | AL63: CREATÓN | AM63: 46269 | AN63: 0.24943287 | AO63: 313 8737070 | AP63: Calle 23 10-14, 152210 Sogamoso, Colombia | AQ63: DP | AR63: 83.2 | AS63: Cata | AT63: People Support 1 | AU63: SI | AV63: OK | AW63: =IF(L63="Otra",IF(M63="","Otra",M63&""),L63&"") -> Ingeniería Industrial | AX63: =IF(OR(AO63="",AO63=0),"",TRIM(AO63)) -> 313 8737070 | AY63: =IFERROR(INDEX(Vacantes!$C:$C,MATCH(AT63,Vacantes!$A:$A,0)),"") -> 127 | AZ63: =IFERROR(INDEX(Vacantes!$D:$D,MATCH(AT63,Vacantes!$A:$A,0)),"") -> 13 de octubre de 2026 | BA63: =IFERROR(INDEX(Vacantes!$E:$E,MATCH(AT63,Vacantes!$A:$A,0)),"") -> 7:30 a.m. a 11:30 a.m.
A64: ana.castromora9@gmail.com | B64: Ana Maria Elena Castro Morales | C64: Cédula de ciudadanía | D64: 1027280496 | E64: Mujer | F64: 22 | G64: TRUE | H64: Bogotá | I64: Bogotá | J64: Universidad Externado de Colombia | L64: Comunicación social | N64: FALSE | O64: FALSE | P64: Avanzado | Q64: Básico | R64: Marketing | U64: Atracción de Talento y Marca Empleadora | W64: Talento | AB64: FALSE | AC64: FALSE | AE64: FALSE | AG64: FALSE | AI64: FALSE | AK64: LinkedIn | AL64: CREATÓN | AM64: 46276 | AN64: 0.59631944 | AO64: 315 0190006 | AP64: Calle 148 99-38, 111161 Bogota, D.C., Colombia | AQ64: DP | AR64: 76.9 | AS64: Santi | AT64: People Support 1 | AU64: SI | AV64: OK | AW64: =IF(L64="Otra",IF(M64="","Otra",M64&""),L64&"") -> Comunicación social | AX64: =IF(OR(AO64="",AO64=0),"",TRIM(AO64)) -> 315 0190006 | AY64: =IFERROR(INDEX(Vacantes!$C:$C,MATCH(AT64,Vacantes!$A:$A,0)),"") -> 127 | AZ64: =IFERROR(INDEX(Vacantes!$D:$D,MATCH(AT64,Vacantes!$A:$A,0)),"") -> 13 de octubre de 2026 | BA64: =IFERROR(INDEX(Vacantes!$E:$E,MATCH(AT64,Vacantes!$A:$A,0)),"") -> 7:30 a.m. a 11:30 a.m.
A65: am.diazv12@uniandes.edu.co | B65: Ashlie Melissa Díaz Villanueva | C65: Cédula de ciudadanía | D65: 1109186833 | E65: Mujer | F65: 20 | G65: TRUE | I65: Bogotá | J65: Universidad de los Andes | L65: Psicología | N65: TRUE | O65: FALSE | P65: Intermedio | Q65: Básico | R65: Talento | U65: Support | W65: Talento | Z65: Atracción de Talento y Marca Empleadora | AB65: FALSE | AC65: FALSE | AE65: FALSE | AG65: FALSE | AI65: FALSE | AK65: LinkedIn | AL65: CREATÓN | AM65: 46277 | AN65: 0.49733796 | AO65: 3197399170 | AP65: Carrera 55A 188-41, 111166 Bogota, D.C., Colombia | AQ65: DP | AR65: 96.7 | AS65: Cata | AT65: People Support 1 | AU65: SI | AV65: OK | AW65: =IF(L65="Otra",IF(M65="","Otra",M65&""),L65&"") -> Psicología | AX65: =IF(OR(AO65="",AO65=0),"",TRIM(AO65)) -> 3197399170 | AY65: =IFERROR(INDEX(Vacantes!$C:$C,MATCH(AT65,Vacantes!$A:$A,0)),"") -> 127 | AZ65: =IFERROR(INDEX(Vacantes!$D:$D,MATCH(AT65,Vacantes!$A:$A,0)),"") -> 13 de octubre de 2026 | BA65: =IFERROR(INDEX(Vacantes!$E:$E,MATCH(AT65,Vacantes!$A:$A,0)),"") -> 7:30 a.m. a 11:30 a.m.
A66: lauraosorio1422@gmail.com | B66: Laura Sofía Osorio Morales | C66: Cédula de ciudadanía | D66: 1013256959 | E66: Mujer | F66: 22 | G66: TRUE | H66: BOGOTA | I66: Bogotá | J66: Universidad de La Sabana | L66: Administración de Empresas | N66: FALSE | O66: FALSE | P66: Avanzado | Q66: Básico | R66: Marketing | U66: Support | W66: Talento | AB66: FALSE | AC66: FALSE | AE66: FALSE | AG66: FALSE | AI66: FALSE | AK66: LinkedIn | AL66: CREATÓN | AM66: 46261 | AN66: 0.89310185 | AO66: 3123483364 | AP66: Calle 146 17-88, 110121 Bogota, D.C., Colombia | AQ66: DP | AR66: 78.4 | AS66: Cata | AT66: People Support 1 | AU66: SI | AV66: OK | AW66: =IF(L66="Otra",IF(M66="","Otra",M66&""),L66&"") -> Administración de Empresas | AX66: =IF(OR(AO66="",AO66=0),"",TRIM(AO66)) -> 3123483364 | AY66: =IFERROR(INDEX(Vacantes!$C:$C,MATCH(AT66,Vacantes!$A:$A,0)),"") -> 127 | AZ66: =IFERROR(INDEX(Vacantes!$D:$D,MATCH(AT66,Vacantes!$A:$A,0)),"") -> 13 de octubre de 2026 | BA66: =IFERROR(INDEX(Vacantes!$E:$E,MATCH(AT66,Vacantes!$A:$A,0)),"") -> 7:30 a.m. a 11:30 a.m.
A67: davidortisanchez@gmail.com | B67: David Francisco Ortiz Sanchez | C67: Cédula de ciudadanía | D67: 1019153214 | E67: Hombre | F67: 26 | G67: TRUE | H67: BOGOTA | I67: Bogotá | J67: Universidad Nacional de Colombia | L67: Administración de Empresas | N67: FALSE | O67: FALSE | P67: Intermedio | Q67: Intermedio | R67: Talento | W67: Marketing | Z67: Atracción de Talento y Marca Empleadora | AB67: FALSE | AC67: FALSE | AE67: FALSE | AG67: FALSE | AI67: FALSE | AK67: Instagram | AL67: CREATÓN | AM67: 46265 | AN67: 0.56326389 | AO67: 302 2352387 | AP67: Carrera 136A Diagonal 151B-52, 111161 Bogota, D.C., Colombia | AQ67: DP | AR67: 82.6 | AS67: Cata | AT67: People Support 1 | AU67: SI | AV67: OK | AW67: =IF(L67="Otra",IF(M67="","Otra",M67&""),L67&"") -> Administración de Empresas | AX67: =IF(OR(AO67="",AO67=0),"",TRIM(AO67)) -> 302 2352387 | AY67: =IFERROR(INDEX(Vacantes!$C:$C,MATCH(AT67,Vacantes!$A:$A,0)),"") -> 127 | AZ67: =IFERROR(INDEX(Vacantes!$D:$D,MATCH(AT67,Vacantes!$A:$A,0)),"") -> 13 de octubre de 2026 | BA67: =IFERROR(INDEX(Vacantes!$E:$E,MATCH(AT67,Vacantes!$A:$A,0)),"") -> 7:30 a.m. a 11:30 a.m.
A68: le.ramirezd1@uniandes.edu.co | B68: Leonardo Enrique Ramírez Doncel | C68: Cédula de ciudadanía | D68: 1011085214 | E68: Hombre | F68: 21 | G68: TRUE | H68: BOGOTA | I68: Bogotá | J68: Universidad de los Andes | L68: Psicología | N68: FALSE | O68: FALSE | P68: Intermedio | Q68: Intermedio | R68: Talento | W68: Marketing | Z68: Atracción de Talento y Marca Empleadora | AB68: FALSE | AC68: FALSE | AE68: FALSE | AG68: FALSE | AI68: FALSE | AK68: Instagram | AL68: CREATÓN | AM68: 46278 | AN68: 0.5109838 | AO68: 323 2300003 | AP68: Carrera 4A 24-37, 110311 Bogota, D.C., Colombia | AQ68: DP | AR68: 78.8 | AS68: Cata | AT68: People Support 1 | AU68: SI | AV68: OK | AW68: =IF(L68="Otra",IF(M68="","Otra",M68&""),L68&"") -> Psicología | AX68: =IF(OR(AO68="",AO68=0),"",TRIM(AO68)) -> 323 2300003 | AY68: =IFERROR(INDEX(Vacantes!$C:$C,MATCH(AT68,Vacantes!$A:$A,0)),"") -> 127 | AZ68: =IFERROR(INDEX(Vacantes!$D:$D,MATCH(AT68,Vacantes!$A:$A,0)),"") -> 13 de octubre de 2026 | BA68: =IFERROR(INDEX(Vacantes!$E:$E,MATCH(AT68,Vacantes!$A:$A,0)),"") -> 7:30 a.m. a 11:30 a.m.
A69: davidpardo.0627@gmail.com | B69: David Alejandro Pardo Niño | C69: Cédula de ciudadanía | D69: 1023872170 | E69: Hombre | F69: 21 | G69: TRUE | H69: BOGOTA | I69: Bogotá | J69: Otra | K69: Universidad Colegio Mayor De Cundinamarca | L69: Administración de Empresas | N69: TRUE | O69: FALSE | P69: Intermedio | Q69: Avanzado | R69: Talento | W69: Marketing | Z69: Atracción de Talento y Marca Empleadora | AB69: FALSE | AC69: FALSE | AE69: FALSE | AG69: FALSE | AI69: FALSE | AK69: TikTok | AL69: CREATÓN | AM69: 46277 | AN69: 0.74820602 | AO69: 313 3567458 | AP69: Calle 38 1, Soacha, Colombia | AQ69: DP | AR69: 73.1 | AS69: Cata | AT69: People Support 1 | AU69: SI | AV69: OK | AW69: =IF(L69="Otra",IF(M69="","Otra",M69&""),L69&"") -> Administración de Empresas | AX69: =IF(OR(AO69="",AO69=0),"",TRIM(AO69)) -> 313 3567458 | AY69: =IFERROR(INDEX(Vacantes!$C:$C,MATCH(AT69,Vacantes!$A:$A,0)),"") -> 127 | AZ69: =IFERROR(INDEX(Vacantes!$D:$D,MATCH(AT69,Vacantes!$A:$A,0)),"") -> 13 de octubre de 2026 | BA69: =IFERROR(INDEX(Vacantes!$E:$E,MATCH(AT69,Vacantes!$A:$A,0)),"") -> 7:30 a.m. a 11:30 a.m.
A70: adrianacastillo612@gmail.com | B70: Adriana carolina Castillo | C70: Cédula de ciudadanía | D70: 1001309326 | E70: Mujer | F70: 26 | G70: TRUE | H70: Bogotá | I70: Bogotá | J70: Universidad de La Sabana | L70: Psicología | N70: FALSE | O70: FALSE | P70: Intermedio | Q70: Intermedio | R70: Talento | U70: Atracción de Talento y Marca Empleadora | W70: Talento | Z70: Compensación y Beneficios | AB70: FALSE | AC70: FALSE | AE70: FALSE | AG70: FALSE | AI70: FALSE | AK70: LinkedIn | AL70: CREATÓN | AM70: 46277 | AN70: 0.53759259 | AO70: 3183529601 | AP70: Conjunto Residencial Caminos de la Esperanza, 111151 Bogota, D.C., Colombia | AQ70: DP | AR70: 70.7 | AS70: Cata | AT70: People Support 1 | AU70: SI | AV70: OK | AW70: =IF(L70="Otra",IF(M70="","Otra",M70&""),L70&"") -> Psicología | AX70: =IF(OR(AO70="",AO70=0),"",TRIM(AO70)) -> 3183529601 | AY70: =IFERROR(INDEX(Vacantes!$C:$C,MATCH(AT70,Vacantes!$A:$A,0)),"") -> 127 | AZ70: =IFERROR(INDEX(Vacantes!$D:$D,MATCH(AT70,Vacantes!$A:$A,0)),"") -> 13 de octubre de 2026 | BA70: =IFERROR(INDEX(Vacantes!$E:$E,MATCH(AT70,Vacantes!$A:$A,0)),"") -> 7:30 a.m. a 11:30 a.m.
A71: nasly.hernandez@hotmail.com | B71: Nasly Shajira Hernandez Riveros | C71: Cédula de ciudadanía | D71: 1021671198 | E71: Mujer | F71: 20 | G71: TRUE | H71: Bogotá | I71: Bogotá | J71: Universidad Piloto de Colombia | L71: Psicología | N71: TRUE | O71: FALSE | P71: Intermedio | Q71: Intermedio | R71: Talento | W71: Asuntos Corporativos | Z71: Atracción de Talento y Marca Empleadora | AB71: FALSE | AC71: FALSE | AE71: FALSE | AG71: FALSE | AI71: FALSE | AK71: Otros | AL71: CREATÓN | AM71: 46264 | AN71: 0.43060185 | AO71: 318 7876579 | AP71: Calle 6A 18-33, 111411 Bogota, D.C., Colombia | AQ71: DP | AR71: 87.5 | AS71: Cata | AT71: People Support 2 | AU71: SI | AV71: OK | AW71: =IF(L71="Otra",IF(M71="","Otra",M71&""),L71&"") -> Psicología | AX71: =IF(OR(AO71="",AO71=0),"",TRIM(AO71)) -> 318 7876579 | AY71: =IFERROR(INDEX(Vacantes!$C:$C,MATCH(AT71,Vacantes!$A:$A,0)),"") -> 127 | AZ71: =IFERROR(INDEX(Vacantes!$D:$D,MATCH(AT71,Vacantes!$A:$A,0)),"") -> 13 de octubre de 2026 | BA71: =IFERROR(INDEX(Vacantes!$E:$E,MATCH(AT71,Vacantes!$A:$A,0)),"") -> 1:30 p.m. a 5:30 p.m.
A72: mariajimenabecerra@gmail.com | B72: Maria Jimena Becerra Beltran | C72: Cédula de ciudadanía | D72: 1019602144 | E72: Mujer | F72: 22 | G72: TRUE | H72: BOGOTA | I72: Bogotá | J72: Universidad del Rosario | L72: Psicología | N72: FALSE | O72: FALSE | P72: Avanzado | Q72: Intermedio | R72: Talento | W72: Comunicaciones | Z72: Atracción de Talento y Marca Empleadora | AB72: FALSE | AC72: FALSE | AE72: FALSE | AG72: FALSE | AI72: FALSE | AK72: LinkedIn | AL72: CREATÓN | AM72: 46273 | AN72: 0.61799769 | AO72: 300 8890118 | AP72: Calle 134A 22-6, 110121 Bogota, D.C., Colombia | AQ72: DP | AR72: 88.2 | AS72: Cata | AT72: People Support 2 | AU72: SI | AV72: OK | AW72: =IF(L72="Otra",IF(M72="","Otra",M72&""),L72&"") -> Psicología | AX72: =IF(OR(AO72="",AO72=0),"",TRIM(AO72)) -> 300 8890118 | AY72: =IFERROR(INDEX(Vacantes!$C:$C,MATCH(AT72,Vacantes!$A:$A,0)),"") -> 127 | AZ72: =IFERROR(INDEX(Vacantes!$D:$D,MATCH(AT72,Vacantes!$A:$A,0)),"") -> 13 de octubre de 2026 | BA72: =IFERROR(INDEX(Vacantes!$E:$E,MATCH(AT72,Vacantes!$A:$A,0)),"") -> 1:30 p.m. a 5:30 p.m.
A73: mariajose.cubides.a@gmail.com | B73: María José Cubides Alba | C73: Cédula de ciudadanía | D73: 1019603862 | E73: Mujer | F73: 21 | G73: TRUE | H73: BOGOTA DC | I73: Bogotá | J73: Universidad Nacional de Colombia | L73: Administración de Empresas | N73: TRUE | O73: FALSE | P73: Intermedio | Q73: Intermedio | R73: Talento | W73: Logística | Z73: Atracción de Talento y Marca Empleadora | AB73: FALSE | AC73: FALSE | AE73: FALSE | AG73: FALSE | AI73: FALSE | AK73: Otros | AL73: CREATÓN | AM73: 46265 | AN73: 0.69452546 | AO73: 305 3502374 | AP73: Calle 102A, Bogota, D.C., Colombia | AQ73: DP | AR73: 81.1 | AS73: Cata | AT73: People Support 2 | AU73: SI | AV73: OK | AW73: =IF(L73="Otra",IF(M73="","Otra",M73&""),L73&"") -> Administración de Empresas | AX73: =IF(OR(AO73="",AO73=0),"",TRIM(AO73)) -> 305 3502374 | AY73: =IFERROR(INDEX(Vacantes!$C:$C,MATCH(AT73,Vacantes!$A:$A,0)),"") -> 127 | AZ73: =IFERROR(INDEX(Vacantes!$D:$D,MATCH(AT73,Vacantes!$A:$A,0)),"") -> 13 de octubre de 2026 | BA73: =IFERROR(INDEX(Vacantes!$E:$E,MATCH(AT73,Vacantes!$A:$A,0)),"") -> 1:30 p.m. a 5:30 p.m.
A74: laurascortesg@gmail.com | B74: Laura Cortés García | C74: Cédula de ciudadanía | D74: 1014657993 | E74: Mujer | F74: 22 | G74: TRUE | H74: Bogotá | I74: Bogotá | J74: Universidad del Bosque | L74: Psicología | N74: TRUE | O74: FALSE | P74: Intermedio | Q74: Intermedio | R74: Marketing | U74: Atracción de Talento y Marca Empleadora | W74: Talento | AB74: FALSE | AC74: FALSE | AE74: FALSE | AG74: FALSE | AI74: FALSE | AK74: Instagram | AL74: CREATÓN | AM74: 46277 | AN74: 0.39241898 | AO74: 323 8265677 | AP74: Calle 7-90, 110811 Bogota, D.C., Colombia | AQ74: DP | AR74: 93.4 | AS74: Cata | AT74: People Support 2 | AU74: SI | AV74: OK | AW74: =IF(L74="Otra",IF(M74="","Otra",M74&""),L74&"") -> Psicología | AX74: =IF(OR(AO74="",AO74=0),"",TRIM(AO74)) -> 323 8265677 | AY74: =IFERROR(INDEX(Vacantes!$C:$C,MATCH(AT74,Vacantes!$A:$A,0)),"") -> 127 | AZ74: =IFERROR(INDEX(Vacantes!$D:$D,MATCH(AT74,Vacantes!$A:$A,0)),"") -> 13 de octubre de 2026 | BA74: =IFERROR(INDEX(Vacantes!$E:$E,MATCH(AT74,Vacantes!$A:$A,0)),"") -> 1:30 p.m. a 5:30 p.m.
A75: isacano.icca@gmail.com | B75: Isabella Cano | C75: Cédula de ciudadanía | D75: 1034988548 | E75: Mujer | F75: 20 | G75: TRUE | H75: CALI | I75: Bogotá | J75: Pontificia Universidad Javeriana| Cali | L75: Psicología | N75: FALSE | O75: FALSE | P75: Avanzado | Q75: Intermedio | R75: Talento | U75: Compensación y Beneficios | W75: Talento | Z75: Atracción de Talento y Marca Empleadora | AB75: FALSE | AC75: TRUE | AE75: FALSE | AG75: FALSE | AH75: Hermano - Nicolas Cano Villegas | AI75: FALSE | AK75: Instagram | AL75: CREATÓN | AM75: 46265 | AN75: 0.92298611 | AO75: 318 5936496 | AP75: Carrera 115, Cali, Colombia | AQ75: DP | AR75: 80.8 | AS75: Santi | AT75: People Support 2 | AU75: SI | AV75: OK | AW75: =IF(L75="Otra",IF(M75="","Otra",M75&""),L75&"") -> Psicología | AX75: =IF(OR(AO75="",AO75=0),"",TRIM(AO75)) -> 318 5936496 | AY75: =IFERROR(INDEX(Vacantes!$C:$C,MATCH(AT75,Vacantes!$A:$A,0)),"") -> 127 | AZ75: =IFERROR(INDEX(Vacantes!$D:$D,MATCH(AT75,Vacantes!$A:$A,0)),"") -> 13 de octubre de 2026 | BA75: =IFERROR(INDEX(Vacantes!$E:$E,MATCH(AT75,Vacantes!$A:$A,0)),"") -> 1:30 p.m. a 5:30 p.m.
A76: majomorenons@gmail.com | B76: Maria Jose Moreno Noriega | C76: Cédula de ciudadanía | D76: 1011082341 | E76: Mujer | F76: 21 | G76: TRUE | I76: Bogotá | J76: Universidad del Rosario | L76: Comunicación social | N76: TRUE | O76: FALSE | P76: Avanzado | Q76: Intermedio | R76: Comunicaciones | U76: Atracción de Talento y Marca Empleadora | W76: Talento | AB76: FALSE | AC76: FALSE | AE76: FALSE | AG76: FALSE | AI76: FALSE | AK76: Instagram | AL76: CREATÓN | AM76: 46255 | AN76: 0.41466435 | AO76: 310 5545269 | AP76: Calle 159 54-35, 111156 Bogota, D.C., Colombia | AQ76: DP | AR76: 81.7 | AS76: Cata | AT76: People Support 2 | AU76: SI | AV76: OK | AW76: =IF(L76="Otra",IF(M76="","Otra",M76&""),L76&"") -> Comunicación social | AX76: =IF(OR(AO76="",AO76=0),"",TRIM(AO76)) -> 310 5545269 | AY76: =IFERROR(INDEX(Vacantes!$C:$C,MATCH(AT76,Vacantes!$A:$A,0)),"") -> 127 | AZ76: =IFERROR(INDEX(Vacantes!$D:$D,MATCH(AT76,Vacantes!$A:$A,0)),"") -> 13 de octubre de 2026 | BA76: =IFERROR(INDEX(Vacantes!$E:$E,MATCH(AT76,Vacantes!$A:$A,0)),"") -> 1:30 p.m. a 5:30 p.m.
A77: 7890thunder@gmail.com | B77: Mariana López Bareño | C77: Cédula de ciudadanía | D77: 1007557956 | E77: Mujer | F77: 23 | G77: TRUE | H77: BOGOTA | I77: Bogotá | J77: Otra | K77: Universidad Ean | L77: Comunicación social | N77: FALSE | O77: FALSE | P77: Intermedio | Q77: Intermedio | R77: Comunicaciones | W77: Marketing | AB77: FALSE | AC77: FALSE | AE77: FALSE | AG77: FALSE | AI77: FALSE | AK77: Instagram | AL77: CREATÓN | AM77: 46275 | AN77: 0.52508102 | AO77: 313 2713653 | AP77: Calle 128A 54B-56, 111111 Bogota, D.C., Colombia | AQ77: DP | AR77: 89.2 | AS77: Cata | AT77: Talento Regional Centro | AU77: SI | AV77: OK | AW77: =IF(L77="Otra",IF(M77="","Otra",M77&""),L77&"") -> Comunicación social | AX77: =IF(OR(AO77="",AO77=0),"",TRIM(AO77)) -> 313 2713653 | AY77: =IFERROR(INDEX(Vacantes!$C:$C,MATCH(AT77,Vacantes!$A:$A,0)),"") -> Regional Centro | AZ77: =IFERROR(INDEX(Vacantes!$D:$D,MATCH(AT77,Vacantes!$A:$A,0)),"") -> 13 de octubre de 2026 | BA77: =IFERROR(INDEX(Vacantes!$E:$E,MATCH(AT77,Vacantes!$A:$A,0)),"") -> 12:30 p.m. a 4:00 p.m.
A78: valemarticas22@gmail.com | B78: Valentina Martinez Castro | C78: Cédula de ciudadanía | D78: 1014662117 | E78: Mujer | F78: 20 | G78: TRUE | H78: Bogotá | I78: Bogotá | J78: Pontificia Universidad Javeriana | L78: Administración de Empresas | N78: FALSE | O78: FALSE | P78: Avanzado | Q78: Avanzado | R78: Marketing | W78: Asuntos Corporativos | AB78: FALSE | AC78: FALSE | AE78: FALSE | AG78: FALSE | AI78: FALSE | AK78: LinkedIn | AL78: CREATÓN | AM78: 46263 | AN78: 0.50123843 | AO78: 304 6772464 | AP78: Calle 86A 69T-81, 111021 Bogota, D.C., Colombia | AQ78: DP | AR78: 91.1 | AS78: Cata | AT78: Talento Regional Centro | AU78: SI | AV78: OK | AW78: =IF(L78="Otra",IF(M78="","Otra",M78&""),L78&"") -> Administración de Empresas | AX78: =IF(OR(AO78="",AO78=0),"",TRIM(AO78)) -> 304 6772464 | AY78: =IFERROR(INDEX(Vacantes!$C:$C,MATCH(AT78,Vacantes!$A:$A,0)),"") -> Regional Centro | AZ78: =IFERROR(INDEX(Vacantes!$D:$D,MATCH(AT78,Vacantes!$A:$A,0)),"") -> 13 de octubre de 2026 | BA78: =IFERROR(INDEX(Vacantes!$E:$E,MATCH(AT78,Vacantes!$A:$A,0)),"") -> 12:30 p.m. a 4:00 p.m.
A79: orjuelagabriela20@gmail.com | B79: Gabriela Orjuela | C79: Cédula de ciudadanía | D79: 1025060093 | E79: Mujer | F79: 22 | G79: TRUE | H79: Bogotá | I79: Bogotá | J79: Universidad del Rosario | L79: Diseño Gráfico | N79: FALSE | O79: FALSE | P79: Avanzado | Q79: Intermedio | R79: Comunicaciones | W79: Marketing | AB79: FALSE | AC79: FALSE | AE79: FALSE | AG79: FALSE | AI79: FALSE | AK79: Instagram | AL79: CREATÓN | AM79: 46278 | AN79: 0.73040509 | AO79: 300 3424911 | AP79: Torreladera Bosque Reservado, 110131 Bogota, D.C., Colombia | AQ79: DP | AR79: 73.2 | AS79: Cata | AT79: Talento Regional Centro | AU79: SI | AV79: OK | AW79: =IF(L79="Otra",IF(M79="","Otra",M79&""),L79&"") -> Diseño Gráfico | AX79: =IF(OR(AO79="",AO79=0),"",TRIM(AO79)) -> 300 3424911 | AY79: =IFERROR(INDEX(Vacantes!$C:$C,MATCH(AT79,Vacantes!$A:$A,0)),"") -> Regional Centro | AZ79: =IFERROR(INDEX(Vacantes!$D:$D,MATCH(AT79,Vacantes!$A:$A,0)),"") -> 13 de octubre de 2026 | BA79: =IFERROR(INDEX(Vacantes!$E:$E,MATCH(AT79,Vacantes!$A:$A,0)),"") -> 12:30 p.m. a 4:00 p.m.
A80: andresfelipeforerotoro7@gmail.com | B80: Andres Felipe Forero Toro | C80: Cédula de ciudadanía | D80: 1000127209 | E80: Hombre | F80: 25 | G80: TRUE | H80: BOGOTÁ | I80: Bogotá | J80: Universidad Distrital Francisco José de Caldas | L80: Comunicación social | N80: FALSE | O80: FALSE | P80: Básico | Q80: Intermedio | R80: Comunicaciones | W80: Marketing | AB80: FALSE | AC80: FALSE | AE80: FALSE | AG80: FALSE | AI80: FALSE | AK80: Otros | AL80: CREATÓN | AM80: 46261 | AN80: 0.39112269 | AO80: 322 9603522 | AP80: Carrera 78B 65J S-50, 110741 Bogota, D.C., Colombia | AQ80: DP | AR80: 88.3 | AS80: Cata | AT80: Talento Regional Centro | AU80: SI | AV80: OK | AW80: =IF(L80="Otra",IF(M80="","Otra",M80&""),L80&"") -> Comunicación social | AX80: =IF(OR(AO80="",AO80=0),"",TRIM(AO80)) -> 322 9603522 | AY80: =IFERROR(INDEX(Vacantes!$C:$C,MATCH(AT80,Vacantes!$A:$A,0)),"") -> Regional Centro | AZ80: =IFERROR(INDEX(Vacantes!$D:$D,MATCH(AT80,Vacantes!$A:$A,0)),"") -> 13 de octubre de 2026 | BA80: =IFERROR(INDEX(Vacantes!$E:$E,MATCH(AT80,Vacantes!$A:$A,0)),"") -> 12:30 p.m. a 4:00 p.m.
A81: danielaromanom@gmail.com | B81: Daniela Roman | C81: Cédula de ciudadanía | D81: 1000698286 | E81: Mujer | F81: 23 | G81: TRUE | H81: Bogota | I81: Bogotá | J81: Universidad de La Sabana | L81: Comunicación social | N81: FALSE | O81: FALSE | P81: Intermedio | Q81: Intermedio | R81: Comunicaciones | W81: Marketing | AB81: FALSE | AC81: FALSE | AE81: FALSE | AG81: FALSE | AI81: FALSE | AK81: LinkedIn | AL81: CREATÓN | AM81: 46277 | AN81: 0.6465162 | AO81: 3163285338 | AP81: Cedritos, Bogota, D.C., Colombia | AQ81: DP | AR81: 75.9 | AS81: Cata | AT81: Talento Regional Centro | AU81: SI | AV81: OK | AW81: =IF(L81="Otra",IF(M81="","Otra",M81&""),L81&"") -> Comunicación social | AX81: =IF(OR(AO81="",AO81=0),"",TRIM(AO81)) -> 3163285338 | AY81: =IFERROR(INDEX(Vacantes!$C:$C,MATCH(AT81,Vacantes!$A:$A,0)),"") -> Regional Centro | AZ81: =IFERROR(INDEX(Vacantes!$D:$D,MATCH(AT81,Vacantes!$A:$A,0)),"") -> 13 de octubre de 2026 | BA81: =IFERROR(INDEX(Vacantes!$E:$E,MATCH(AT81,Vacantes!$A:$A,0)),"") -> 12:30 p.m. a 4:00 p.m.
A82: paulargb2004@hotmail.com | B82: Paula Andrea Rodriguez Gomez | C82: Cédula de ciudadanía | D82: 1146635183 | E82: Mujer | F82: 21 | G82: TRUE | H82: Bogota | I82: Bogotá | J82: Universidad de los Andes | L82: Administración de Empresas | N82: FALSE | O82: FALSE | P82: Avanzado | Q82: Intermedio | R82: Marketing | W82: Comunicaciones | AB82: FALSE | AC82: FALSE | AE82: FALSE | AG82: FALSE | AI82: FALSE | AK82: LinkedIn | AL82: CREATÓN | AM82: 46278 | AN82: 0.63690972 | AO82: 301 5595946 | AP82: Calle 137 12B-70, 110121 Bogota, D.C., Colombia | AQ82: DP | AR82: 72.6 | AS82: Cata | AT82: Talento Regional Centro | AU82: SI | AV82: OK | AW82: =IF(L82="Otra",IF(M82="","Otra",M82&""),L82&"") -> Administración de Empresas | AX82: =IF(OR(AO82="",AO82=0),"",TRIM(AO82)) -> 301 5595946 | AY82: =IFERROR(INDEX(Vacantes!$C:$C,MATCH(AT82,Vacantes!$A:$A,0)),"") -> Regional Centro | AZ82: =IFERROR(INDEX(Vacantes!$D:$D,MATCH(AT82,Vacantes!$A:$A,0)),"") -> 13 de octubre de 2026 | BA82: =IFERROR(INDEX(Vacantes!$E:$E,MATCH(AT82,Vacantes!$A:$A,0)),"") -> 12:30 p.m. a 4:00 p.m.
A83: danpame1219@gmail.com | B83: Daniel Patiño Mejia | C83: Cédula de ciudadanía | D83: 1076905047 | E83: Hombre | F83: 20 | G83: TRUE | I83: Bogotá | J83: Escuela Colombiana de Ingeniería Julio Garavito | L83: Ingeniería de Sistemas | N83: TRUE | O83: FALSE | P83: Avanzado | Q83: Básico | R83: Tecnología | W83: Asuntos Corporativos | AB83: FALSE | AC83: FALSE | AE83: FALSE | AG83: FALSE | AI83: FALSE | AK83: Otros | AL83: CREATÓN | AM83: 46256 | AN83: 0.42581019 | AO83: 311 5244990 | AP83: Carrera 74 163-33, 111156 Bogota, D.C., Colombia | AQ83: DP | AR83: 97.4 | AS83: Cata | AT83: Tecnología (JR Data Scientist) | AU83: SI | AV83: OK | AW83: =IF(L83="Otra",IF(M83="","Otra",M83&""),L83&"") -> Ingeniería de Sistemas | AX83: =IF(OR(AO83="",AO83=0),"",TRIM(AO83)) -> 311 5244990 | AY83: =IFERROR(INDEX(Vacantes!$C:$C,MATCH(AT83,Vacantes!$A:$A,0)),"") -> 127 | AZ83: =IFERROR(INDEX(Vacantes!$D:$D,MATCH(AT83,Vacantes!$A:$A,0)),"") -> 13 de octubre de 2026 | BA83: =IFERROR(INDEX(Vacantes!$E:$E,MATCH(AT83,Vacantes!$A:$A,0)),"") -> 7:30 a.m. a 11:30 a.m.
A84: mariayr501@gmail.com | B84: Maria Paula Rodriguez Muñoz | C84: Cédula de ciudadanía | D84: 1016592928 | E84: Mujer | F84: 22 | G84: TRUE | H84: Bogotá, D.C. | I84: Bogotá | J84: Escuela Colombiana de Ingeniería Julio Garavito | L84: Ingeniería de Sistemas | N84: TRUE | O84: FALSE | P84: Intermedio | Q84: Intermedio | R84: Tecnología | W84: Tecnología | AB84: FALSE | AC84: FALSE | AE84: FALSE | AG84: FALSE | AI84: FALSE | AK84: Otros | AL84: CREATÓN | AM84: 46266 | AN84: 0.75907407 | AO84: 311 2494264 | AP84: Carrera 74A 66A-80, 111051 Bogota, D.C., Colombia | AQ84: DP | AR84: 98 | AS84: Cata | AT84: Tecnología (JR Data Scientist) | AU84: SI | AV84: OK | AW84: =IF(L84="Otra",IF(M84="","Otra",M84&""),L84&"") -> Ingeniería de Sistemas | AX84: =IF(OR(AO84="",AO84=0),"",TRIM(AO84)) -> 311 2494264 | AY84: =IFERROR(INDEX(Vacantes!$C:$C,MATCH(AT84,Vacantes!$A:$A,0)),"") -> 127 | AZ84: =IFERROR(INDEX(Vacantes!$D:$D,MATCH(AT84,Vacantes!$A:$A,0)),"") -> 13 de octubre de 2026 | BA84: =IFERROR(INDEX(Vacantes!$E:$E,MATCH(AT84,Vacantes!$A:$A,0)),"") -> 7:30 a.m. a 11:30 a.m.
A85: valrg0827@gmail.com | B85: Laura Valentina Gonzalez Rojas | C85: Cédula de ciudadanía | D85: 1002367458 | E85: Mujer | F85: 22 | G85: TRUE | I85: Bogotá | J85: Otra | K85: Universidad Manuela Beltran | L85: Ingeniería de Software | N85: FALSE | O85: FALSE | P85: Avanzado | Q85: Intermedio | R85: Tecnología | AB85: FALSE | AC85: FALSE | AE85: FALSE | AG85: FALSE | AI85: FALSE | AK85: Instagram | AL85: CREATÓN | AM85: 46255 | AN85: 0.41469907 | AO85: 314 4277940 | AP85: Calle 95A 71A-18, 111121 Bogota, D.C., Colombia | AQ85: DP | AR85: 82.6 | AS85: Cata | AT85: Tecnología (JR Data Scientist) | AU85: SI | AV85: OK | AW85: =IF(L85="Otra",IF(M85="","Otra",M85&""),L85&"") -> Ingeniería de Software | AX85: =IF(OR(AO85="",AO85=0),"",TRIM(AO85)) -> 314 4277940 | AY85: =IFERROR(INDEX(Vacantes!$C:$C,MATCH(AT85,Vacantes!$A:$A,0)),"") -> 127 | AZ85: =IFERROR(INDEX(Vacantes!$D:$D,MATCH(AT85,Vacantes!$A:$A,0)),"") -> 13 de octubre de 2026 | BA85: =IFERROR(INDEX(Vacantes!$E:$E,MATCH(AT85,Vacantes!$A:$A,0)),"") -> 7:30 a.m. a 11:30 a.m.
A86: jorgeszarate@outlook.com | B86: Jorge Sánchez Zarate | C86: Cédula de ciudadanía | D86: 1193115873 | E86: Hombre | F86: 26 | G86: TRUE | H86: BOGOTA | I86: Bogotá | J86: Universidad del Rosario | L86: Administración de Empresas | N86: FALSE | O86: FALSE | P86: Avanzado | Q86: Intermedio | R86: Marketing | W86: Ventas | AA86: Ventas Comercial | AB86: FALSE | AC86: FALSE | AE86: FALSE | AG86: FALSE | AI86: FALSE | AK86: Instagram | AL86: CREATÓN | AM86: 46278 | AN86: 0.70621528 | AO86: 321 3877492 | AP86: Avenida Calle 85 7A-45, 110221 Bogota, D.C., Colombia | AQ86: DP | AR86: 86.1 | AS86: Cata | AT86: Ventas comercial (Trade Marketing) Regional Centro | AU86: SI | AV86: OK | AW86: =IF(L86="Otra",IF(M86="","Otra",M86&""),L86&"") -> Administración de Empresas | AX86: =IF(OR(AO86="",AO86=0),"",TRIM(AO86)) -> 321 3877492 | AY86: =IFERROR(INDEX(Vacantes!$C:$C,MATCH(AT86,Vacantes!$A:$A,0)),"") -> Regional Centro | AZ86: =IFERROR(INDEX(Vacantes!$D:$D,MATCH(AT86,Vacantes!$A:$A,0)),"") -> 13 de octubre de 2026 | BA86: =IFERROR(INDEX(Vacantes!$E:$E,MATCH(AT86,Vacantes!$A:$A,0)),"") -> 12:30 p.m. a 4:00 p.m.
A87: andresmontana811@gmail.com | B87: Andres Montaña | C87: Cédula de ciudadanía | D87: 1031421663 | E87: Hombre | F87: 20 | G87: TRUE | H87: bogota | I87: Bogotá | J87: Universidad de los Andes | L87: Economía | N87: FALSE | O87: FALSE | P87: Avanzado | Q87: Intermedio | R87: Marketing | W87: Ventas | AA87: Ventas Comercial | AB87: FALSE | AC87: FALSE | AE87: FALSE | AG87: FALSE | AI87: FALSE | AK87: Otros | AL87: CREATÓN | AM87: 46267 | AN87: 0.77230324 | AO87: 3208971335 | AP87: Calle 24C 84-85, 110931 Bogota, D.C., Colombia | AQ87: DP | AR87: 85.7 | AS87: Santi | AT87: Ventas comercial (Trade Marketing) Regional Centro | AU87: SI | AV87: OK | AW87: =IF(L87="Otra",IF(M87="","Otra",M87&""),L87&"") -> Economía | AX87: =IF(OR(AO87="",AO87=0),"",TRIM(AO87)) -> 3208971335 | AY87: =IFERROR(INDEX(Vacantes!$C:$C,MATCH(AT87,Vacantes!$A:$A,0)),"") -> Regional Centro | AZ87: =IFERROR(INDEX(Vacantes!$D:$D,MATCH(AT87,Vacantes!$A:$A,0)),"") -> 13 de octubre de 2026 | BA87: =IFERROR(INDEX(Vacantes!$E:$E,MATCH(AT87,Vacantes!$A:$A,0)),"") -> 12:30 p.m. a 4:00 p.m.
A88: juangarzon1853@gmail.com | B88: Juan Camilo Garzón Ramírez | C88: Cédula de ciudadanía | D88: 1013256749 | E88: Hombre | F88: 22 | G88: TRUE | H88: Bogotá | I88: Bogotá | J88: Universidad de La Sabana | L88: Administración de Empresas | N88: FALSE | O88: FALSE | P88: Avanzado | Q88: Avanzado | R88: Ventas | V88: Talento Ventas | W88: Ventas | AA88: Gestión de Ejecución Premium | AB88: FALSE | AC88: FALSE | AE88: FALSE | AG88: FALSE | AI88: FALSE | AK88: LinkedIn | AL88: CREATÓN | AM88: 46278 | AN88: 0.53662037 | AO88: 301 6040200 | AP88: Vereda Canelon, Cajicá, Colombia | AQ88: DP | AR88: 75.8 | AS88: Cata | AT88: Ventas comercial (Trade Marketing) Regional Centro | AU88: SI | AV88: OK | AW88: =IF(L88="Otra",IF(M88="","Otra",M88&""),L88&"") -> Administración de Empresas | AX88: =IF(OR(AO88="",AO88=0),"",TRIM(AO88)) -> 301 6040200 | AY88: =IFERROR(INDEX(Vacantes!$C:$C,MATCH(AT88,Vacantes!$A:$A,0)),"") -> Regional Centro | AZ88: =IFERROR(INDEX(Vacantes!$D:$D,MATCH(AT88,Vacantes!$A:$A,0)),"") -> 13 de octubre de 2026 | BA88: =IFERROR(INDEX(Vacantes!$E:$E,MATCH(AT88,Vacantes!$A:$A,0)),"") -> 12:30 p.m. a 4:00 p.m.
A89: anaasofiaamonteroo@gmail.com | B89: Ana Sofia Montero Angulo | C89: Cédula de ciudadanía | D89: 1077721001 | E89: Mujer | F89: 22 | G89: TRUE | H89: BOGOTA | I89: Bogotá | J89: Universidad de los Andes | L89: Administración de Empresas | N89: FALSE | O89: FALSE | P89: Avanzado | Q89: Intermedio | R89: Marketing | W89: Ventas | AA89: Ventas Comercial | AB89: FALSE | AC89: FALSE | AE89: FALSE | AG89: FALSE | AI89: FALSE | AK89: LinkedIn | AL89: CREATÓN | AM89: 46271 | AN89: 0.72023148 | AO89: 3142249659 | AP89: Carrera 7C 138-60, 110121 Bogota, D.C., Colombia | AQ89: DP | AR89: 79.6 | AS89: Cata | AT89: Ventas comercial (Trade Marketing) Regional Centro | AU89: SI | AV89: OK | AW89: =IF(L89="Otra",IF(M89="","Otra",M89&""),L89&"") -> Administración de Empresas | AX89: =IF(OR(AO89="",AO89=0),"",TRIM(AO89)) -> 3142249659 | AY89: =IFERROR(INDEX(Vacantes!$C:$C,MATCH(AT89,Vacantes!$A:$A,0)),"") -> Regional Centro | AZ89: =IFERROR(INDEX(Vacantes!$D:$D,MATCH(AT89,Vacantes!$A:$A,0)),"") -> 13 de octubre de 2026 | BA89: =IFERROR(INDEX(Vacantes!$E:$E,MATCH(AT89,Vacantes!$A:$A,0)),"") -> 12:30 p.m. a 4:00 p.m.
A90: doblecontabilidad@gmail.com | B90: Natalia Orejuela castrillon | C90: Cédula de ciudadanía | D90: 1006037327 | E90: Mujer | F90: 23 | G90: TRUE | I90: Bogotá | J90: Otra | K90: Universidad ICESI | L90: Marketing / Mercadeo | N90: FALSE | O90: FALSE | P90: Intermedio | Q90: Intermedio | R90: Marketing | W90: Ventas | AA90: Canal Moderno | AB90: FALSE | AC90: FALSE | AE90: FALSE | AG90: FALSE | AI90: FALSE | AK90: Instagram | AL90: CREATÓN | AM90: 46255 | AN90: 0.4146875 | AO90: 313 7808424 | AP90: Calle 76 16-156, 760033 Cali, Colombia | AQ90: DP | AR90: 88.3 | AS90: Cata | AT90: Ventas comercial (Trade Marketing) Regional Centro | AU90: SI | AV90: OK | AW90: =IF(L90="Otra",IF(M90="","Otra",M90&""),L90&"") -> Marketing / Mercadeo | AX90: =IF(OR(AO90="",AO90=0),"",TRIM(AO90)) -> 313 7808424 | AY90: =IFERROR(INDEX(Vacantes!$C:$C,MATCH(AT90,Vacantes!$A:$A,0)),"") -> Regional Centro | AZ90: =IFERROR(INDEX(Vacantes!$D:$D,MATCH(AT90,Vacantes!$A:$A,0)),"") -> 13 de octubre de 2026 | BA90: =IFERROR(INDEX(Vacantes!$E:$E,MATCH(AT90,Vacantes!$A:$A,0)),"") -> 12:30 p.m. a 4:00 p.m.
A91: danielaalejandrao920@gmail.com | B91: Daniela Alejandra Hernández Ortiz | C91: Cédula de ciudadanía | D91: 1081275499 | E91: Mujer | F91: 20 | G91: TRUE | H91: CALI | I91: Bogotá | J91: Pontificia Universidad Javeriana| Cali | L91: Economía | N91: FALSE | O91: FALSE | P91: Avanzado | Q91: Avanzado | R91: Ventas | V91: Ventas Comercial | W91: Compras | AB91: FALSE | AC91: FALSE | AE91: FALSE | AG91: FALSE | AI91: FALSE | AK91: Otros | AL91: CREATÓN | AM91: 46276 | AN91: 0.65149306 | AO91: 314 4065467 | AP91: Carrera 72 11-30, 760033 Cali, Colombia | AQ91: DP | AR91: 87.2 | AS91: Cata | AT91: Ventas comercial (Trade Marketing) Regional Centro | AU91: SI | AV91: OK | AW91: =IF(L91="Otra",IF(M91="","Otra",M91&""),L91&"") -> Economía | AX91: =IF(OR(AO91="",AO91=0),"",TRIM(AO91)) -> 314 4065467 | AY91: =IFERROR(INDEX(Vacantes!$C:$C,MATCH(AT91,Vacantes!$A:$A,0)),"") -> Regional Centro | AZ91: =IFERROR(INDEX(Vacantes!$D:$D,MATCH(AT91,Vacantes!$A:$A,0)),"") -> 13 de octubre de 2026 | BA91: =IFERROR(INDEX(Vacantes!$E:$E,MATCH(AT91,Vacantes!$A:$A,0)),"") -> 12:30 p.m. a 4:00 p.m.
A92: jsqo4320@gmail.com | B92: Juan Sebastián Quiñones Oeding | C92: Cédula de ciudadanía | D92: 1014859269 | E92: Hombre | F92: 21 | G92: TRUE | H92: BOGOTA | I92: Bogotá | J92: Universidad de los Andes | L92: Ingeniería Industrial | N92: FALSE | O92: FALSE | P92: Avanzado | Q92: Avanzado | R92: Marketing | W92: Ventas | AA92: Ventas Comercial | AB92: FALSE | AC92: FALSE | AE92: FALSE | AG92: FALSE | AI92: FALSE | AK92: Instagram | AL92: CREATÓN | AM92: 46271 | AN92: 0.94869213 | AO92: 321 2966629 | AP92: Diagonal 72 1-16, 110221 Bogota, D.C., Colombia | AQ92: DP | AR92: 95 | AS92: Cata | AT92: Ventas comercial (Trade Marketing) Regional Centro | AU92: SI | AV92: OK | AW92: =IF(L92="Otra",IF(M92="","Otra",M92&""),L92&"") -> Ingeniería Industrial | AX92: =IF(OR(AO92="",AO92=0),"",TRIM(AO92)) -> 321 2966629 | AY92: =IFERROR(INDEX(Vacantes!$C:$C,MATCH(AT92,Vacantes!$A:$A,0)),"") -> Regional Centro | AZ92: =IFERROR(INDEX(Vacantes!$D:$D,MATCH(AT92,Vacantes!$A:$A,0)),"") -> 13 de octubre de 2026 | BA92: =IFERROR(INDEX(Vacantes!$E:$E,MATCH(AT92,Vacantes!$A:$A,0)),"") -> 12:30 p.m. a 4:00 p.m.
A93: andrevelezf@gmail.com | B93: Andrea Vélez Fernández | C93: Cédula de ciudadanía | D93: 1029500104 | E93: Mujer | F93: 21 | G93: TRUE | I93: Bogotá | J93: Colegio de Estudios Superiores de Administración CESA | L93: Administración de Empresas | N93: TRUE | O93: FALSE | P93: Avanzado | Q93: Avanzado | R93: Marketing | W93: Ventas | AA93: Canal Moderno | AB93: FALSE | AC93: FALSE | AE93: FALSE | AG93: FALSE | AI93: FALSE | AK93: LinkedIn | AL93: CREATÓN | AM93: 46256 | AN93: 0.42581019 | AO93: 302 3029042 | AP93: Calle 77, Bogota, D.C., Colombia | AQ93: DP | AR93: 87.2 | AS93: Santi | AT93: Canal moderno (KA) | AU93: SI | AV93: OK | AW93: =IF(L93="Otra",IF(M93="","Otra",M93&""),L93&"") -> Administración de Empresas | AX93: =IF(OR(AO93="",AO93=0),"",TRIM(AO93)) -> 302 3029042 | AY93: =IFERROR(INDEX(Vacantes!$C:$C,MATCH(AT93,Vacantes!$A:$A,0)),"") -> 127 | AZ93: =IFERROR(INDEX(Vacantes!$D:$D,MATCH(AT93,Vacantes!$A:$A,0)),"") -> 13 de octubre de 2026 | BA93: =IFERROR(INDEX(Vacantes!$E:$E,MATCH(AT93,Vacantes!$A:$A,0)),"") -> 1:30 p.m. a 5:30 p.m.
A94: jm.aguirre@uniandes.edu.co | B94: Juan Miguel Aguirre Guzman | C94: Cédula de ciudadanía | D94: 1001300590 | E94: Hombre | F94: 22 | G94: TRUE | I94: Bogotá | J94: Universidad de los Andes | L94: Economía | N94: FALSE | O94: FALSE | P94: Avanzado | Q94: Intermedio | R94: Asuntos corporativos | W94: Compras | AB94: FALSE | AC94: FALSE | AE94: FALSE | AG94: FALSE | AI94: FALSE | AK94: Medios Tradicionales | AL94: CREATÓN | AM94: 46256 | AN94: 0.5362037 | AO94: 312 2329005 | AP94: Happa Hub - Apartamentos en El Centro de la Ciudad, 110311 Bogota, D.C., Colombia | AQ94: DP | AR94: 92.2 | AS94: Cata | AT94: Asuntos Corporativos | AU94: SI | AV94: OK | AW94: =IF(L94="Otra",IF(M94="","Otra",M94&""),L94&"") -> Economía | AX94: =IF(OR(AO94="",AO94=0),"",TRIM(AO94)) -> 312 2329005 | AY94: =IFERROR(INDEX(Vacantes!$C:$C,MATCH(AT94,Vacantes!$A:$A,0)),"") -> 127 | AZ94: =IFERROR(INDEX(Vacantes!$D:$D,MATCH(AT94,Vacantes!$A:$A,0)),"") -> 13 de octubre de 2026 | BA94: =IFERROR(INDEX(Vacantes!$E:$E,MATCH(AT94,Vacantes!$A:$A,0)),"") -> 1:30 p.m. a 5:30 p.m.
A95: jjsalcedohernandez@gmail.com | B95: Juan Salcedo | C95: Cédula de ciudadanía | D95: 1002156347 | E95: Hombre | F95: 24 | G95: TRUE | H95: Bogotá | I95: Bogotá | J95: Universidad del Rosario | L95: Derecho | N95: FALSE | O95: FALSE | P95: Avanzado | Q95: Intermedio | R95: Asuntos corporativos | T95: Finanzas Impuestos | W95: Finanzas | AB95: FALSE | AC95: FALSE | AE95: FALSE | AG95: FALSE | AI95: FALSE | AK95: Otros | AL95: CREATÓN | AM95: 46278 | AN95: 0.35966435 | AO95: 310 3456622 | AP95: Calle 137 55-42, 111111 Bogota, D.C., Colombia | AQ95: DP | AR95: 76.6 | AS95: Cata | AT95: Asuntos Corporativos | AU95: SI | AV95: OK | AW95: =IF(L95="Otra",IF(M95="","Otra",M95&""),L95&"") -> Derecho | AX95: =IF(OR(AO95="",AO95=0),"",TRIM(AO95)) -> 310 3456622 | AY95: =IFERROR(INDEX(Vacantes!$C:$C,MATCH(AT95,Vacantes!$A:$A,0)),"") -> 127 | AZ95: =IFERROR(INDEX(Vacantes!$D:$D,MATCH(AT95,Vacantes!$A:$A,0)),"") -> 13 de octubre de 2026 | BA95: =IFERROR(INDEX(Vacantes!$E:$E,MATCH(AT95,Vacantes!$A:$A,0)),"") -> 1:30 p.m. a 5:30 p.m.
A96: sofiaramirezdelavalle27@gmail.com | B96: Sofía Ramírez De Lavalle | C96: Cédula de ciudadanía | D96: 1013260058 | E96: Mujer | F96: 20 | G96: TRUE | H96: Bogota | I96: Bogotá | J96: Colegio de Estudios Superiores de Administración CESA | L96: Administración de Empresas | N96: TRUE | O96: FALSE | P96: Intermedio | Q96: Intermedio | R96: Marketing | W96: Ventas | AA96: Canal Moderno | AB96: FALSE | AC96: FALSE | AE96: FALSE | AG96: FALSE | AI96: FALSE | AK96: LinkedIn | AL96: CREATÓN | AM96: 46258 | AN96: 0.66832176 | AO96: 3002356621 | AP96: Calle 93A, Bogota, D.C., Colombia | AQ96: DP | AR96: 84.8 | AS96: Cata | AT96: Canal moderno (KA) | AU96: SI | AV96: OK | AW96: =IF(L96="Otra",IF(M96="","Otra",M96&""),L96&"") -> Administración de Empresas | AX96: =IF(OR(AO96="",AO96=0),"",TRIM(AO96)) -> 3002356621 | AY96: =IFERROR(INDEX(Vacantes!$C:$C,MATCH(AT96,Vacantes!$A:$A,0)),"") -> 127 | AZ96: =IFERROR(INDEX(Vacantes!$D:$D,MATCH(AT96,Vacantes!$A:$A,0)),"") -> 13 de octubre de 2026 | BA96: =IFERROR(INDEX(Vacantes!$E:$E,MATCH(AT96,Vacantes!$A:$A,0)),"") -> 1:30 p.m. a 5:30 p.m.
A97: anamariabeltransaenz02@gmail.com | B97: Ana María Beltrán Sáenz | C97: Cédula de ciudadanía | D97: 1007475387 | E97: Mujer | F97: 24 | G97: TRUE | H97: Boyacá | I97: Bogotá | J97: Universidad Santo Tomás | L97: Administración de Empresas | N97: FALSE | O97: FALSE | P97: Intermedio | Q97: Intermedio | R97: Talento | W97: Asuntos Corporativos | Z97: Atracción de Talento y Marca Empleadora | AB97: FALSE | AC97: FALSE | AE97: FALSE | AG97: FALSE | AI97: FALSE | AK97: Instagram | AL97: CREATÓN | AM97: 46259 | AN97: 0.5543287 | AO97: 313 3019024 | AP97: Carrera 4 3-4, 154240 Santa Sofía, Colombia | AQ97: DP | AR97: 80 | AS97: Cata | AT97: Compensación y beneficios | AU97: SI | AV97: OK | AW97: =IF(L97="Otra",IF(M97="","Otra",M97&""),L97&"") -> Administración de Empresas | AX97: =IF(OR(AO97="",AO97=0),"",TRIM(AO97)) -> 313 3019024 | AY97: =IFERROR(INDEX(Vacantes!$C:$C,MATCH(AT97,Vacantes!$A:$A,0)),"") -> 127 | AZ97: =IFERROR(INDEX(Vacantes!$D:$D,MATCH(AT97,Vacantes!$A:$A,0)),"") -> 13 de octubre de 2026 | BA97: =IFERROR(INDEX(Vacantes!$E:$E,MATCH(AT97,Vacantes!$A:$A,0)),"") -> 7:30 a.m. a 11:30 a.m.
A98: viasusgabriela205@gmail.com | B98: Gabriela Fernanda Viasus Castro | C98: Cédula de ciudadanía | D98: 1002760191 | E98: Mujer | F98: 22 | G98: TRUE | H98: TUTA | I98: Bogotá | J98: Universidad Pedagógica y Tecnológica de Colombia | L98: Finanzas | N98: FALSE | O98: FALSE | P98: Intermedio | Q98: Intermedio | R98: Finanzas | W98: Compras | Y98: Finanzas Impuestos | AB98: FALSE | AC98: FALSE | AE98: FALSE | AG98: FALSE | AI98: FALSE | AK98: Instagram | AL98: CREATÓN | AM98: 46264 | AN98: 0.43061343 | AO98: 310 7613100 | AP98: Tuta, Colombia | AQ98: DP | AR98: 86.4 | AS98: Cata | AT98: Compras (Procurement PPM Reporting) | AU98: SI | AV98: OK | AW98: =IF(L98="Otra",IF(M98="","Otra",M98&""),L98&"") -> Finanzas | AX98: =IF(OR(AO98="",AO98=0),"",TRIM(AO98)) -> 310 7613100 | AY98: =IFERROR(INDEX(Vacantes!$C:$C,MATCH(AT98,Vacantes!$A:$A,0)),"") -> 127 | AZ98: =IFERROR(INDEX(Vacantes!$D:$D,MATCH(AT98,Vacantes!$A:$A,0)),"") -> 13 de octubre de 2026 | BA98: =IFERROR(INDEX(Vacantes!$E:$E,MATCH(AT98,Vacantes!$A:$A,0)),"") -> 7:30 a.m. a 11:30 a.m.
A99: estefaniaduran.w@gmail.com | B99: Estefanía Durán Luna | C99: Cédula de ciudadanía | D99: 1095788078 | E99: Mujer | F99: 22 | G99: TRUE | I99: Bogotá | J99: Universidad del Rosario | L99: Logística | N99: TRUE | O99: FALSE | P99: Avanzado | Q99: Avanzado | R99: Logística | W99: Marketing | AB99: FALSE | AC99: FALSE | AE99: FALSE | AG99: FALSE | AI99: FALSE | AK99: LinkedIn | AL99: CREATÓN | AM99: 46278 | AN99: 0.43967593 | AO99: 320 4915165 | AP99: Calle 146 13-22, 110121 Bogota, D.C., Colombia | AQ99: DP | AR99: 86.2 | AS99: Cata | AT99: Logística T2 (Safety & DPO T2) | AU99: SI | AV99: OK | AW99: =IF(L99="Otra",IF(M99="","Otra",M99&""),L99&"") -> Logística | AX99: =IF(OR(AO99="",AO99=0),"",TRIM(AO99)) -> 320 4915165 | AY99: =IFERROR(INDEX(Vacantes!$C:$C,MATCH(AT99,Vacantes!$A:$A,0)),"") -> 127 | AZ99: =IFERROR(INDEX(Vacantes!$D:$D,MATCH(AT99,Vacantes!$A:$A,0)),"") -> 13 de octubre de 2026 | BA99: =IFERROR(INDEX(Vacantes!$E:$E,MATCH(AT99,Vacantes!$A:$A,0)),"") -> 7:30 a.m. a 11:30 a.m.
A100: andrestoncel123@gmail.com | B100: ANDRES TONCEL VASQUEZ | C100: Cédula de ciudadanía | D100: 1004360759 | E100: Hombre | F100: 23 | G100: TRUE | H100: SANTA MARTA | I100: Bogotá | J100: Universidad del Magdalena | L100: Negocios Internacionales | N100: FALSE | O100: FALSE | P100: Intermedio | Q100: Intermedio | R100: Talento | W100: Logística | Z100: Support | AB100: FALSE | AC100: FALSE | AE100: FALSE | AG100: FALSE | AI100: FALSE | AK100: Otros | AL100: CREATÓN | AM100: 46277 | AN100: 0.91222222 | AO100: 304 3749681 | AP100: Vía Santa Marta Taganga 18-207, 470001 Santa Marta, Colombia | AQ100: DP | AR100: 79.8 | AS100: Cata | AT100: People Support 1 | AU100: SI | AV100: OK | AW100: =IF(L100="Otra",IF(M100="","Otra",M100&""),L100&"") -> Negocios Internacionales | AX100: =IF(OR(AO100="",AO100=0),"",TRIM(AO100)) -> 304 3749681 | AY100: =IFERROR(INDEX(Vacantes!$C:$C,MATCH(AT100,Vacantes!$A:$A,0)),"") -> 127 | AZ100: =IFERROR(INDEX(Vacantes!$D:$D,MATCH(AT100,Vacantes!$A:$A,0)),"") -> 13 de octubre de 2026 | BA100: =IFERROR(INDEX(Vacantes!$E:$E,MATCH(AT100,Vacantes!$A:$A,0)),"") -> 7:30 a.m. a 11:30 a.m.
...

Sheet Vacantes
A1: Vacante | B1: Ubicación / Planta (funnel) | C1: Site | D1: Fecha creatón | E1: Horario creatón | F1: Fecha creatón (texto original)
A2: Area financiera (PPM) | B2: 127 | C2: 127 | D2: 13 de octubre de 2026 | E2: 7:30 a.m. a 11:30 a.m. | F2: 13 de octubre de 2026, 7:30 a.m. a 11:30 a.m.
A3: Asuntos Corporativos | B3: 127 | C3: 127 | D3: 13 de octubre de 2026 | E3: 1:30 p.m. a 5:30 p.m. | F3: 13 de octubre de 2026, 1:30 p.m. a 5:30 p.m.
A4: Atracción de talento y Marca Empleadora | B4: 127 | C4: 127 | D4: 13 de octubre de 2026 | E4: 7:30 a.m. a 11:30 a.m. | F4: 13 de octubre de 2026, 7:30 a.m. a 11:30 a.m.
A5: Canal moderno (KA) | B5: 127 | C5: 127 | D5: 13 de octubre de 2026 | E5: 1:30 p.m. a 5:30 p.m. | F5: 13 de octubre de 2026, 1:30 p.m. a 5:30 p.m.
A6: Channel Strategy and Performance (BEES) | B6: 127 | C6: 127 | D6: 13 de octubre de 2026 | E6: 1:30 p.m. a 5:30 p.m. | F6: 13 de octubre de 2026, 1:30 p.m. a 5:30 p.m.
A7: Compensación y beneficios | B7: 127 | C7: 127 | D7: 13 de octubre de 2026 | E7: 7:30 a.m. a 11:30 a.m. | F7: 13 de octubre de 2026, 7:30 a.m. a 11:30 a.m.
A8: Compras (Procurement PPM Reporting) | B8: 127 | C8: 127 | D8: 13 de octubre de 2026 | E8: 7:30 a.m. a 11:30 a.m. | F8: 13 de octubre de 2026, 7:30 a.m. a 11:30 a.m.
A9: Comunicaciones | B9: 127 | C9: 127 | D9: 13 de octubre de 2026 | E9: 1:30 p.m. a 5:30 p.m. | F9: 13 de octubre de 2026, 1:30 p.m. a 5:30 p.m.
A10: Finanzas Control Interno | B10: 127 | C10: 127 | D10: No aplica (vacante a 1 año) | E10: No aplica (vacante a 1 año) | F10: No aplica (vacante a 1 año)
A11: Gestión de talento | B11: 127 | C11: 127 | D11: No aplica (vacante a 1 año) | E11: No aplica (vacante a 1 año) | F11: No aplica (vacante a 1 año)
A12: Logística T2 (Safety & DPO T2) | B12: 127/Regional Centro | C12: 127 | D12: 13 de octubre de 2026 | E12: 7:30 a.m. a 11:30 a.m. | F12: 13 de octubre de 2026, 7:30 a.m. a 11:30 a.m.
A13: MKT Balance choice | B13: 127 | C13: 127 | D13: 16 de octubre de 2026 | E13: 1:30 p.m. a 3:30 p.m. | F13: 16 de octubre de 2026, 1:30 p.m. a 3:30 p.m.
A14: MKT Core brands | B14: 127 | C14: 127 | D14: 16 de octubre de 2026 | E14: 1:30 p.m. a 3:30 p.m. | F14: 16 de octubre de 2026, 1:30 p.m. a 3:30 p.m.
A15: MKT High end | B15: 127 | C15: 127 | D15: 16 de octubre de 2026 | E15: 1:30 p.m. a 3:30 p.m. | F15: 16 de octubre de 2026, 1:30 p.m. a 3:30 p.m.
A16: MKT Premium brands | B16: 127 | C16: 127 | D16: 16 de octubre de 2026 | E16: 1:30 p.m. a 3:30 p.m. | F16: 16 de octubre de 2026, 1:30 p.m. a 3:30 p.m.
A17: People Support 1 | B17: 127 | C17: 127 | D17: 13 de octubre de 2026 | E17: 7:30 a.m. a 11:30 a.m. | F17: 13 de octubre de 2026, 7:30 a.m. a 11:30 a.m.
A18: People Support 2 | B18: 127 | C18: 127 | D18: 13 de octubre de 2026 | E18: 1:30 p.m. a 5:30 p.m. | F18: 13 de octubre de 2026, 1:30 p.m. a 5:30 p.m.
A19: Relaciones laborales | B19: 127 | C19: 127 | D19: Por confirmar | E19: Por confirmar | F19: Por confirmar
A20: TEV Transporte T1 | B20: Planta Tocancipá | C20: Cervecería de Tocancipá | D20: 27 de octubre de 2026 | E20: 12:30 p.m. a 4:00 p.m. | F20: 27 de octubre de 2026, 12:30 p.m. a 4:00 p.m.
A21: Tecnología (JR Data Scientist) | B21: 127 | C21: 127 | D21: 13 de octubre de 2026 | E21: 7:30 a.m. a 11:30 a.m. | F21: 13 de octubre de 2026, 7:30 a.m. a 11:30 a.m.
A22: Producción (operaciones) Atlantico Envase | B22: Planta Atlantico | C22: Cervecería de Atlántico | D22: 23 de octubre de 2026 | E22: 8:30 a.m. a 12:00 p.m. | F22: 23 de octubre de 2026, 8:30 a.m. a 12:00 p.m.
A23: Producción (operaciones) Atlantico Gestión | B23: Planta Atlantico | C23: Cervecería de Atlántico | D23: 23 de octubre de 2026 | E23: 8:30 a.m. a 12:00 p.m. | F23: 23 de octubre de 2026, 8:30 a.m. a 12:00 p.m.
A24: Brewing & Quality Cervecería de Barranquilla | B24: Planta Barranquilla | C24: Cervecería de Barranquilla | D24: 22 de octubre de 2026 | E24: 12:30 p.m. a 5:00 p.m. | F24: 22 de octubre de 2026, 12:30 p.m. a 5:00 p.m.
A25: Envase Cervecería de Barranquilla | B25: Planta Barranquilla | C25: Cervecería de Barranquilla | D25: 22 de octubre de 2026 | E25: 12:30 p.m. a 5:00 p.m. | F25: 22 de octubre de 2026, 12:30 p.m. a 5:00 p.m.
A26: I&S Cervecería de Barranquilla | B26: Planta Barranquilla | C26: Cervecería de Barranquilla | D26: 22 de octubre de 2026 | E26: 12:30 p.m. a 5:00 p.m. | F26: 22 de octubre de 2026, 12:30 p.m. a 5:00 p.m.
A27: Talento Supply Cervecería de Barranquilla | B27: Planta Barranquilla | C27: Cervecería de Barranquilla | D27: 22 de octubre de 2026 | E27: 12:30 p.m. a 5:00 p.m. | F27: 22 de octubre de 2026, 12:30 p.m. a 5:00 p.m.
A28: Elaboración Boyacá Cervecería de Boyacá | B28: Planta Boyacá | C28: Cervecería de Boyacá | D28: 20 de octubre de 2026 | E28: 7:30 a.m. a 12:00 p.m. | F28: 20 de octubre de 2026, 7:30 a.m. a 12:00 p.m.
A29: Talento Cervecería de Boyacá | B29: Planta Boyacá | C29: Cervecería de Boyacá | D29: 20 de octubre de 2026 | E29: 7:30 a.m. a 12:00 p.m. | F29: 20 de octubre de 2026, 7:30 a.m. a 12:00 p.m.
A30: Producción (operaciones) Bucaramanga | B30: Planta Bucaramanga | C30: Cervecería de Bucaramanga | D30: 21 de octubre de 2026 | E30: 7:30 a.m. a 12:00 p.m. | F30: 21 de octubre de 2026, 7:30 a.m. a 12:00 p.m.
A31: Talento Supply Bucaramanga | B31: Planta Bucaramanga | C31: Cervecería de Bucaramanga | D31: 21 de octubre de 2026 | E31: 7:30 a.m. a 12:00 p.m. | F31: 21 de octubre de 2026, 7:30 a.m. a 12:00 p.m.
A32: Elaboración Cervecería de Medellín | B32: Planta Medellín | C32: Cervecería de Medellín | D32: 21 de octubre de 2026 | E32: 12:30 p.m. a 4:30 p.m. | F32: 21 de octubre de 2026, 12:30 p.m. a 4:30 p.m.
A33: Envase Cervecería de Medellín (Tienen practicante de un año) | B33: Planta Medellín | C33: Cervecería de Medellín | D33: Por confirmar | E33: Por confirmar | F33: Por confirmar
... A55: Ventas Regional Sur | B55: Regional Sur | C55: Regional Sur | D55: 22 de octubre de 2026 | E55: 8:30 a.m. a 12:00 p.m. | F55: 22 de octubre de 2026, 8:30 a.m. a 12:00 p.m.
A57: Nota: Site, Fecha y Horario de la Maestra se buscan aquí por "Vacante sugerida". Si cambia la fecha u horario de una vacante, edítalo en esta hoja y actualiza las tablas dinámicas (Datos > Actualizar todo).
A58: Relaciones laborales queda "Por confirmar" por indicación de TA. Filas en naranja en la Maestra = vacante asignada en esta actualización.

Sheet 127 - R.CENTRO
A1: Candidatos confirmados a la Creatón — 127, Regional Centro
A6: #VALUE!
A49: MKT High end | B49: 1014977540 | C49: Daniela Prado Sahab

Sheet INDUGRAL
A1: Candidatos confirmados a la Creatón — Indugral
A3: Site | B3: Indugral
A4: Confirmación | B4: SI
A6: Vacante | B6: Cédula | C6: Nombre del candidato | D6: Correo | E6: Teléfono contacto | F6: Carrera | G6: Fecha creatón | H6: Horario creatón
A7: Calidad Supply Indugral | B7: 1004419222 | C7: PAULA CAMILA ORTIZ GALINDEZ | D7: cami188ortiz@gmail.com | E7: 317 1662760 | F7: Química | G7: 15 de octubre de 2026 | H7: 12:30 p.m. a 4:00 p.m.
A8: Calidad Supply Indugral | B8: 1005784074 | C8: Natalia Osorio Henao | D8: nataliahenao0527@gmail.com | E8: 300 5568536 | F8: Ingeniería Química | G8: 15 de octubre de 2026 | H8: 12:30 p.m. a 4:00 p.m.
A9: Calidad Supply Indugral | B9: 1006053135 | C9: Brandon Steven Ocampo López | D9: ocampob2003@gmail.com | E9: 318 5139065 | F9: Ingeniería Química | G9: 15 de octubre de 2026 | H9: 12:30 p.m. a 4:00 p.m.
A10: Calidad Supply Indugral | B10: 1083752386 | C10: Nathalia Stephanie Caez Daza | D10: nathalia.caez@correounivalle.edu.co | E10: 300 7487102 | F10: Ingeniería Química | G10: 15 de octubre de 2026 | H10: 12:30 p.m. a 4:00 p.m.
A11: Calidad Supply Indugral | B11: 1085896222 | C11: Juan Coral Tulcan | D11: coraltulcanjuancarlos@gmail.com | E11: 318 4101038 | F11: INGENIERIA EN AUTOMATICA INDUSTRIAL | G11: 15 de octubre de 2026 | H11: 12:30 p.m. a 4:00 p.m.
A12: Calidad Supply Indugral | B12: 1109665069 | C12: Nicol Dayan Pinzón Astaiza | D12: nicold.astaiza@gmail.com | E12: 3144784547 | F12: Ingeniería Industrial | G12: 15 de octubre de 2026 | H12: 12:30 p.m. a 4:00 p.m.
A13: Calidad Supply Indugral | B13: 1110283459 | C13: LINA GISELLE JARAMILLO ORTIZ | D13: lina.giselle.jaramillo@correounivalle.edu.co | E13: 320 2205129 | F13: Química | G13: 15 de octubre de 2026 | H13: 12:30 p.m. a 4:00 p.m.
A14: Calidad Supply Indugral | B14: 1117013881 | C14: Laura Sofía Garcia Patiño | D14: garcialaurasofia0@gmail.com | E14: 322 6378982 | F14: Ingeniería Química | G14: 15 de octubre de 2026 | H14: 12:30 p.m. a 4:00 p.m.
A15: Envase Supply Indugral | B15: 1002777341 | C15: Antonio Guasca | D15: guascawilson797@gmail.com | E15: 314 8443067 | F15: Ingeniería Industrial | G15: 15 de octubre de 2026 | H15: 12:30 p.m. a 4:00 p.m.
A16: Envase Supply Indugral | B16: 1004154247 | C16: Cristian Alexis Gonzalez Gutiérrez | D16: cristiangonzalez842737@gmail.com | E16: 320 8753642 | F16: Ingeniería Industrial | G16: 15 de octubre de 2026 | H16: 12:30 p.m. a 4:00 p.m.
A17: Envase Supply Indugral | B17: 1004691011 | C17: Oscar Danilo Colimba Cuaical | D17: danilocuai12@gmail.com | F17: Ingeniería Mecánica | G17: 15 de octubre de 2026 | H17: 12:30 p.m. a 4:00 p.m.
A18: Envase Supply Indugral | B18: 1006101876 | C18: Alejandro Diaz Nieva | D18: alejandrodiaznieva@gmail.com | E18: 3135404291 | F18: Ingeniería Química | G18: 15 de octubre de 2026 | H18: 12:30 p.m. a 4:00 p.m.
A19: Envase Supply Indugral | B19: 1006427742 | C19: Catalina Atehortua Zuluaga | D19: catehortua310@gmail.com | E19: 323 3317100 | F19: Ingeniería Industrial | G19: 15 de octubre de 2026 | H19: 12:30 p.m. a 4:00 p.m.
A20: Envase Supply Indugral | B20: 1088589197 | C20: DIANA CAMILA MARTINEZ SOTO | D20: diana.martinez12@u.icesi.edu.co | E20: 3106456019 | F20: Ingeniería Industrial | G20: 15 de octubre de 2026 | H20: 12:30 p.m. a 4:00 p.m.
A21: Envase Supply Indugral | B21: 1089512175 | C21: Janer Darío Bolaños Quiñones | D21: dariojbq27@gmail.com | E21: 320 5293145 | F21: Ingeniería Industrial | G21: 15 de octubre de 2026 | H21: 12:30 p.m. a 4:00 p.m.
A22: Envase Supply Indugral | B22: 1193600407 | C22: Miguel Angel Salazar Ramirez | D22: miguelsalazar1105@gmail.com | E22: 314 5015242 | F22: Ingeniería Mecatrónica | G22: 15 de octubre de 2026 | H22: 12:30 p.m. a 4:00 p.m.

Sheet C.CALI
A1: Candidatos confirmados a la Creatón — Cervecería del Valle
A3: Site | B3: Cervecería del Valle
A4: Confirmación | B4: SI
A6: Vacante | B6: Cédula | C6: Nombre del candidato | D6: Correo | E6: Teléfono contacto | F6: Carrera | G6: Fecha creatón | H6: Horario creatón
A7: Calidad Cervecería del Valle | B7: 1107835167 | C7: Santiago Tamayo Quevedo | D7: santiago.tamayo3103@gmail.com | E7: 315 8084417 | F7: Ingeniería Bioquímica | G7: 21 de octubre de 2026 | H7: 7:30 a.m. a 11:30 a.m.
A8: Calidad Cervecería del Valle | B8: 1108558815 | C8: Danna Sofia Hoyos Jaramillo | D8: dannaso04@gmail.com | E8: 3157699360 | F8: Ingeniería Química | G8: 21 de octubre de 2026 | H8: 7:30 a.m. a 11:30 a.m.
A9: Calidad Cervecería del Valle | B9: 1113152043 | C9: John Edinson Agredo Muñoz | D9: johnagredo@outlook.com | E9: 3127386690 | F9: Ingeniería Industrial | G9: 21 de octubre de 2026 | H9: 7:30 a.m. a 11:30 a.m.
A10: Calidad Cervecería del Valle | B10: 1126965198 | C10: Melissa Andrea Londoño Poveda | D10: londonomelissa16@gmail.com | E10: 305 3309565 | F10: Ingeniería Industrial | G10: 21 de octubre de 2026 | H10: 7:30 a.m. a 11:30 a.m.
A11: Calidad Cervecería del Valle | B11: 1193249727 | C11: JUAN GUEVARA | D11: juan.camilo@correounivalle.edu.co | E11: 310 4297075 | F11: Ingeniería Química | G11: 21 de octubre de 2026 | H11: 7:30 a.m. a 11:30 a.m.
A12: Elaboración Cervecería del Valle | B12: 1005935212 | C12: LIZETH MAYERLI MONTENEGRO RESTREPO | D12: montenegro.lizeth@correounivalle.edu.co | E12: 318 8018223 | F12: Química | G12: 21 de octubre de 2026 | H12: 7:30 a.m. a 11:30 a.m.
A13: Elaboración Cervecería del Valle | B13: 1037776478 | C13: Maria José Oquendo Chavarría | D13: mariajoquendoch@gmail.com | E13: 300 4788939 | F13: Ingeniería Biológica | G13: 21 de octubre de 2026 | H13: 7:30 a.m. a 11:30 a.m.
A14: Elaboración Cervecería del Valle | B14: 1062275043 | C14: Maria Jose Calambas Casamachin | D14: mariajoseav52@gmail.com | E14: 310 4233492 | F14: Ingeniería de Alimentos | G14: 21 de octubre de 2026 | H14: 7:30 a.m. a 11:30 a.m.
A15: Elaboración Cervecería del Valle | B15: 1105363099 | C15: Sarah Piza Prada | D15: sarahlizethpizaprada@gmail.com | E15: 321 2048843 | F15: Ingeniería Química | G15: 21 de octubre de 2026 | H15: 7:30 a.m. a 11:30 a.m.
A16: Elaboración Cervecería del Valle | B16: 1105368091 | C16: Daniel Stiven Salinas Castillo | D16: salinas.daniel1206@gmail.com | E16: 320 7618708 | F16: Tecnología en electrónica industrial | G16: 21 de octubre de 2026 | H16: 7:30 a.m. a 11:30 a.m.
A17: Elaboración Cervecería del Valle | B17: 1105369065 | C17: Manuel Alejandro Cortés Parra | D17: alejo.cparra12@gmail.com | E17: 301 2449988 | F17: Ingeniería Industrial | G17: 21 de octubre de 2026 | H17: 7:30 a.m. a 11:30 a.m.
A18: Elaboración Cervecería del Valle | B18: 1107042882 | C18: Laura Tatiana Torres Trujillo | D18: laura.tatiana.torres@correounivalle.edu.co | E18: 315 4901789 | F18: Ingeniería Industrial | G18: 21 de octubre de 2026 | H18: 7:30 a.m. a 11:30 a.m.
... A38: Talento Cervecería del Valle | B38: 1112618688 | C38: Julian Esteban Betancourt Ocampo | D38: julianestebanbetancourt@gmail.com | E38: 317 3309191 | F38: Ingeniería Industrial | G38: 21 de octubre de 2026 | H38: 7:30 a.m. a 11:30 a.m.

Sheet C.MEDELLÍN
A1: Candidatos confirmados a la Creatón — Cervecería de Medellín
A3: Site | B3: Cervecería de Medellín
A4: Confirmación | B4: SI
A6: Vacante | B6: Cédula | C6: Nombre del candidato | D6: Correo | E6: Teléfono contacto | F6: Carrera | G6: Fecha creatón | H6: Horario creatón
A7: Elaboración Cervecería de Medellín | B7: 1029981862 | C7: Maria Paula Diaz Martinez | D7: mdiazmar@unal.edu.co | E7: 322 8949260 | F7: Ingeniería Industrial | G7: Por confirmar | H7: Por confirmar

Sheet R.ANDES
A1: Candidatos confirmados a la Creatón — Regional Andes
A3: Site | B3: Regional Andes
A4: Confirmación | B4: SI
A6: Vacante | B6: Cédula | C6: Nombre del candidato | D6: Correo | E6: Teléfono contacto | F6: Carrera | G6: Fecha creatón | H6: Horario creatón
A7: Logística T2 Regional Andes | B7: 1023523325 | C7: María Fernanda Bedoya Escobar | D7: mbedoya87@unilasallista.edu.co | E7: 321 8212815 | F7: Administración de Empresas | G7: 23 de octubre de 2026 | H7: 8:30 a.m. a 12:00 p.m.
A8: Logística T2 Regional Andes | B8: 1023523538 | C8: Yesica Alejandra Gallo Botero | D8: yesica.gallo1@udea.edu.co | E8: 310 8795621 | F8: Administración de Empresas | G8: 23 de octubre de 2026 | H8: 8:30 a.m. a 12:00 p.m.
A9: Logística T2 Regional Andes | B9: 1025880974 | C9: Manuela Lopera Monsalve | D9: manulopera2013@gmail.com | E9: 321 6544399 | F9: Administración de Empresas | G9: 23 de octubre de 2026 | H9: 8:30 a.m. a 12:00 p.m.
A10: Logística T2 Regional Andes | B10: 1034987448 | C10: Juan José Zapata | D10: jjzv2004@gmail.com | E10: 321 5798177 | F10: Negocios Internacionales | G10: 23 de octubre de 2026 | H10: 8:30 a.m. a 12:00 p.m.
A11: Logística T2 Regional Andes | B11: 1037670821 | C11: Jhon Sebastian Giraldo Pineda | D11: sebasgiraldo001@gmail.com | E11: 3113598719 | F11: Negocios Internacionales | G11: 23 de octubre de 2026 | H11: 8:30 a.m. a 12:00 p.m.
A12: Logística T2 Regional Andes | B12: 1068417699 | C12: Daniel Payares | D12: payaresdaniel20@gmail.com | E12: 319 3885124 | F12: Ingeniería Industrial | G12: 23 de octubre de 2026 | H12: 8:30 a.m. a 12:00 p.m.
A13: Logística T2 Regional Andes | B13: 1125781473 | C13: Mariana Alzate Gil | D13: marianalzate06@gmail.com | E13: 321 7538047 | F13: Negocios Internacionales | G13: 23 de octubre de 2026 | H13: 8:30 a.m. a 12:00 p.m.
A14: Ventas (gestión de ejecución premium) Regional Andes | B14: 1001095936 | C14: Daniel Felipe Hincapié López | D14: danielhincapie888@gmail.com | E14: 323 2175901 | F14: Ingeniería Industrial | G14: 23 de octubre de 2026 | H14: 8:30 a.m. a 12:00 p.m.
A15: Ventas (gestión de ejecución premium) Regional Andes | B15: 1011510808 | C15: Jennifer Giraldo | D15: jennifergiraldojaramillo@gmail.com | E15: 322 5903956 | F15: Ingeniería Administrativa | G15: 23 de octubre de 2026 | H15: 8:30 a.m. a 12:00 p.m.
A16: Ventas (gestión de ejecución premium) Regional Andes | B16: 1013457902 | C16: María José Monsalve Gómez | D16: majomonsalvegomez@gmail.com | E16: 321 8334820 | F16: Marketing / Mercadeo | G16: 23 de octubre de 2026 | H16: 8:30 a.m. a 12:00 p.m.
A17: Ventas (gestión de ejecución premium) Regional Andes | B17: 1018232610 | C17: Mariam Camila Orrego Jiménez | D17: mariam.orrego@upb.edu.co | E17: 3194401899 | F17: Negocios Internacionales | G17: 23 de octubre de 2026 | H17: 8:30 a.m. a 12:00 p.m.
A18: Ventas (gestión de ejecución premium) Regional Andes | B18: 1027740396 | C18: Sofía Echeverri Ríos | D18: sofiaecheverri5324@gmail.com | E18: 305 3059203 | F18: Negocios Internacionales | G18: 23 de octubre de 2026 | H18: 8:30 a.m. a 12:00 p.m.
... A23: Ventas (gestión de ejecución premium) Regional Andes | B23: 1105361230 | C23: Hallison Daniela Amaya Lopez | D23: hallisondaniela@gmail.com | E23: 3137503885 | F23: Marketing / Mercadeo | G23: 23 de octubre de 2026 | H23: 8:30 a.m. a 12:00 p.m.

Sheet C.ATLÁNTICO
A1: Candidatos confirmados a la Creatón — Cervecería de Atlántico
A3: Site | B3: Cervecería de Atlántico
A4: Confirmación | B4: SI
A6: Vacante | B6: Cédula | C6: Nombre del candidato | D6: Correo | E6: Teléfono contacto | F6: Carrera | G6: Fecha creatón | H6: Horario creatón
A7: Producción (operaciones) Atlantico Envase | B7: 1004368328 | C7: Jesus David Mora Ramirez | D7: danidavid338@gmail.com | E7: 3007316702 | F7: Ingeniería Industrial | G7: 23 de octubre de 2026 | H7: 8:30 a.m. a 12:00 p.m.
A8: Producción (operaciones) Atlantico Envase | B8: 1042241995 | C8: Juan David Miranda Centeno | D8: mirandajuandavid0710@gmail.com | E8: 300 4327190 | F8: Ingeniería Industrial | G8: 23 de octubre de 2026 | H8: 8:30 a.m. a 12:00 p.m.
A9: Producción (operaciones) Atlantico Envase | B9: 1043665142 | C9: Valeria Andrea González Castaño | D9: vacastano@uninorte.edu.co | E9: 305 4050713 | F9: Ingeniería Mecánica | G9: 23 de octubre de 2026 | H9: 8:30 a.m. a 12:00 p.m.
A10: Producción (operaciones) Atlantico Envase | B10: 1044210202 | C10: cinthya de alba | D10: dealba447cp@gmail.com | E10: 304 5469960 | F10: Ingeniería Industrial | G10: 23 de octubre de 2026 | H10: 8:30 a.m. a 12:00 p.m.
A11: Producción (operaciones) Atlantico Envase | B11: 1082470342 | C11: orlan Barraza tinoco | D11: obarrazatinoco12@gmail.com | E11: 310 8218310 | F11: Ingeniería Electrónica | G11: 23 de octubre de 2026 | H11: 8:30 a.m. a 12:00 p.m.
A12: Producción (operaciones) Atlantico Envase | B12: 1107836866 | C12: Valeria Paz Arrieta | D12: valeriapazarrieta@gmail.com | E12: 3105274860 | F12: Ingeniería Industrial | G12: 23 de octubre de 2026 | H12: 8:30 a.m. a 12:00 p.m.
A13: Producción (operaciones) Atlantico Envase | B13: 1129506759 | C13: Jahaira Guzmán Visbal | D13: jahairavisbal@gmail.com | E13: 311 6124925 | F13: Ingeniería Industrial | G13: 23 de octubre de 2026 | H13: 8:30 a.m. a 12:00 p.m.
A14: Producción (operaciones) Atlantico Envase | B14: 1141320197 | C14: Sebastian Meriño Cantillo | D14: sebastian.merinoc06@gmail.com | E14: 304 2752561 | F14: ANALISIS Y DESARROLLO DE SOFTWARE | G14: 23 de octubre de 2026 | H14: 8:30 a.m. a 12:00 p.m.
A15: Producción (operaciones) Atlantico Gestión | B15: 1004501029 | C15: Mauricio Argumedo Soto | D15: argumedosoto31@gmail.com | E15: 3157085604 | F15: Ingeniería Industrial | G15: 23 de octubre de 2026 | H15: 8:30 a.m. a 12:00 p.m.
A16: Producción (operaciones) Atlantico Gestión | B16: 1043665416 | C16: ALAN JOSUE CABRALES MEJIA | D16: jacke8015@gmail.com | E16: 300 8603362 | F16: Ingeniería Industrial | G16: 23 de octubre de 2026 | H16: 8:30 a.m. a 12:00 p.m.
A17: Producción (operaciones) Atlantico Gestión | B17: 1043673339 | C17: Yuliana Miranda | D17: yulianamirandasehuanes@gmail.com | E17: 324 4798404 | F17: Ingeniería Industrial | G17: 23 de octubre de 2026 | H17: 8:30 a.m. a 12:00 p.m.
A18: Producción (operaciones) Atlantico Gestión | B18: 1045166605 | C18: Julio Bolivar | D18: juliobolivar1094@gmail.com | E18: 304 4555434 | F18: Contaduría Pública | G18: 23 de octubre de 2026 | H18: 8:30 a.m. a 12:00 p.m.
... A22: Producción (operaciones) Atlantico Gestión | B22: 1140906335 | C22: carlos mateo | D22: carlosmateo2209@gmail.com | E22: 300 1303873 | F22: Logística | G22: 23 de octubre de 2026 | H22: 8:30 a.m. a 12:00 p.m.

Sheet C.BARRANQUILLA
A1: Candidatos confirmados a la Creatón — Cervecería de Barranquilla
A3: Site | B3: Cervecería de Barranquilla
A4: Confirmación | B4: SI
A6: Vacante | B6: Cédula | C6: Nombre del candidato | D6: Correo | E6: Teléfono contacto | F6: Carrera | G6: Fecha creatón | H6: Horario creatón
A7: Brewing & Quality Cervecería de Barranquilla | B7: 1007764065 | C7: Mayerlis Peluffo Mendoza | D7: danzapeluffo@gmail.com | E7: 312 6172663 | F7: Ingeniería Química | G7: 22 de octubre de 2026 | H7: 12:30 p.m. a 5:00 p.m.
A8: Brewing & Quality Cervecería de Barranquilla | B8: 1010151670 | C8: LAURA DANIELA GUERRERO RAMOS | D8: danielaguerrero270@gmail.com | E8: 316 2503458 | F8: Microbiología | G8: 22 de octubre de 2026 | H8: 12:30 p.m. a 5:00 p.m.
A9: Brewing & Quality Cervecería de Barranquilla | B9: 1041970241 | C9: Danilo Alexander Carballo Jabba | D9: danilocarballo53@gmail.com | F9: Ingeniería de Alimentos | G9: 22 de octubre de 2026 | H9: 12:30 p.m. a 5:00 p.m.
A10: Brewing & Quality Cervecería de Barranquilla | B10: 1042244929 | C10: Liseth Barrios Guzman | D10: plbarrios@uninorte.edu.co | E10: 300 7536860 | F10: Ingeniería Industrial | G10: 22 de octubre de 2026 | H10: 12:30 p.m. a 5:00 p.m.
A11: Brewing & Quality Cervecería de Barranquilla | B11: 1045226956 | C11: MARIA CAROLINA ZAPATA ROA | D11: mcarolinazapata@mail.uniatlantico.edu.co | E11: 300 1246603 | F11: Ingeniería Química | G11: 22 de octubre de 2026 | H11: 12:30 p.m. a 5:00 p.m.
A12: Brewing & Quality Cervecería de Barranquilla | B12: 1048264316 | C12: LAURA VALENTINA SANDOVAL ORTIZ | D12: sandovalortizlauravalentina@gmail.com | E12: 324 2183271 | F12: Ingeniería Química | G12: 22 de octubre de 2026 | H12: 12:30 p.m. a 5:00 p.m.
A13: Brewing & Quality Cervecería de Barranquilla | B13: 1048264627 | C13: KAROL DE BARROS PADILLA | D13: kayrol2810@gmail.com | E13: 3004451226 | F13: Ingeniería Química | G13: 22 de octubre de 2026 | H13: 12:30 p.m. a 5:00 p.m.
A14: Brewing & Quality Cervecería de Barranquilla | B14: 1048434816 | C14: Laura Alvarado Zapata | D14: lauraalvaradozp04@gmail.com | E14: 314 5227092 | F14: Ingeniería Industrial | G14: 22 de octubre de 2026 | H14: 12:30 p.m. a 5:00 p.m.
A15: Brewing & Quality Cervecería de Barranquilla | B15: 1048434954 | C15: Johan Miguel Granados Hidalgo | D15: johanmiguel.jmgh@gmail.com | E15: 3012298941 | F15: Ingeniería Química | G15: 22 de octubre de 2026 | H15: 12:30 p.m. a 5:00 p.m.
A16: Brewing & Quality Cervecería de Barranquilla | B16: 1052946093 | C16: Nataly Alvarez Menco | D16: nalvarezmenco1119@gmail.com | E16: 3205739128 | F16: Ingeniería Química | G16: 22 de octubre de 2026 | H16: 12:30 p.m. a 5:00 p.m.
A17: Envase Cervecería de Barranquilla | B17: 1001825014 | C17: Mateo Marin | D17: matemarinm@gmail.com | E17: 3028404613 | F17: Ingeniería Industrial | G17: 22 de octubre de 2026 | H17: 12:30 p.m. a 5:00 p.m.
A18: Envase Cervecería de Barranquilla | B18: 1002163133 | C18: Angel Zuñiga Robles | D18: zuniga.angel0802@gmail.com | E18: 300 2916918 | F18: Ingeniería Mecánica | G18: 22 de octubre de 2026 | H18: 12:30 p.m. a 5:00 p.m.
A19: Envase Cervecería de Barranquilla | B19: 1002163280 | C19: Stefany Oporto Alvarez | D19: stefanyoporto@gmail.com | E19: 3137286283 | F19: Ingeniería Mecánica | G19: 22 de octubre de 2026 | H19: 12:30 p.m. a 5:00 p.m.
A20: Envase Cervecería de Barranquilla | B20: 1042242843 | C20: Carlos Andres De Avila Espinosa | D20: carlosada567@gmail.com | E20: 302 8476293 | F20: Ingeniería Mecánica | G20: 22 de octubre de 2026 | H20: 12:30 p.m. a 5:00 p.m.
A21: Envase Cervecería de Barranquilla | B21: 1042247753 | C21: Ana Jiménez | D21: an20-13@hotmail.com | E21: 3002713372 | F21: Ingeniería Industrial | G21: 22 de octubre de 2026 | H21: 12:30 p.m. a 5:00 p.m.
... A46: Talento Supply Cervecería de Barranquilla | B46: 1129539518 | C46: Andres Felipe Quiroz Borja | D46: afqb0108@gmail.com | E46: 301 5176294 | F46: Administración de Empresas | G46: 22 de octubre de 2026 | H46: 12:30 p.m. a 5:00 p.m.

Sheet R.NORTE
A1: Candidatos confirmados a la Creatón — Regional Norte
A3: Site | B3: Regional Norte
A4: Confirmación | B4: SI
A6: Vacante | B6: Cédula | C6: Nombre del candidato | D6: Correo | E6: Teléfono contacto | F6: Carrera | G6: Fecha creatón | H6: Horario creatón
A7: Talento Ventas Regional Norte | B7: 1000951426 | C7: Juan David Porto Léon | D7: jporto0804@gmail.com | E7: 321 8076611 | F7: Administración de Empresas | G7: 22 de octubre de 2026 | H7: 1:30 p.m. a 5:00 p.m.
A8: Talento Ventas Regional Norte | B8: 1042243295 | C8: ANDRES FELIPE ACOSTA GUTIERREZ | D8: faandres@uninorte.edu.co | E8: 301 3969374 | F8: Negocios Internacionales | G8: 22 de octubre de 2026 | H8: 1:30 p.m. a 5:00 p.m.
A9: Talento Ventas Regional Norte | B9: 1043652925 | C9: Nicolle Carolina Rodriguez Blanquicett | D9: nicollerodriguezblanquicett@gmail.com | E9: 302 4118837 | F9: Negocios Internacionales | G9: 22 de octubre de 2026 | H9: 1:30 p.m. a 5:00 p.m.
A10: Talento Ventas Regional Norte | B10: 1065588728 | C10: Isabella Betancur Lopez | D10: isabella.betancur@urosario.edu.co | E10: 3184636614 | F10: Negocios Internacionales | G10: 22 de octubre de 2026 | H10: 1:30 p.m. a 5:00 p.m.
A11: Talento Ventas Regional Norte | B11: 1082856658 | C11: Jhosep Olivera Gaviria | D11: jhosepoliveragaviria@gmail.com | E11: 314 7902917 | F11: Negocios Internacionales | G11: 22 de octubre de 2026 | H11: 1:30 p.m. a 5:00 p.m.
A12: Talento Ventas Regional Norte | B12: 1082873539 | C12: Adriana Maria Sierra Cabrera | D12: adrianita.sc03@gmail.com | E12: 3176940867 | F12: Ingeniería Industrial | G12: 22 de octubre de 2026 | H12: 1:30 p.m. a 5:00 p.m.

Sheet C.BOYACÁ
A1: Candidatos confirmados a la Creatón — Cervecería de Boyacá
A3: Site | B3: Cervecería de Boyacá
A4: Confirmación | B4: (Varios elementos)
A6: Vacante | B6: Cédula | C6: Nombre del candidato | D6: Correo | E6: Teléfono contacto | F6: Carrera | G6: Fecha creatón | H6: Horario creatón
A7: Elaboración Boyacá Cervecería de Boyacá | B7: 1002455397 | C7: Luisa Yuliana Carreño Pérez | D7: luisacarreno3012@gmail.com | E7: 320 8367712 | F7: Ingeniería Química | G7: 20 de octubre de 2026 | H7: 7:30 a.m. a 12:00 p.m.
A8: Elaboración Boyacá Cervecería de Boyacá | B8: 1006554579 | C8: Leonart Rincon | D8: leonardrincon18@gmail.com | E8: 3205909541 | F8: Ingeniería Industrial | G8: 20 de octubre de 2026 | H8: 7:30 a.m. a 12:00 p.m.
A9: Elaboración Boyacá Cervecería de Boyacá | B9: 1006734815 | C9: Javier Alfonso Muñoz Guette | D9: javiestudio2142@gmail.com | E9: 3112388229 | F9: Ingeniería Industrial | G9: 20 de octubre de 2026 | H9: 7:30 a.m. a 12:00 p.m.
A10: Elaboración Boyacá Cervecería de Boyacá | B10: 1052381342 | C10: Astrid Juliana Fajardo Vargas | D10: astridfajardovargas@gmail.com | E10: 311 8242698 | F10: Ingeniería Industrial | G10: 20 de octubre de 2026 | H10: 7:30 a.m. a 12:00 p.m.
A11: Elaboración Boyacá Cervecería de Boyacá | B11: 1053442581 | C11: Loren Daniela Duarte Colmenares | D11: lorensofi2010@hotmail.com | E11: 321 7866399 | F11: Ingeniería Industrial | G11: 20 de octubre de 2026 | H11: 7:30 a.m. a 12:00 p.m.
A12: Elaboración Boyacá Cervecería de Boyacá | B12: 1056798003 | C12: Juan sebastian Gil Rodriguez | D12: juansebastiangilrodriguez11@gmail.com | E12: 3186987976 | F12: Ingeniería Industrial | G12: 20 de octubre de 2026 | H12: 7:30 a.m. a 12:00 p.m.
A13: Elaboración Boyacá Cervecería de Boyacá | B13: 1057570417 | C13: Diego Andres Perez Rodriguez | D13: diegoandresp275@gmail.com | E13: 3202806780 | F13: Ingeniería Electrónica | G13: 20 de octubre de 2026 | H13: 7:30 a.m. a 12:00 p.m.
A14: Elaboración Boyacá Cervecería de Boyacá | B14: 1118533053 | C14: Karen Eliana Ortiz Caicedo | D14: ortizeliana2004@gmail.com | E14: 3154190320 | F14: Ingeniería Química | G14: 20 de octubre de 2026 | H14: 7:30 a.m. a 12:00 p.m.
A15: Elaboración Boyacá Cervecería de Boyacá | B15: (en blanco) | C15: Ean Bryan Alexandre Ladino Pérez | D15: ebladino@uniboyaca.edu.co | E15: 313 4266421 | F15: Ingeniería Ambiental | G15: 20 de octubre de 2026 | H15: 7:30 a.m. a 12:00 p.m.
A16: Elaboración Boyacá Cervecería de Boyacá | B16: 1050090351 | C16: KAREN NATALIA ROJAS CASTILLO | D16: nataliarojascastillo2325@gmail.com | E16: 310 8803925 | F16: Ingeniería Ambiental | G16: 20 de octubre de 2026 | H16: 7:30 a.m. a 12:00 p.m.
A17: Talento Cervecería de Boyacá | B17: 1002459278 | C17: Catalina Gallego | D17: tatamc9515@gmail.com | E17: 3105595063 | F17: DISEÑO INDUSTRIAL | G17: 20 de octubre de 2026 | H17: 7:30 a.m. a 12:00 p.m.
A18: Talento Cervecería de Boyacá | B18: 1002559370 | C18: Juan Sebastian Castro Aguirre | D18: est.juan.scastro@unimilitar.edu.co | E18: 312 3264153 | F18: Seguridad y Salud en el Trabajo | G18: 20 de octubre de 2026 | H18: 7:30 a.m. a 12:00 p.m.
A19: Talento Cervecería de Boyacá | B19: 1002697466 | C19: Nicolas Torres Carreño | D19: nicolastorres5h6@gmail.com | E19: 321 2038347 | F19: Ingeniería Industrial | G19: 20 de octubre de 2026 | H19: 7:30 a.m. a 12:00 p.m.
A20: Talento Cervecería de Boyacá | B20: 1057214413 | C20: Lizeth Mariana Sánchez Forero | D20: liz24022006@gmail.com | E20: 313 4401989 | F20: Comunicación social | G20: 20 de octubre de 2026 | H20: 7:30 a.m. a 12:00 p.m.
A21: Talento Cervecería de Boyacá | B21: 1057978536 | C21: Laura valentina Velandia Camargo | D21: lauravalentinavelandiacamargo@gmail.com | E21: 3125891400 | F21: Comunicación social | G21: 20 de octubre de 2026 | H21: 7:30 a.m. a 12:00 p.m.
A22: Talento Cervecería de Boyacá | B22: (en blanco) | C22: Karen Juliana Vela Cárdenas | D22: karenvela1001@gmail.com | E22: 314 2225915 | F22: Comunicación social | G22: 20 de octubre de 2026 | H22: 7:30 a.m. a 12:00 p.m.
A23: Talento Cervecería de Boyacá | B23: (en blanco) | C23: Luis Carlos Blanco León | D23: blancoleonl63@gmail.com | E23: 320 3456294 | F23: Comunicación social | G23: 20 de octubre de 2026 | H23: 7:30 a.m. a 12:00 p.m.

Sheet R.SUR
A1: Candidatos confirmados a la Creatón — Regional Sur
A3: Site | B3: Regional Sur
A4: Confirmación | B4: SI
A6: Vacante | B6: Cédula | C6: Nombre del candidato | D6: Correo | E6: Teléfono contacto | F6: Carrera | G6: Fecha creatón | H6: Horario creatón
A7: Talento Regional Sur | B7: 1084331089 | C7: ISABELLA DIAZ | D7: isis.diazc07@gmail.com | E7: 3124247820 | F7: Comunicación social | G7: 22 de octubre de 2026 | H7: 8:30 a.m. a 12:00 p.m.
A8: Talento Regional Sur | B8: 1086754228 | C8: JESÚS ANDRÉS BENAVIDES FREIRE | D8: andresbenavidezj@gmail.com | E8: 316 5372511 | F8: Administración de Empresas | G8: 22 de octubre de 2026 | H8: 8:30 a.m. a 12:00 p.m.
A9: Talento Regional Sur | B9: 1098609475 | C9: Daniela Gutierrez de Piñerez Maiguel | D9: daniela.maiguel@correounivalle.edu.co | E9: 316 4963071 | F9: Ingeniería Industrial | G9: 22 de octubre de 2026 | H9: 8:30 a.m. a 12:00 p.m.
A10: Talento Regional Sur | B10: 1114541627 | C10: MEILYN YINETH CARDONA CANAVAL | D10: cardonameilyn91@gmail.com | E10: 318 4111789 | F10: Administración de Empresas | G10: 22 de octubre de 2026 | H10: 8:30 a.m. a 12:00 p.m.
A11: Talento Regional Sur | B11: 1193290817 | C11: Valeria Arroyave Grisales | D11: valeriaagall@gmail.com | E11: 317 2129349 | F11: Comercio Internacional | G11: 22 de octubre de 2026 | H11: 8:30 a.m. a 12:00 p.m.
A12: Ventas Regional Sur | B12: 1002965497 | C12: Luisa Viviana Alegria Jojoa | D12: luisaalegria390@gmail.com | E12: 3218878289 | F12: Administración de Empresas | G12: 22 de octubre de 2026 | H12: 8:30 a.m. a 12:00 p.m.
A13: Ventas Regional Sur | B13: 1006016564 | C13: Veronica Mejia Raquejo | D13: veronikamejia95@gmail.com | E13: 318 2468842 | F13: Marketing / Mercadeo | G13: 22 de octubre de 2026 | H13: 8:30 a.m. a 12:00 p.m.
A14: Ventas Regional Sur | B14: 1006493201 | C14: Yeraldin Umaña | D14: geral125.u@gmail.com | E14: 3106231132 | F14: Comercio Internacional | G14: 22 de octubre de 2026 | H14: 8:30 a.m. a 12:00 p.m.
A15: Ventas Regional Sur | B15: 1010960473 | C15: David Santiago Suárez Rodríguez | D15: davidrodriguez081@hotmail.com | E15: 318 6029672 | F15: Administración de Empresas | G15: 22 de octubre de 2026 | H15: 8:30 a.m. a 12:00 p.m.
A16: Ventas Regional Sur | B16: 1105364869 | C16: Luisa Fernanda Bravo Otero | D16: bravooteroluisafernanda@gmail.com | E16: 311 3233801 | F16: Comercio Exterior | G16: 22 de octubre de 2026 | H16: 8:30 a.m. a 12:00 p.m.
A17: Ventas Regional Sur | B17: 1105365016 | C17: Mariana Freire Baltan | D17: marianafbaltan@gmail.com | E17: 300 2439716 | F17: Marketing / Mercadeo | G17: 22 de octubre de 2026 | H17: 8:30 a.m. a 12:00 p.m.
A18: Ventas Regional Sur | B18: 1105928637 | C18: Nicolás Barbosa Fernández | D18: nicolasbarfer@gmail.com | F18: Economía | G18: 22 de octubre de 2026 | H18: 8:30 a.m. a 12:00 p.m.
A19: Ventas Regional Sur | B19: 1109185610 | C19: Ana María Gualtero Rios | D19: ana.gualtero@u.icesi.edu.co | E19: 314 3490138 | F19: Administración de Empresas | G19: 22 de octubre de 2026 | H19: 8:30 a.m. a 12:00 p.m.

Sheet C.BUCARAMANGA
A1: Candidatos confirmados a la Creatón — Cervecería de Bucaramanga
A3: Site | B3: Cervecería de Bucaramanga
A4: Confirmación | B4: SI
A6: Vacante | B6: Cédula | C6: Nombre del candidato | D6: Correo | E6: Teléfono contacto | F6: Carrera | G6: Fecha creatón | H6: Horario creatón
A7: Producción (operaciones) Bucaramanga | B7: 1002528206 | C7: Julieth Ximena Albarran Vargas | D7: albarranximena00@gmail.com | E7: 3152069944 | F7: Ingeniería Química | G7: 21 de octubre de 2026 | H7: 7:30 a.m. a 12:00 p.m.
A8: Producción (operaciones) Bucaramanga | B8: 1004795078 | C8: Daniel Andres Ruiz Sandoval | D8: danielandresruizsandoval@gmail.com | E8: 320 2359161 | F8: Ingeniería Mecánica | G8: 21 de octubre de 2026 | H8: 7:30 a.m. a 12:00 p.m.
A9: Producción (operaciones) Bucaramanga | B9: 1005260233 | C9: Katherine Nicolle Sarmiento Coy | D9: katherine.sarmiento.coy@gmail.com | E9: 3156201141 | F9: Ingeniería Química | G9: 21 de octubre de 2026 | H9: 7:30 a.m. a 12:00 p.m.
A10: Producción (operaciones) Bucaramanga | B10: 1005334499 | C10: German David Villamizar Nova | D10: gerdavidvn20@gmail.com | E10: 3142093772 | F10: Ingeniería Industrial | G10: 21 de octubre de 2026 | H10: 7:30 a.m. a 12:00 p.m.
A11: Producción (operaciones) Bucaramanga | B11: 1085037242 | C11: Camilo Di Zeo Oliveros | D11: dizeocamilo@gmail.com | E11: 310 5361024 | F11: Ingeniería Industrial | G11: 21 de octubre de 2026 | H11: 7:30 a.m. a 12:00 p.m.
A12: Producción (operaciones) Bucaramanga | B12: 1096800652 | C12: Andrés Polo | D12: andrespolo151@gmail.com | E12: 3208719059 | F12: Ingeniería Mecatrónica | G12: 21 de octubre de 2026 | H12: 7:30 a.m. a 12:00 p.m.
A13: Producción (operaciones) Bucaramanga | B13: 1097093780 | C13: Emily Smith Quiceno Guerrero | D13: emilyquicenoguerrero@gmail.com | E13: 318 8620569 | F13: Ingeniería Mecánica | G13: 21 de octubre de 2026 | H13: 7:30 a.m. a 12:00 p.m.
A14: Producción (operaciones) Bucaramanga | B14: 1097094457 | C14: Samuel David Hurtado Jaimes | D14: hurtadojaimessamuel@gmail.com | E14: 300 2085133 | F14: Ingeniería Mecánica | G14: 21 de octubre de 2026 | H14: 7:30 a.m. a 12:00 p.m.
A15: Producción (operaciones) Bucaramanga | B15: 1098612128 | C15: Connie Alexandra Gelvez Mojica | D15: gelvezconnie@gmail.com | E15: 301 7990303 | F15: Ingeniería Mecánica | G15: 21 de octubre de 2026 | H15: 7:30 a.m. a 12:00 p.m.
A16: Producción (operaciones) Bucaramanga | B16: 1130266716 | C16: Diego Fernando Prada romero | D16: dfernandx@gmail.com | E16: 3009477921 | F16: Ingeniería Mecánica | G16: 21 de octubre de 2026 | H16: 7:30 a.m. a 12:00 p.m.
A17: Talento Supply Bucaramanga | B17: 1004898829 | C17: María torrado | D17: macama3456@gmail.com | E17: 318 8023106 | F17: Ingeniería Industrial | G17: 21 de octubre de 2026 | H17: 7:30 a.m. a 12:00 p.m.
A18: Talento Supply Bucaramanga | B18: 1005479785 | C18: LAURA NATALIA SALAZAR TORRES | D18: lsalazar14@udi.edu.co | E18: 3105656315 | F18: Administración de Empresas | G18: 21 de octubre de 2026 | H18: 7:30 a.m. a 12:00 p.m.
... A21: Talento Supply Bucaramanga | B21: 1193553981 | C21: Trino García Martelo | D21: trinogarcia2002@outlook.com | E21: 310 5919408 | F21: Administración de Empresas | G21: 21 de octubre de 2026 | H21: 7:30 a.m. a 12:00 p.m.

Sheet C.TOCANCIPÁ
A1: Candidatos confirmados a la Creatón — Cervecería de Tocancipá
A3: Site | B3: Cervecería de Tocancipá
A4: Confirmación | B4: SI
A6: Vacante | B6: Cédula | C6: Nombre del candidato | D6: Correo | E6: Teléfono contacto | F6: Carrera | G6: Fecha creatón | H6: Horario creatón
A7: Calidad Cervecería de Tocancipá | B7: 1000159919 | C7: Tatiana Aguilera | D7: tatisagui.0318@gmail.com | E7: 310 6843734 | F7: Ingeniería Ambiental | G7: 27 de octubre de 2026 | H7: 12:30 p.m. a 4:00 p.m.
A8: Calidad Cervecería de Tocancipá | B8: 1000698418 | C8: Emily Oppenheim Chiriboga | D8: emmioppen@gmail.com | E8: 3112717077 | F8: Ingeniería Química | G8: 27 de octubre de 2026 | H8: 12:30 p.m. a 4:00 p.m.
A9: Calidad Cervecería de Tocancipá | B9: 1003908604 | C9: Leidy Juliana Jaramillo Monroy | D9: cjjaramillod_3@hotmail.com | E9: 316 3164613 | F9: Química | G9: 27 de octubre de 2026 | H9: 12:30 p.m. a 4:00 p.m.
A10: Calidad Cervecería de Tocancipá | B10: 1005849189 | C10: Laura Michell Ñustes Ortiz | D10: lauritamich15@gmail.com | E10: 304 4262137 | F10: Ingeniería Química | G10: 27 de octubre de 2026 | H10: 12:30 p.m. a 4:00 p.m.
A11: Calidad Cervecería de Tocancipá | B11: 1031806915 | C11: Liseth Dayana Fajardo Mejia | D11: dayafame26@gmail.com | E11: 312 5091792 | F11: Química | G11: 27 de octubre de 2026 | H11: 12:30 p.m. a 4:00 p.m.
A12: Calidad Cervecería de Tocancipá | B12: 1034276263 | C12: Juana Camila Camacho Murcia | D12: jucamu26@gmail.com | E12: 324 3928424 | F12: Ingeniería Química | G12: 27 de octubre de 2026 | H12: 12:30 p.m. a 4:00 p.m.
A13: Calidad Cervecería de Tocancipá | B13: 1054543116 | C13: Juan David Salgado Hernandez | D13: juan.salgado1@utp.edu.co | E13: 301 6260541 | F13: Ingeniería de manufactura | G13: 27 de octubre de 2026 | H13: 12:30 p.m. a 4:00 p.m.
A14: Calidad Cervecería de Tocancipá | B14: 1097783237 | C14: Karen Mosquera | D14: mosquerakarenksmh@gmail.com | E14: 315 6794059 | F14: Ingeniería Química | G14: 27 de octubre de 2026 | H14: 12:30 p.m. a 4:00 p.m.
A15: Calidad Cervecería de Tocancipá | B15: 1116612016 | C15: Danna Sofia Chaparro Barrera | D15: dachaparrob@unal.edu.co | E15: 310 3244082 | F15: Ingeniería Química | G15: 27 de octubre de 2026 | H15: 12:30 p.m. a 4:00 p.m.
A16: Elaboración Cervecería de Tocancipá | B16: 1003565150 | C16: Angel Camilo Suta Rueda | D16: angelcamilo2703@gmail.com | E16: 3147560352 | F16: Ingeniería Ambiental | G16: 27 de octubre de 2026 | H16: 12:30 p.m. a 4:00 p.m.
A17: Elaboración Cervecería de Tocancipá | B17: 1011081594 | C17: Paula Vanessa Manrique Camacho | D17: paulamaanrique052@hotmail.com | E17: 3046547913 | F17: Ingeniería Química | G17: 27 de octubre de 2026 | H17: 12:30 p.m. a 4:00 p.m.
A18: Elaboración Cervecería de Tocancipá | B18: 1050604600 | C18: PAULA ANDREA LAVERDE TIPAZOCA | D18: andreatipazoca5@gmail.com | E18: 317 5933601 | F18: Negocios Internacionales | G18: 27 de octubre de 2026 | H18: 12:30 p.m. a 4:00 p.m.
... A39: Talento Supply Cervecería de Tocancipá | B39: 1091965068 | C39: DEYSA IVETH PORRAS FORERO | D39: deysaivethporrasforero27@gmail.com | E39: 3102549573 | F39: Ingeniería Industrial | G39: 27 de octubre de 2026 | H39: 12:30 p.m. a 4:00 p.m.

Sheet C.TIBITÓ
A1: Candidatos confirmados a la Creatón — Cervecería de Tibitó
A3: Site | B3: Cervecería de Tibitó
A4: Confirmación | B4: SI
A6: Vacante | B6: Cédula | C6: Nombre del candidato | D6: Correo | E6: Teléfono contacto | F6: Carrera | G6: Fecha creatón | H6: Horario creatón
A7: Producción (operaciones) Cervecería de Tibitó | B7: 1000953816 | C7: Vanessa Alejandra Angulo Alba | D7: vaneanguloalba@gmail.com | E7: 333 7505212 | F7: Administración de Empresas Agropecuarias | G7: 27 de octubre de 2026 | H7: 12:30 p.m. a 4:00 p.m.
A8: Producción (operaciones) Cervecería de Tibitó | B8: 1003912861 | C8: Jose Alexander Romero Cardenas | D8: jose231101a@gmail.com | E8: 322 2067541 | F8: Ingeniería de Sistemas | G8: 27 de octubre de 2026 | H8: 12:30 p.m. a 4:00 p.m.
A9: Producción (operaciones) Cervecería de Tibitó | B9: 1013260438 | C9: Paula Jimena Pinzón Forero | D9: paulapinzon2005@gmail.com | E9: 3143606567 | F9: Ingeniería Industrial | G9: 27 de octubre de 2026 | H9: 12:30 p.m. a 4:00 p.m.
A10: Producción (operaciones) Cervecería de Tibitó | B10: 1014738447 | C10: Joseph German Corredor Torres | D10: german05corredor@gmail.com | E10: 3192705164 | F10: Ingeniería Eléctrica | G10: 27 de octubre de 2026 | H10: 12:30 p.m. a 4:00 p.m.
A11: Producción (operaciones) Cervecería de Tibitó | B11: 1016947267 | C11: Sara Sofia Aranguren Bolívar | D11: sofiaaranguren21@gmail.com | E11: 3209135713 | F11: Ingeniería Industrial | G11: 27 de octubre de 2026 | H11: 12:30 p.m. a 4:00 p.m.
A12: Producción (operaciones) Cervecería de Tibitó | B12: 1054372023 | C12: Michael Stevent Chavarro Nope | D12: maicolestivenchavarronope3@gmail.com | E12: 314 2209452 | F12: Ingeniería de Sistemas | G12: 27 de octubre de 2026 | H12: 12:30 p.m. a 4:00 p.m.
